[
  {
    "date": "2018-05-10",
    "id": "bitcoin",
    "cap": "153988453198",
    "high": "9396.04003906",
    "low": "9040.51953125"
  },
  {
    "date": "2018-05-10",
    "id": "bitcoin-cash",
    "cap": "26170760101.5",
    "high": "1669.82995605",
    "low": "1523.56005859"
  },
  {
    "date": "2018-05-10",
    "id": "neo",
    "cap": "4561492000.0",
    "high": "76.9665985107",
    "low": "70.1768035889"
  },
  {
    "date": "2018-05-10",
    "id": "dash",
    "cap": "3397588841.46",
    "high": "460.730987549",
    "low": "420.407012939"
  },
  {
    "date": "2018-05-10",
    "id": "nem",
    "cap": "3167324999.65",
    "high": "0.382683992386",
    "low": "0.351924985647"
  },
  {
    "date": "2018-05-10",
    "id": "bytecoin-bcn",
    "cap": "2229825054.59",
    "high": "0.0142778996378",
    "low": "0.012040800415"
  },
  {
    "date": "2018-05-10",
    "id": "binance-coin",
    "cap": "1575868163.25",
    "high": "15.0455999374",
    "low": "13.818400383"
  },
  {
    "date": "2018-05-10",
    "id": "lisk",
    "cap": "1174922847.1",
    "high": "12.4490995407",
    "low": "11.1097002029"
  },
  {
    "date": "2018-05-10",
    "id": "bitcoin-gold",
    "cap": "1100569739.89",
    "high": "70.9625015259",
    "low": "64.75340271"
  },
  {
    "date": "2018-05-10",
    "id": "aeternity",
    "cap": "1030710133.48",
    "high": "4.86944007874",
    "low": "4.41071987152"
  },
  {
    "date": "2018-05-10",
    "id": "0x",
    "cap": "985504580.962",
    "high": "2.03138995171",
    "low": "1.72555994987"
  },
  {
    "date": "2018-05-10",
    "id": "bitcoin-diamond",
    "cap": "692297562.605",
    "high": "5.55772018433",
    "low": "4.50835990906"
  },
  {
    "date": "2018-05-10",
    "id": "bitcoin-private",
    "cap": "565971511.243",
    "high": "31.724899292",
    "low": "27.7035007477"
  },
  {
    "date": "2018-05-10",
    "id": "augur",
    "cap": "487084400.0",
    "high": "50.7910995483",
    "low": "44.2803993225"
  },
  {
    "date": "2018-05-10",
    "id": "loopring",
    "cap": "433007419.973",
    "high": "0.822745978832",
    "low": "0.756907999516"
  },
  {
    "date": "2018-05-10",
    "id": "aelf",
    "cap": "400132500.0",
    "high": "1.81406998634",
    "low": "1.56240999699"
  },
  {
    "date": "2018-05-10",
    "id": "aion",
    "cap": "389782748.643",
    "high": "3.33994007111",
    "low": "2.92908000946"
  },
  {
    "date": "2018-05-10",
    "id": "basic-attention-token",
    "cap": "383166000.0",
    "high": "0.394201010466",
    "low": "0.365482002497"
  },
  {
    "date": "2018-05-10",
    "id": "ardor",
    "cap": "345946532.122",
    "high": "0.370241999626",
    "low": "0.345243990421"
  },
  {
    "date": "2018-05-10",
    "id": "ark",
    "cap": "315715616.237",
    "high": "3.29524993896",
    "low": "3.07846999168"
  },
  {
    "date": "2018-05-10",
    "id": "ethos",
    "cap": "289136219.99",
    "high": "5.02201986313",
    "low": "3.77307009697"
  },
  {
    "date": "2018-05-10",
    "id": "funfair",
    "cap": "261989333.676",
    "high": "0.0588673986495",
    "low": "0.0536675006151"
  },
  {
    "date": "2018-05-10",
    "id": "substratum",
    "cap": "251864651.028",
    "high": "0.713738024235",
    "low": "0.657573997974"
  },
  {
    "date": "2018-05-10",
    "id": "bancor",
    "cap": "249600643.478",
    "high": "5.16315984726",
    "low": "4.81725978851"
  },
  {
    "date": "2018-05-10",
    "id": "gxchain",
    "cap": "245219400.0",
    "high": "4.43570995331",
    "low": "4.05329990387"
  },
  {
    "date": "2018-05-10",
    "id": "matrix-ai-network",
    "cap": "205002000.0",
    "high": "1.79014003277",
    "low": "1.3478000164"
  },
  {
    "date": "2018-05-10",
    "id": "veritaseum",
    "cap": "196860518.914",
    "high": "105.666999817",
    "low": "96.5802993774"
  },
  {
    "date": "2018-05-10",
    "id": "nexo",
    "cap": "186622243.333",
    "high": "0.427821010351",
    "low": "0.331492006779"
  },
  {
    "date": "2018-05-10",
    "id": "salt",
    "cap": "183180374.834",
    "high": "3.57249999046",
    "low": "3.11299991608"
  },
  {
    "date": "2018-05-10",
    "id": "all-sports",
    "cap": "170302690.198",
    "high": "0.282157987356",
    "low": "0.227672994137"
  },
  {
    "date": "2018-05-10",
    "id": "achain",
    "cap": "168215149.533",
    "high": "0.386541992426",
    "low": "0.351318001747"
  },
  {
    "date": "2018-05-10",
    "id": "crypto-com",
    "cap": "164296907.348",
    "high": "11.1532001495",
    "low": "10.4026002884"
  },
  {
    "date": "2018-05-10",
    "id": "maidsafecoin",
    "cap": "163242443.295",
    "high": "0.399975001812",
    "low": "0.345633000135"
  },
  {
    "date": "2018-05-10",
    "id": "nucleus-vision",
    "cap": "158016814.452",
    "high": "0.04283849895",
    "low": "0.0383339002728"
  },
  {
    "date": "2018-05-10",
    "id": "obyte",
    "cap": "157291083.88",
    "high": "264.319000244",
    "low": "243.268997192"
  },
  {
    "date": "2018-05-10",
    "id": "emercoin",
    "cap": "145413623.825",
    "high": "3.77359008789",
    "low": "3.47059011459"
  },
  {
    "date": "2018-05-10",
    "id": "bottos",
    "cap": "140411963.631",
    "high": "0.330139994621",
    "low": "0.283939003944"
  },
  {
    "date": "2018-05-10",
    "id": "storj",
    "cap": "137125045.956",
    "high": "1.13136994839",
    "low": "1.00610995293"
  },
  {
    "date": "2018-05-10",
    "id": "civic",
    "cap": "132884996.116",
    "high": "0.417962998152",
    "low": "0.387694001198"
  },
  {
    "date": "2018-05-10",
    "id": "smartcash",
    "cap": "123322193.872",
    "high": "0.140428006649",
    "low": "0.123524002731"
  },
  {
    "date": "2018-05-10",
    "id": "arcblock",
    "cap": "119657927.387",
    "high": "1.41474997997",
    "low": "1.28138995171"
  },
  {
    "date": "2018-05-10",
    "id": "aragon",
    "cap": "119049071.005",
    "high": "4.91071987152",
    "low": "4.48246002197"
  },
  {
    "date": "2018-05-10",
    "id": "enjin-coin",
    "cap": "117046505.347",
    "high": "0.161973997951",
    "low": "0.149284005165"
  },
  {
    "date": "2018-05-10",
    "id": "high-performance-blockchain",
    "cap": "110950617.285",
    "high": "3.94976997375",
    "low": "3.73537993431"
  },
  {
    "date": "2018-05-10",
    "id": "apex",
    "cap": "102303128.946",
    "high": "0.278697997332",
    "low": "0.242640003562"
  },
  {
    "date": "2018-05-10",
    "id": "dew",
    "cap": "95382996.4767",
    "high": "0.98710501194",
    "low": "0.895451009274"
  },
  {
    "date": "2018-05-10",
    "id": "asch",
    "cap": "92951009.0614",
    "high": "1.04460000992",
    "low": "0.953787982464"
  },
  {
    "date": "2018-05-10",
    "id": "iht-real-estate-protocol",
    "cap": "90221123.1484",
    "high": "0.188855007291",
    "low": "0.175185993314"
  },
  {
    "date": "2018-05-10",
    "id": "bibox-token",
    "cap": "89532096.4177",
    "high": "0.920315027237",
    "low": "0.81205201149"
  },
  {
    "date": "2018-05-10",
    "id": "amber",
    "cap": "87121123.1216",
    "high": "0.710087001324",
    "low": "0.598313987255"
  },
  {
    "date": "2018-05-10",
    "id": "bitcore",
    "cap": "86360529.1963",
    "high": "6.01304006577",
    "low": "5.548620224"
  },
  {
    "date": "2018-05-10",
    "id": "iot-chain",
    "cap": "84700396.9322",
    "high": "1.90011000633",
    "low": "1.71385002136"
  },
  {
    "date": "2018-05-10",
    "id": "red-pulse",
    "cap": "84363642.5107",
    "high": "0.117141000926",
    "low": "0.104681000113"
  },
  {
    "date": "2018-05-10",
    "id": "ethlend",
    "cap": "77552339.3813",
    "high": "0.0775630995631",
    "low": "0.0713886991143"
  },
  {
    "date": "2018-05-10",
    "id": "medibloc",
    "cap": "75108845.412",
    "high": "0.0284088999033",
    "low": "0.0253199990839"
  },
  {
    "date": "2018-05-10",
    "id": "blockv",
    "cap": "69653749.6125",
    "high": "0.0519157014787",
    "low": "0.0439739003778"
  },
  {
    "date": "2018-05-10",
    "id": "adx-net",
    "cap": "64647581.4227",
    "high": "0.983137011528",
    "low": "0.880388975143"
  },
  {
    "date": "2018-05-10",
    "id": "airswap",
    "cap": "62937600.0",
    "high": "0.476197004318",
    "low": "0.419584006071"
  },
  {
    "date": "2018-05-10",
    "id": "bitbay",
    "cap": "60578110.1727",
    "high": "0.068942502141",
    "low": "0.0593456998467"
  },
  {
    "date": "2018-05-10",
    "id": "eidoo",
    "cap": "58793883.6866",
    "high": "2.21947002411",
    "low": "2.00077009201"
  },
  {
    "date": "2018-05-10",
    "id": "zclassic",
    "cap": "57437583.855",
    "high": "16.9174995422",
    "low": "12.4335002899"
  },
  {
    "date": "2018-05-10",
    "id": "appcoins",
    "cap": "57029456.9369",
    "high": "0.630263984203",
    "low": "0.569984972477"
  },
  {
    "date": "2018-05-10",
    "id": "linkeye",
    "cap": "55147260.0",
    "high": "0.0977625995874",
    "low": "0.0778976976871"
  },
  {
    "date": "2018-05-10",
    "id": "salus",
    "cap": "55141860.531",
    "high": "56.913898468",
    "low": "53.1659011841"
  },
  {
    "date": "2018-05-10",
    "id": "burst",
    "cap": "53359119.6957",
    "high": "0.0297283995897",
    "low": "0.0275513995439"
  },
  {
    "date": "2018-05-10",
    "id": "pura",
    "cap": "44996406.2611",
    "high": "0.285416990519",
    "low": "0.256058990955"
  },
  {
    "date": "2018-05-10",
    "id": "babb",
    "cap": "44050957.5261",
    "high": "0.00225422997028",
    "low": "0.00200748001225"
  },
  {
    "date": "2018-05-10",
    "id": "bitrent",
    "cap": "43786824.9",
    "high": "0.0565897002816",
    "low": "0.0519804991782"
  },
  {
    "date": "2018-05-10",
    "id": "bitcny",
    "cap": "40522883.752",
    "high": "0.158544003963",
    "low": "0.152271002531"
  },
  {
    "date": "2018-05-10",
    "id": "gulden",
    "cap": "38717903.3285",
    "high": "0.103008002043",
    "low": "0.0974526032805"
  },
  {
    "date": "2018-05-10",
    "id": "banca",
    "cap": "38627074.2564",
    "high": "0.00386704993434",
    "low": "0.00318566011265"
  },
  {
    "date": "2018-05-10",
    "id": "sentinel",
    "cap": "35982009.984",
    "high": "0.021178400144",
    "low": "0.0188223998994"
  },
  {
    "date": "2018-05-10",
    "id": "suncontract",
    "cap": "33000598.6163",
    "high": "0.307065993547",
    "low": "0.270689994097"
  },
  {
    "date": "2018-05-10",
    "id": "sentinel-chain",
    "cap": "32437840.2355",
    "high": "0.182587996125",
    "low": "0.164332002401"
  },
  {
    "date": "2018-05-10",
    "id": "aeon",
    "cap": "31369013.3768",
    "high": "2.09508991241",
    "low": "1.94772005081"
  },
  {
    "date": "2018-05-10",
    "id": "bankex",
    "cap": "31298705.8626",
    "high": "0.46788200736",
    "low": "0.441877007484"
  },
  {
    "date": "2018-05-10",
    "id": "adtoken",
    "cap": "29256300.0",
    "high": "0.0544398017228",
    "low": "0.0487604998052"
  },
  {
    "date": "2018-05-10",
    "id": "aidoc",
    "cap": "28247309.3116",
    "high": "0.0682386979461",
    "low": "0.0601745992899"
  },
  {
    "date": "2018-05-10",
    "id": "bitgreen",
    "cap": "27658264.6543",
    "high": "10.5472002029",
    "low": "8.69414043427"
  },
  {
    "date": "2018-05-10",
    "id": "bean-cash",
    "cap": "25521969.879",
    "high": "0.0123014003038",
    "low": "0.0102014997974"
  },
  {
    "date": "2018-05-10",
    "id": "bitcoin-atom",
    "cap": "24971854.5244",
    "high": "1.47552001476",
    "low": "1.17891001701"
  },
  {
    "date": "2018-05-10",
    "id": "agrello-delta",
    "cap": "23443085.4911",
    "high": "0.304019004107",
    "low": "0.272069007158"
  },
  {
    "date": "2018-05-10",
    "id": "mediccoin",
    "cap": "22597710.0925",
    "high": "0.145841002464",
    "low": "0.1244020015"
  },
  {
    "date": "2018-05-10",
    "id": "aichain",
    "cap": "21197966.1848",
    "high": "0.0428199991584",
    "low": "0.0305116008967"
  },
  {
    "date": "2018-05-10",
    "id": "alphacat",
    "cap": "21115615.7801",
    "high": "0.00854466017336",
    "low": "0.00755457999185"
  },
  {
    "date": "2018-05-10",
    "id": "guaranteed-ethurance-token-extra",
    "cap": "20544330.0",
    "high": "0.0840881019831",
    "low": "0.0664713978767"
  },
  {
    "date": "2018-05-10",
    "id": "te-food",
    "cap": "19727688.9153",
    "high": "0.0496147982776",
    "low": "0.0417933985591"
  },
  {
    "date": "2018-05-10",
    "id": "vericoin",
    "cap": "19074937.4762",
    "high": "0.665579974651",
    "low": "0.616249978542"
  },
  {
    "date": "2018-05-10",
    "id": "attention-token-of-media",
    "cap": "18828112.4918",
    "high": "0.00450437981635",
    "low": "0.00400173012167"
  },
  {
    "date": "2018-05-10",
    "id": "alqo",
    "cap": "18343199.6624",
    "high": "0.520364999771",
    "low": "0.433331996202"
  },
  {
    "date": "2018-05-10",
    "id": "decent-bet",
    "cap": "18211831.3343",
    "high": "0.188334003091",
    "low": "0.109580002725"
  },
  {
    "date": "2018-05-10",
    "id": "aeron",
    "cap": "17955600.0",
    "high": "1.53963005543",
    "low": "1.37943005562"
  },
  {
    "date": "2018-05-10",
    "id": "banyan-network",
    "cap": "17947845.2796",
    "high": "0.128718003631",
    "low": "0.114177003503"
  },
  {
    "date": "2018-05-10",
    "id": "covesting",
    "cap": "16850750.0",
    "high": "1.03620994091",
    "low": "0.96045601368"
  },
  {
    "date": "2018-05-10",
    "id": "bitclave",
    "cap": "16471357.7624",
    "high": "0.0346257016063",
    "low": "0.0327529013157"
  },
  {
    "date": "2018-05-10",
    "id": "axpire",
    "cap": "16194865.5",
    "high": "0.0684256032109",
    "low": "0.0602500997484"
  },
  {
    "date": "2018-05-10",
    "id": "pareto-rewards",
    "cap": "15912276.6927",
    "high": "0.0747113004327",
    "low": "0.0632762983441"
  },
  {
    "date": "2018-05-10",
    "id": "bitshares-music",
    "cap": "15856838.9384",
    "high": "1.40429997444",
    "low": "1.08744001389"
  },
  {
    "date": "2018-05-10",
    "id": "bismuth",
    "cap": "15501847.0112",
    "high": "1.76324999332",
    "low": "1.58335995674"
  },
  {
    "date": "2018-05-10",
    "id": "hacken",
    "cap": "15117101.3211",
    "high": "3.4330599308",
    "low": "3.09889006615"
  }
]