[
  {
    "date": "2014-03-08",
    "id": "bitcoin",
    "cap": "7712151171.25",
    "high": "635.140014648",
    "low": "604.460021973"
  },
  {
    "date": "2014-03-08",
    "id": "auroracoin",
    "cap": "295753819.252",
    "high": "31.1026992798",
    "low": "19.192199707"
  },
  {
    "date": "2014-03-08",
    "id": "megacoin",
    "cap": "5557987.80772",
    "high": "0.274255990982",
    "low": "0.239279001951"
  },
  {
    "date": "2014-03-08",
    "id": "mintcoin",
    "cap": "2107438.25932",
    "high": "0.000130864995299",
    "low": "0.000103639002191"
  },
  {
    "date": "2014-03-08",
    "id": "anoncoin",
    "cap": "1497782.01406",
    "high": "2.07395005226",
    "low": "1.39107000828"
  },
  {
    "date": "2014-03-08",
    "id": "ixcoin",
    "cap": "1288614.69084",
    "high": "0.0766493007541",
    "low": "0.0531326010823"
  },
  {
    "date": "2014-03-08",
    "id": "sexcoin",
    "cap": "373892.741764",
    "high": "0.0063484897837",
    "low": "0.00568473013118"
  },
  {
    "date": "2014-03-08",
    "id": "bitbar",
    "cap": "354153.772516",
    "high": "38.9639015198",
    "low": "31.7176990509"
  },
  {
    "date": "2014-03-08",
    "id": "42-coin",
    "cap": "98575.0156002",
    "high": "69328.1015625",
    "low": "55364.0"
  },
  {
    "date": "2014-03-08",
    "id": "pandacoin-pnd",
    "cap": "96517.8015499",
    "high": "0.00000635139986116",
    "low": "0.00000604460001341"
  },
  {
    "date": "2014-03-08",
    "id": "betacoin",
    "cap": "72313.2924994",
    "high": "0.0125443004072",
    "low": "0.00750102009624"
  },
  {
    "date": "2014-03-08",
    "id": "argentum",
    "cap": "58157.2510728",
    "high": "0.0613476000726",
    "low": "0.0510285012424"
  }
]