[
  {
    "date": "2017-01-05",
    "id": "bitcoin",
    "cap": "16300254795.1",
    "high": "1191.09997559",
    "low": "910.416992188"
  },
  {
    "date": "2017-01-05",
    "id": "augur",
    "cap": "56132450.0",
    "high": "5.77714014053",
    "low": "4.1353597641"
  },
  {
    "date": "2017-01-05",
    "id": "nem",
    "cap": "32740919.9964",
    "high": "0.00405758013949",
    "low": "0.00322637008503"
  },
  {
    "date": "2017-01-05",
    "id": "ardor",
    "cap": "10944339.1676",
    "high": "0.0122843999416",
    "low": "0.00998516008258"
  },
  {
    "date": "2017-01-05",
    "id": "bytecoin-bcn",
    "cap": "9581185.46255",
    "high": "0.0000687096980982",
    "low": "0.0000472563988296"
  },
  {
    "date": "2017-01-05",
    "id": "emercoin",
    "cap": "8599642.31854",
    "high": "0.249596998096",
    "low": "0.193103000522"
  },
  {
    "date": "2017-01-05",
    "id": "bitcrystals",
    "cap": "4725895.14563",
    "high": "0.119285002351",
    "low": "0.0905579999089"
  },
  {
    "date": "2017-01-05",
    "id": "agoras-tokens",
    "cap": "4553598.0",
    "high": "0.124379999936",
    "low": "0.0956349000335"
  },
  {
    "date": "2017-01-05",
    "id": "aeon",
    "cap": "1815943.92658",
    "high": "0.177248999476",
    "low": "0.130140006542"
  },
  {
    "date": "2017-01-05",
    "id": "auroracoin",
    "cap": "1069462.00421",
    "high": "0.143026992679",
    "low": "0.105016998947"
  }
]