[
  {
    "date": "2014-11-28",
    "id": "bitcoin",
    "cap": "5101280352.88",
    "high": "382.838012695",
    "low": "358.454986572"
  },
  {
    "date": "2014-11-28",
    "id": "bytecoin-bcn",
    "cap": "1250255.712",
    "high": "0.00000835526043375",
    "low": "0.00000693469019097"
  },
  {
    "date": "2014-11-28",
    "id": "pandacoin-pnd",
    "cap": "1093011.13063",
    "high": "0.000034430398955",
    "low": "0.0000288940991595"
  },
  {
    "date": "2014-11-28",
    "id": "bitbay",
    "cap": "909399.554154",
    "high": "0.000942491984461",
    "low": "0.000786141026765"
  },
  {
    "date": "2014-11-28",
    "id": "ultracoin",
    "cap": "836090.317757",
    "high": "0.0383373983204",
    "low": "0.0291562005877"
  },
  {
    "date": "2014-11-28",
    "id": "ixcoin",
    "cap": "782836.595859",
    "high": "0.0380981005728",
    "low": "0.0306787006557"
  },
  {
    "date": "2014-11-28",
    "id": "megacoin",
    "cap": "511816.707793",
    "high": "0.0201955009252",
    "low": "0.0192104000598"
  },
  {
    "date": "2014-11-28",
    "id": "anoncoin",
    "cap": "373418.884005",
    "high": "0.273773998022",
    "low": "0.24969099462"
  },
  {
    "date": "2014-11-28",
    "id": "emercoin",
    "cap": "279611.088544",
    "high": "0.0109197003767",
    "low": "0.00788601022214"
  },
  {
    "date": "2014-11-28",
    "id": "gulden",
    "cap": "260104.465077",
    "high": "0.00163148995489",
    "low": "0.00140114000533"
  }
]