[
  {
    "date": "2014-04-20",
    "id": "bitcoin",
    "cap": "6312896983.8",
    "high": "510.871002197",
    "low": "490.839996338"
  },
  {
    "date": "2014-04-20",
    "id": "anoncoin",
    "cap": "848220.092928",
    "high": "1.07624995708",
    "low": "0.932393014431"
  },
  {
    "date": "2014-04-20",
    "id": "bitcoin-scrypt",
    "cap": "169921.927175",
    "high": "0.037478800863",
    "low": "0.0310734994709"
  },
  {
    "date": "2014-04-20",
    "id": "42-coin",
    "cap": "72486.1035545",
    "high": "26530.4003906",
    "low": "24599.5996094"
  }
]