[
  {
    "date": "2015-02-15",
    "id": "bitcoin",
    "cap": "3250242178.12",
    "high": "265.610992432",
    "low": "227.684005737"
  },
  {
    "date": "2015-02-15",
    "id": "bitshares",
    "cap": "20453803.4174",
    "high": "0.0091525297612",
    "low": "0.00781457964331"
  },
  {
    "date": "2015-02-15",
    "id": "maidsafecoin",
    "cap": "14302556.9393",
    "high": "0.0366653986275",
    "low": "0.0296701993793"
  },
  {
    "date": "2015-02-15",
    "id": "dash",
    "cap": "14165278.2457",
    "high": "2.89119005203",
    "low": "2.56177997589"
  },
  {
    "date": "2015-02-15",
    "id": "stellar",
    "cap": "11853367.6412",
    "high": "0.00370148010552",
    "low": "0.00325560988858"
  },
  {
    "date": "2015-02-15",
    "id": "namecoin",
    "cap": "5160060.39785",
    "high": "0.552245020866",
    "low": "0.465627014637"
  },
  {
    "date": "2015-02-15",
    "id": "bytecoin-bcn",
    "cap": "1662724.0775",
    "high": "0.0000108686999738",
    "low": "0.00000951148012973"
  },
  {
    "date": "2015-02-15",
    "id": "monero",
    "cap": "1575834.33426",
    "high": "0.280849993229",
    "low": "0.242443993688"
  },
  {
    "date": "2015-02-15",
    "id": "omni",
    "cap": "1193414.05436",
    "high": "2.43182992935",
    "low": "2.16521000862"
  },
  {
    "date": "2015-02-15",
    "id": "mintcoin",
    "cap": "820795.779285",
    "high": "0.0000513049017172",
    "low": "0.0000256942003034"
  },
  {
    "date": "2015-02-15",
    "id": "ixcoin",
    "cap": "474287.076991",
    "high": "0.0269218999892",
    "low": "0.0219358000904"
  },
  {
    "date": "2015-02-15",
    "id": "nav-coin",
    "cap": "391139.478258",
    "high": "0.00825649034232",
    "low": "0.00666048983112"
  },
  {
    "date": "2015-02-15",
    "id": "curecoin",
    "cap": "328049.634222",
    "high": "0.013048700057",
    "low": "0.00730213010684"
  },
  {
    "date": "2015-02-15",
    "id": "vericoin",
    "cap": "326867.616856",
    "high": "0.014763600193",
    "low": "0.0115588996559"
  },
  {
    "date": "2015-02-15",
    "id": "megacoin",
    "cap": "299461.208393",
    "high": "0.0133405001834",
    "low": "0.0106183998287"
  },
  {
    "date": "2015-02-15",
    "id": "gulden",
    "cap": "299106.153649",
    "high": "0.0158405993134",
    "low": "0.00140909000766"
  },
  {
    "date": "2015-02-15",
    "id": "emercoin",
    "cap": "286924.363637",
    "high": "0.0096693597734",
    "low": "0.00814586970955"
  },
  {
    "date": "2015-02-15",
    "id": "anoncoin",
    "cap": "269566.814846",
    "high": "0.173979997635",
    "low": "0.13699400425"
  },
  {
    "date": "2015-02-15",
    "id": "feathercoin",
    "cap": "266667.190427",
    "high": "0.00458004977554",
    "low": "0.00364897004329"
  },
  {
    "date": "2015-02-15",
    "id": "pandacoin-pnd",
    "cap": "227382.517918",
    "high": "0.00000796833955974",
    "low": "0.00000522046002516"
  },
  {
    "date": "2015-02-15",
    "id": "burst",
    "cap": "223733.078476",
    "high": "0.000449301995104",
    "low": "0.000363024999388"
  },
  {
    "date": "2015-02-15",
    "id": "potcoin",
    "cap": "216130.629481",
    "high": "0.00133428000845",
    "low": "0.00109412998427"
  },
  {
    "date": "2015-02-15",
    "id": "cannabiscoin",
    "cap": "207971.605251",
    "high": "0.00317652989179",
    "low": "0.00272072991356"
  },
  {
    "date": "2015-02-15",
    "id": "zetacoin",
    "cap": "187048.079683",
    "high": "0.00131441000849",
    "low": "0.00113029999193"
  },
  {
    "date": "2015-02-15",
    "id": "zeitcoin",
    "cap": "171671.639018",
    "high": "0.00000659918987367",
    "low": "0.00000454631981484"
  },
  {
    "date": "2015-02-15",
    "id": "bitcny",
    "cap": "152287.051409",
    "high": "0.167379006743",
    "low": "0.148350998759"
  },
  {
    "date": "2015-02-15",
    "id": "ultracoin",
    "cap": "152166.21029",
    "high": "0.00669466983527",
    "low": "0.00539545016363"
  },
  {
    "date": "2015-02-15",
    "id": "startcoin",
    "cap": "138605.922936",
    "high": "0.0133474003524",
    "low": "0.0109307002276"
  },
  {
    "date": "2015-02-15",
    "id": "spreadcoin",
    "cap": "131624.754775",
    "high": "0.0902585014701",
    "low": "0.0627119988203"
  },
  {
    "date": "2015-02-15",
    "id": "stealth",
    "cap": "129033.849198",
    "high": "0.00717101013288",
    "low": "0.0059560299851"
  },
  {
    "date": "2015-02-15",
    "id": "digitalcoin",
    "cap": "126762.339123",
    "high": "0.00728385010734",
    "low": "0.00618301006034"
  },
  {
    "date": "2015-02-15",
    "id": "faircoin",
    "cap": "120175.405603",
    "high": "0.00473053008318",
    "low": "0.00227683992125"
  },
  {
    "date": "2015-02-15",
    "id": "bitbay",
    "cap": "117453.12821",
    "high": "0.000142000004416",
    "low": "0.000113841997518"
  },
  {
    "date": "2015-02-15",
    "id": "boostcoin",
    "cap": "109393.187121",
    "high": "0.0101581001654",
    "low": "0.00900319032371"
  },
  {
    "date": "2015-02-15",
    "id": "opal",
    "cap": "100010.723088",
    "high": "0.0442100986838",
    "low": "0.00665443995968"
  },
  {
    "date": "2015-02-15",
    "id": "myriad",
    "cap": "75345.1266296",
    "high": "0.0000898506987141",
    "low": "0.0000731788022676"
  },
  {
    "date": "2015-02-15",
    "id": "quotient",
    "cap": "53367.6622425",
    "high": "0.00610544998199",
    "low": "0.00358891999349"
  },
  {
    "date": "2015-02-15",
    "id": "bitstar",
    "cap": "53066.9446403",
    "high": "0.00363763002679",
    "low": "0.00236088992096"
  },
  {
    "date": "2015-02-15",
    "id": "iocoin",
    "cap": "51174.4207803",
    "high": "0.00439515011385",
    "low": "0.00313423993066"
  },
  {
    "date": "2015-02-15",
    "id": "e-gulden",
    "cap": "41852.4071529",
    "high": "0.00884419027716",
    "low": "0.00762232998386"
  },
  {
    "date": "2015-02-15",
    "id": "auroracoin",
    "cap": "37803.0398627",
    "high": "0.0184275005013",
    "low": "0.0155918998644"
  },
  {
    "date": "2015-02-15",
    "id": "carboncoin",
    "cap": "35368.2637837",
    "high": "0.00000521899983141",
    "low": "0.00000227683995035"
  },
  {
    "date": "2015-02-15",
    "id": "artbyte",
    "cap": "31106.2193685",
    "high": "0.0000835039973026",
    "low": "0.0000725046993466"
  },
  {
    "date": "2015-02-15",
    "id": "verge",
    "cap": "30764.235525",
    "high": "0.0000157601007231",
    "low": "0.00000455442977909"
  },
  {
    "date": "2015-02-15",
    "id": "supercoin",
    "cap": "30226.2971026",
    "high": "0.00151584995911",
    "low": "0.00122672994621"
  },
  {
    "date": "2015-02-15",
    "id": "dimecoin",
    "cap": "27591.3419784",
    "high": "0.000000109219001843",
    "low": "0.0000000897040024483"
  },
  {
    "date": "2015-02-15",
    "id": "sexcoin",
    "cap": "26882.9014223",
    "high": "0.000355233001756",
    "low": "0.000284999987343"
  },
  {
    "date": "2015-02-15",
    "id": "securecoin",
    "cap": "26593.275975",
    "high": "0.0130971996114",
    "low": "0.0116771999747"
  },
  {
    "date": "2015-02-15",
    "id": "groestlcoin",
    "cap": "24501.4048659",
    "high": "0.000444150005933",
    "low": "0.000375678995624"
  },
  {
    "date": "2015-02-15",
    "id": "terracoin",
    "cap": "23510.872391",
    "high": "0.00531368004158",
    "low": "0.00351590989158"
  },
  {
    "date": "2015-02-15",
    "id": "bitcoin-scrypt",
    "cap": "23194.4843813",
    "high": "0.0220226999372",
    "low": "0.000861915992573"
  },
  {
    "date": "2015-02-15",
    "id": "bitgold",
    "cap": "21406.1906887",
    "high": "1327.13000488",
    "low": "1129.0"
  },
  {
    "date": "2015-02-15",
    "id": "rabbitcoin",
    "cap": "18551.8146295",
    "high": "0.000000202953003736",
    "low": "0.000000179408004897"
  },
  {
    "date": "2015-02-15",
    "id": "trollcoin",
    "cap": "16988.9928825",
    "high": "0.0000043118297981",
    "low": "0.00000365947994396"
  },
  {
    "date": "2015-02-15",
    "id": "petrodollar",
    "cap": "15020.407764",
    "high": "0.000330937997205",
    "low": "0.000236011997913"
  },
  {
    "date": "2015-02-15",
    "id": "cryptonite",
    "cap": "14680.387785",
    "high": "0.000249147997238",
    "low": "0.00020491599571"
  },
  {
    "date": "2015-02-15",
    "id": "gcn-coin",
    "cap": "14350.523378",
    "high": "0.000000246934007464",
    "low": "0.000000190370002429"
  },
  {
    "date": "2015-02-15",
    "id": "bitbtc",
    "cap": "12497.9276052",
    "high": "314.470001221",
    "low": "223.589996338"
  },
  {
    "date": "2015-02-15",
    "id": "flo",
    "cap": "11486.4820686",
    "high": "0.000150374005898",
    "low": "0.000133299996378"
  },
  {
    "date": "2015-02-15",
    "id": "bitbar",
    "cap": "11193.3071971",
    "high": "0.792612016201",
    "low": "0.668357014656"
  },
  {
    "date": "2015-02-15",
    "id": "acoin",
    "cap": "10757.0004371",
    "high": "0.0197841990739",
    "low": "0.0133026000112"
  },
  {
    "date": "2015-02-15",
    "id": "blakecoin",
    "cap": "9852.29513392",
    "high": "0.00206655007787",
    "low": "0.00159394997172"
  },
  {
    "date": "2015-02-15",
    "id": "kobocoin",
    "cap": "7711.67625419",
    "high": "0.000882839027327",
    "low": "0.00064686499536"
  },
  {
    "date": "2015-02-15",
    "id": "bitcoin-plus",
    "cap": "6597.76581392",
    "high": "0.265608012676",
    "low": "0.116130001843"
  },
  {
    "date": "2015-02-15",
    "id": "emerald",
    "cap": "5411.16694754",
    "high": "0.000537446991075",
    "low": "0.000439430004917"
  },
  {
    "date": "2015-02-15",
    "id": "betacoin",
    "cap": "5218.77649617",
    "high": "0.000295612990158",
    "low": "0.000230236997595"
  },
  {
    "date": "2015-02-15",
    "id": "plncoin",
    "cap": "4593.000896",
    "high": "0.000305452995235",
    "low": "0.000235004001297"
  },
  {
    "date": "2015-02-15",
    "id": "argentum",
    "cap": "3054.52273578",
    "high": "0.00238401000388",
    "low": "0.00202183006331"
  },
  {
    "date": "2015-02-15",
    "id": "britcoin",
    "cap": "2833.47485844",
    "high": "0.000387443986256",
    "low": "0.000255005987128"
  },
  {
    "date": "2015-02-15",
    "id": "42-coin",
    "cap": "1091.1060497",
    "high": "1429.68994141",
    "low": "1139.48999023"
  },
  {
    "date": "2015-02-15",
    "id": "monetaryunit",
    "cap": "1067.493621",
    "high": "0.0000317300000461",
    "low": "0.0000205034993996"
  },
  {
    "date": "2015-02-15",
    "id": "belacoin",
    "cap": "143.00114056",
    "high": "0.0000265610997303",
    "low": "0.0000227683995035"
  },
  {
    "date": "2015-02-15",
    "id": "skeincoin",
    "cap": "-1",
    "high": "0.000069058900408",
    "low": "0.0000628830966889"
  },
  {
    "date": "2015-02-15",
    "id": "joincoin",
    "cap": "-1",
    "high": "0.00374245992862",
    "low": "0.00239097001031"
  }
]