[
  {
    "date": "2018-04-27",
    "id": "bitcoin",
    "cap": "152802874822",
    "high": "9375.46972656",
    "low": "8987.04980469"
  },
  {
    "date": "2018-04-27",
    "id": "bitcoin-cash",
    "cap": "22873890375.0",
    "high": "1422.06005859",
    "low": "1337.84997559"
  },
  {
    "date": "2018-04-27",
    "id": "stellar",
    "cap": "7262888447.1",
    "high": "0.425157010555",
    "low": "0.383910000324"
  },
  {
    "date": "2018-04-27",
    "id": "iota",
    "cap": "5270378550.81",
    "high": "2.09082007408",
    "low": "1.89075005054"
  },
  {
    "date": "2018-04-27",
    "id": "tron",
    "cap": "4867786367.06",
    "high": "0.0791542008519",
    "low": "0.0718396008015"
  },
  {
    "date": "2018-04-27",
    "id": "neo",
    "cap": "4723387500.0",
    "high": "77.3094024658",
    "low": "72.6675033569"
  },
  {
    "date": "2018-04-27",
    "id": "monero",
    "cap": "4023636238.6",
    "high": "268.630004883",
    "low": "251.87600708"
  },
  {
    "date": "2018-04-27",
    "id": "dash",
    "cap": "3792522899.77",
    "high": "504.290008545",
    "low": "471.565002441"
  },
  {
    "date": "2018-04-27",
    "id": "nem",
    "cap": "3497048999.61",
    "high": "0.408412009478",
    "low": "0.388370007277"
  },
  {
    "date": "2018-04-27",
    "id": "omisego",
    "cap": "1776897566.62",
    "high": "19.0182991028",
    "low": "17.4132995605"
  },
  {
    "date": "2018-04-27",
    "id": "binance-coin",
    "cap": "1634109050.11",
    "high": "14.7716999054",
    "low": "14.1837997437"
  },
  {
    "date": "2018-04-27",
    "id": "bitcoin-gold",
    "cap": "1245765660.43",
    "high": "79.2530975342",
    "low": "73.139503479"
  },
  {
    "date": "2018-04-27",
    "id": "lisk",
    "cap": "1179838593.85",
    "high": "11.8985004425",
    "low": "11.1054000854"
  },
  {
    "date": "2018-04-27",
    "id": "steem",
    "cap": "1098473076.24",
    "high": "4.64793014526",
    "low": "3.78624010086"
  },
  {
    "date": "2018-04-27",
    "id": "zcash",
    "cap": "1075595603.38",
    "high": "303.437011719",
    "low": "281.533996582"
  },
  {
    "date": "2018-04-27",
    "id": "verge",
    "cap": "1009161791.29",
    "high": "0.0745069012046",
    "low": "0.0675968974829"
  },
  {
    "date": "2018-04-27",
    "id": "siacoin",
    "cap": "983080395.334",
    "high": "0.0326892994344",
    "low": "0.0272496994585"
  },
  {
    "date": "2018-04-27",
    "id": "bytecoin-bcn",
    "cap": "971461977.685",
    "high": "0.00563301006332",
    "low": "0.00528367003426"
  },
  {
    "date": "2018-04-27",
    "id": "bytom",
    "cap": "949518675.0",
    "high": "1.0754699707",
    "low": "0.962024986744"
  },
  {
    "date": "2018-04-27",
    "id": "bitcoin-diamond",
    "cap": "889617635.445",
    "high": "6.89971017838",
    "low": "5.30522012711"
  },
  {
    "date": "2018-04-27",
    "id": "bitcoin-private",
    "cap": "808661271.937",
    "high": "50.1608009338",
    "low": "33.2425003052"
  },
  {
    "date": "2018-04-27",
    "id": "bitshares",
    "cap": "685572915.84",
    "high": "0.280470013618",
    "low": "0.261716991663"
  },
  {
    "date": "2018-04-27",
    "id": "aeternity",
    "cap": "676467751.366",
    "high": "3.16704010963",
    "low": "2.57106995583"
  },
  {
    "date": "2018-04-27",
    "id": "zilliqa",
    "cap": "660272486.49",
    "high": "0.0985551029444",
    "low": "0.0905900001526"
  },
  {
    "date": "2018-04-27",
    "id": "ontology",
    "cap": "594906939.655",
    "high": "5.6894698143",
    "low": "5.15808010101"
  },
  {
    "date": "2018-04-27",
    "id": "stratis",
    "cap": "594304757.233",
    "high": "6.4633398056",
    "low": "5.96035003662"
  },
  {
    "date": "2018-04-27",
    "id": "0x",
    "cap": "559611735.701",
    "high": "1.16885995865",
    "low": "1.06555998325"
  },
  {
    "date": "2018-04-27",
    "id": "golem-network-tokens",
    "cap": "490735433.474",
    "high": "0.714944005013",
    "low": "0.538282990456"
  },
  {
    "date": "2018-04-27",
    "id": "status",
    "cap": "485232631.787",
    "high": "0.146660000086",
    "low": "0.139816999435"
  },
  {
    "date": "2018-04-27",
    "id": "aion",
    "cap": "473754750.107",
    "high": "3.81253004074",
    "low": "3.54753994942"
  },
  {
    "date": "2018-04-27",
    "id": "waltonchain",
    "cap": "457111290.28",
    "high": "15.4513998032",
    "low": "13.7756004333"
  },
  {
    "date": "2018-04-27",
    "id": "augur",
    "cap": "441973400.0",
    "high": "43.4007987976",
    "low": "40.1794013977"
  },
  {
    "date": "2018-04-27",
    "id": "loopring",
    "cap": "431283760.881",
    "high": "0.79740601778",
    "low": "0.753274023533"
  },
  {
    "date": "2018-04-27",
    "id": "basic-attention-token",
    "cap": "418297000.0",
    "high": "0.447371989489",
    "low": "0.416669994593"
  },
  {
    "date": "2018-04-27",
    "id": "iostoken",
    "cap": "408933840.0",
    "high": "0.0525636002421",
    "low": "0.0486826002598"
  },
  {
    "date": "2018-04-27",
    "id": "ardor",
    "cap": "383233189.273",
    "high": "0.401176005602",
    "low": "0.38025200367"
  },
  {
    "date": "2018-04-27",
    "id": "kyber-network",
    "cap": "355866116.898",
    "high": "3.09042000771",
    "low": "2.59647989273"
  },
  {
    "date": "2018-04-27",
    "id": "ark",
    "cap": "347843486.714",
    "high": "3.57473993301",
    "low": "3.37968993187"
  },
  {
    "date": "2018-04-27",
    "id": "aelf",
    "cap": "285230000.0",
    "high": "1.17597997189",
    "low": "1.11020994186"
  },
  {
    "date": "2018-04-27",
    "id": "substratum",
    "cap": "277605960.351",
    "high": "0.790749013424",
    "low": "0.709801971912"
  },
  {
    "date": "2018-04-27",
    "id": "dentacoin",
    "cap": "271738218.171",
    "high": "0.000944375991821",
    "low": "0.00083412398817"
  },
  {
    "date": "2018-04-27",
    "id": "dragonchain",
    "cap": "270823481.646",
    "high": "1.24082005024",
    "low": "1.0954400301"
  },
  {
    "date": "2018-04-27",
    "id": "storm",
    "cap": "259322930.161",
    "high": "0.0686549991369",
    "low": "0.0624307990074"
  },
  {
    "date": "2018-04-27",
    "id": "gifto",
    "cap": "253361544.688",
    "high": "0.60050201416",
    "low": "0.424513995647"
  },
  {
    "date": "2018-04-27",
    "id": "ethos",
    "cap": "252357096.969",
    "high": "3.63592004776",
    "low": "3.29698991776"
  },
  {
    "date": "2018-04-27",
    "id": "bancor",
    "cap": "232375831.686",
    "high": "4.72481012344",
    "low": "4.48072004318"
  },
  {
    "date": "2018-04-27",
    "id": "salt",
    "cap": "213501091.183",
    "high": "3.92353010178",
    "low": "3.59043002129"
  },
  {
    "date": "2018-04-27",
    "id": "gxchain",
    "cap": "212123400.0",
    "high": "3.83392000198",
    "low": "3.48757004738"
  },
  {
    "date": "2018-04-27",
    "id": "funfair",
    "cap": "210110951.42",
    "high": "0.0472473986447",
    "low": "0.0443238988519"
  },
  {
    "date": "2018-04-27",
    "id": "veritaseum",
    "cap": "204452725.785",
    "high": "121.21900177",
    "low": "100.387001038"
  },
  {
    "date": "2018-04-27",
    "id": "power-ledger",
    "cap": "192787104.577",
    "high": "0.560949981213",
    "low": "0.525849997997"
  },
  {
    "date": "2018-04-27",
    "id": "enigma",
    "cap": "185040664.999",
    "high": "2.67364001274",
    "low": "2.45584988594"
  },
  {
    "date": "2018-04-27",
    "id": "crypto-com",
    "cap": "181914925.935",
    "high": "12.6333999634",
    "low": "11.4427995682"
  },
  {
    "date": "2018-04-27",
    "id": "obyte",
    "cap": "167622344.411",
    "high": "282.812011719",
    "low": "255.511001587"
  },
  {
    "date": "2018-04-27",
    "id": "nucleus-vision",
    "cap": "165400836.284",
    "high": "0.0441491007805",
    "low": "0.0401839017868"
  },
  {
    "date": "2018-04-27",
    "id": "fusion",
    "cap": "165237829.625",
    "high": "5.76992988586",
    "low": "5.41345977783"
  },
  {
    "date": "2018-04-27",
    "id": "maidsafecoin",
    "cap": "164252992.831",
    "high": "0.395420014858",
    "low": "0.362948000431"
  },
  {
    "date": "2018-04-27",
    "id": "neblio",
    "cap": "158416951.986",
    "high": "13.30189991",
    "low": "12.1464004517"
  },
  {
    "date": "2018-04-27",
    "id": "zencash",
    "cap": "151986535.661",
    "high": "42.3512992859",
    "low": "37.8042984009"
  },
  {
    "date": "2018-04-27",
    "id": "smartcash",
    "cap": "151554897.842",
    "high": "0.17782600224",
    "low": "0.161304995418"
  },
  {
    "date": "2018-04-27",
    "id": "particl",
    "cap": "150765579.093",
    "high": "18.1590003967",
    "low": "16.6401004791"
  },
  {
    "date": "2018-04-27",
    "id": "storj",
    "cap": "150445803.503",
    "high": "1.16322004795",
    "low": "1.10794997215"
  },
  {
    "date": "2018-04-27",
    "id": "skycoin",
    "cap": "144856490.783",
    "high": "19.8833999634",
    "low": "17.7800998688"
  },
  {
    "date": "2018-04-27",
    "id": "iconomi",
    "cap": "140868678.867",
    "high": "1.54815995693",
    "low": "1.41242003441"
  },
  {
    "date": "2018-04-27",
    "id": "achain",
    "cap": "138677000.109",
    "high": "0.307960003614",
    "low": "0.274327009916"
  },
  {
    "date": "2018-04-27",
    "id": "matrix-ai-network",
    "cap": "138532050.0",
    "high": "0.997106015682",
    "low": "0.912878990173"
  },
  {
    "date": "2018-04-27",
    "id": "game",
    "cap": "137307917.551",
    "high": "0.27472999692",
    "low": "0.229221999645"
  },
  {
    "date": "2018-04-27",
    "id": "civic",
    "cap": "132610150.743",
    "high": "0.410961002111",
    "low": "0.386572003365"
  },
  {
    "date": "2018-04-27",
    "id": "poa-network",
    "cap": "130708802.891",
    "high": "0.692524015903",
    "low": "0.625436007977"
  },
  {
    "date": "2018-04-27",
    "id": "emercoin",
    "cap": "129647771.314",
    "high": "3.48063993454",
    "low": "3.09105992317"
  },
  {
    "date": "2018-04-27",
    "id": "litecoin-cash",
    "cap": "127590436.977",
    "high": "0.243048995733",
    "low": "0.196587994695"
  },
  {
    "date": "2018-04-27",
    "id": "poet",
    "cap": "121717735.565",
    "high": "0.057643301785",
    "low": "0.0535556003451"
  },
  {
    "date": "2018-04-27",
    "id": "dew",
    "cap": "120428576.357",
    "high": "1.39379000664",
    "low": "1.09768998623"
  },
  {
    "date": "2018-04-27",
    "id": "dent",
    "cap": "119554052.706",
    "high": "0.0127584999427",
    "low": "0.0112595995888"
  },
  {
    "date": "2018-04-27",
    "id": "quantstamp",
    "cap": "111853623.867",
    "high": "0.196208998561",
    "low": "0.179336994886"
  },
  {
    "date": "2018-04-27",
    "id": "santiment",
    "cap": "111838109.895",
    "high": "1.94226002693",
    "low": "1.77371001244"
  },
  {
    "date": "2018-04-27",
    "id": "time-new-bank",
    "cap": "111237002.141",
    "high": "0.0511851012707",
    "low": "0.0471008010209"
  },
  {
    "date": "2018-04-27",
    "id": "cybermiles",
    "cap": "111051299.199",
    "high": "0.186967000365",
    "low": "0.163956999779"
  },
  {
    "date": "2018-04-27",
    "id": "aragon",
    "cap": "110364802.999",
    "high": "4.55099010468",
    "low": "4.18531990051"
  },
  {
    "date": "2018-04-27",
    "id": "enjin-coin",
    "cap": "110173471.396",
    "high": "0.151962995529",
    "low": "0.144451007247"
  },
  {
    "date": "2018-04-27",
    "id": "bitcore",
    "cap": "109740978.484",
    "high": "8.43200969696",
    "low": "7.40766000748"
  },
  {
    "date": "2018-04-27",
    "id": "medibloc",
    "cap": "104628520.145",
    "high": "0.0361839011312",
    "low": "0.0335679017007"
  },
  {
    "date": "2018-04-27",
    "id": "raiden-network-token",
    "cap": "104286167.263",
    "high": "2.19984006882",
    "low": "2.05838990211"
  },
  {
    "date": "2018-04-27",
    "id": "singularitynet",
    "cap": "104171510.389",
    "high": "0.20758600533",
    "low": "0.189397007227"
  },
  {
    "date": "2018-04-27",
    "id": "arcblock",
    "cap": "103314958.891",
    "high": "1.17056000233",
    "low": "1.10207998753"
  },
  {
    "date": "2018-04-27",
    "id": "high-performance-blockchain",
    "cap": "99033921.3517",
    "high": "3.61366009712",
    "low": "3.33418011665"
  },
  {
    "date": "2018-04-27",
    "id": "groestlcoin",
    "cap": "98851443.5838",
    "high": "1.46133995056",
    "low": "1.36858999729"
  },
  {
    "date": "2018-04-27",
    "id": "apex",
    "cap": "97421306.2523",
    "high": "0.260111004114",
    "low": "0.245123997331"
  },
  {
    "date": "2018-04-27",
    "id": "cube",
    "cap": "96534931.948",
    "high": "0.0174768008292",
    "low": "0.0152716999874"
  },
  {
    "date": "2018-04-27",
    "id": "genaro-network",
    "cap": "94149720.6166",
    "high": "0.429565995932",
    "low": "0.391981989145"
  },
  {
    "date": "2018-04-27",
    "id": "amber",
    "cap": "92137273.2263",
    "high": "0.674130022526",
    "low": "0.632445991039"
  },
  {
    "date": "2018-04-27",
    "id": "sirin-labs-token",
    "cap": "91451944.8002",
    "high": "0.406569987535",
    "low": "0.378968000412"
  },
  {
    "date": "2018-04-27",
    "id": "credits",
    "cap": "87355469.8321",
    "high": "0.70403701067",
    "low": "0.61560600996"
  },
  {
    "date": "2018-04-27",
    "id": "blockv",
    "cap": "86431373.9373",
    "high": "0.0618911981583",
    "low": "0.0564382001758"
  },
  {
    "date": "2018-04-27",
    "id": "red-pulse",
    "cap": "86223937.8922",
    "high": "0.115875996649",
    "low": "0.107050001621"
  },
  {
    "date": "2018-04-27",
    "id": "sonm",
    "cap": "83943585.6",
    "high": "0.258763998747",
    "low": "0.225311994553"
  },
  {
    "date": "2018-04-27",
    "id": "nav-coin",
    "cap": "83238892.9137",
    "high": "1.45624005795",
    "low": "1.32625997066"
  },
  {
    "date": "2018-04-27",
    "id": "bluzelle",
    "cap": "82960680.0",
    "high": "0.550697982311",
    "low": "0.502792000771"
  },
  {
    "date": "2018-04-27",
    "id": "pillar",
    "cap": "81590668.7056",
    "high": "0.37745898962",
    "low": "0.354193001986"
  },
  {
    "date": "2018-04-27",
    "id": "zclassic",
    "cap": "80225654.325",
    "high": "40.7591018677",
    "low": "17.4783000946"
  },
  {
    "date": "2018-04-27",
    "id": "ethlend",
    "cap": "78253136.7643",
    "high": "0.0759150013328",
    "low": "0.0712305977941"
  },
  {
    "date": "2018-04-27",
    "id": "genesis-vision",
    "cap": "77168216.0271",
    "high": "22.2791996002",
    "low": "20.7063999176"
  },
  {
    "date": "2018-04-27",
    "id": "airswap",
    "cap": "76155150.0",
    "high": "0.553246974945",
    "low": "0.505780994892"
  },
  {
    "date": "2018-04-27",
    "id": "asch",
    "cap": "74276208.6482",
    "high": "0.826611995697",
    "low": "0.703154027462"
  },
  {
    "date": "2018-04-27",
    "id": "bitbay",
    "cap": "72496359.0122",
    "high": "0.0769490972161",
    "low": "0.0711231976748"
  },
  {
    "date": "2018-04-27",
    "id": "bibox-token",
    "cap": "71818815.0388",
    "high": "0.721154987812",
    "low": "0.676998019218"
  },
  {
    "date": "2018-04-27",
    "id": "c20",
    "cap": "70320800.1762",
    "high": "1.86231005192",
    "low": "1.74823999405"
  },
  {
    "date": "2018-04-27",
    "id": "adx-net",
    "cap": "69390396.9696",
    "high": "1.03097999096",
    "low": "0.944977998734"
  },
  {
    "date": "2018-04-27",
    "id": "eidoo",
    "cap": "66978899.6352",
    "high": "2.37656998634",
    "low": "2.25135993958"
  },
  {
    "date": "2018-04-27",
    "id": "streamr-datacoin",
    "cap": "66754907.7219",
    "high": "0.105623997748",
    "low": "0.0966510996222"
  },
  {
    "date": "2018-04-27",
    "id": "ripio-credit-network",
    "cap": "65854224.8784",
    "high": "0.142777994275",
    "low": "0.134046003222"
  },
  {
    "date": "2018-04-27",
    "id": "telcoin",
    "cap": "65252984.2705",
    "high": "0.00241316994652",
    "low": "0.00216957996599"
  },
  {
    "date": "2018-04-27",
    "id": "iht-real-estate-protocol",
    "cap": "64011336.5876",
    "high": "0.198623001575",
    "low": "0.179516002536"
  },
  {
    "date": "2018-04-27",
    "id": "iot-chain",
    "cap": "63681091.8779",
    "high": "1.41284000874",
    "low": "1.31020998955"
  },
  {
    "date": "2018-04-27",
    "id": "bottos",
    "cap": "63488201.0249",
    "high": "0.139516994357",
    "low": "0.132707998157"
  },
  {
    "date": "2018-04-27",
    "id": "minexcoin",
    "cap": "60468014.2595",
    "high": "18.5055999756",
    "low": "16.4134998322"
  },
  {
    "date": "2018-04-27",
    "id": "electrifyasia",
    "cap": "59990962.0778",
    "high": "0.207646995783",
    "low": "0.162244006991"
  },
  {
    "date": "2018-04-27",
    "id": "wepower",
    "cap": "59940361.6667",
    "high": "0.160258993506",
    "low": "0.147092998028"
  },
  {
    "date": "2018-04-27",
    "id": "vibe",
    "cap": "58439632.8212",
    "high": "0.311693012714",
    "low": "0.285762995481"
  },
  {
    "date": "2018-04-27",
    "id": "salus",
    "cap": "57584681.4177",
    "high": "60.7379989624",
    "low": "56.9901008606"
  },
  {
    "date": "2018-04-27",
    "id": "appcoins",
    "cap": "56749104.7552",
    "high": "0.599650025368",
    "low": "0.541261970997"
  },
  {
    "date": "2018-04-27",
    "id": "district0x",
    "cap": "56232960.0",
    "high": "0.103653997183",
    "low": "0.0927810966969"
  },
  {
    "date": "2018-04-27",
    "id": "internet-node-token",
    "cap": "55144050.0",
    "high": "0.434763997793",
    "low": "0.366086006165"
  },
  {
    "date": "2018-04-27",
    "id": "bitrent",
    "cap": "54362583.1292",
    "high": "0.0674600973725",
    "low": "0.0609318986535"
  },
  {
    "date": "2018-04-27",
    "id": "spankchain",
    "cap": "53950201.1499",
    "high": "0.19544300437",
    "low": "0.178509995341"
  },
  {
    "date": "2018-04-27",
    "id": "pura",
    "cap": "50347514.2552",
    "high": "0.312584012747",
    "low": "0.288201987743"
  },
  {
    "date": "2018-04-27",
    "id": "library-credit",
    "cap": "49329167.508",
    "high": "0.322477996349",
    "low": "0.29486399889"
  },
  {
    "date": "2018-04-27",
    "id": "qlink",
    "cap": "47740560.0",
    "high": "0.217822000384",
    "low": "0.198918998241"
  },
  {
    "date": "2018-04-27",
    "id": "wagerr",
    "cap": "47555661.0",
    "high": "0.278436988592",
    "low": "0.257506996393"
  },
  {
    "date": "2018-04-27",
    "id": "feathercoin",
    "cap": "47083032.4004",
    "high": "0.255596995354",
    "low": "0.234436005354"
  },
  {
    "date": "2018-04-27",
    "id": "burst",
    "cap": "46725937.2261",
    "high": "0.026655100286",
    "low": "0.0240675006062"
  },
  {
    "date": "2018-04-27",
    "id": "envion",
    "cap": "46069230.4505",
    "high": "0.473648011684",
    "low": "0.428582012653"
  },
  {
    "date": "2018-04-27",
    "id": "etherparty",
    "cap": "44663583.315",
    "high": "0.100419998169",
    "low": "0.0919618010521"
  },
  {
    "date": "2018-04-27",
    "id": "gulden",
    "cap": "43535531.5996",
    "high": "0.118257001042",
    "low": "0.109430998564"
  },
  {
    "date": "2018-04-27",
    "id": "melon",
    "cap": "43391764.8",
    "high": "75.5725021362",
    "low": "72.391998291"
  },
  {
    "date": "2018-04-27",
    "id": "decent",
    "cap": "42561376.5787",
    "high": "0.900385975838",
    "low": "0.817332029343"
  },
  {
    "date": "2018-04-27",
    "id": "mobius",
    "cap": "42202589.8564",
    "high": "0.118753001094",
    "low": "0.112044997513"
  },
  {
    "date": "2018-04-27",
    "id": "experience-points",
    "cap": "40520467.9896",
    "high": "0.000257965002675",
    "low": "0.000178625006811"
  },
  {
    "date": "2018-04-27",
    "id": "adtoken",
    "cap": "40052760.0",
    "high": "0.076226003468",
    "low": "0.0638116970658"
  },
  {
    "date": "2018-04-27",
    "id": "soarcoin",
    "cap": "39660743.6159",
    "high": "0.0384217984974",
    "low": "0.0366798005998"
  },
  {
    "date": "2018-04-27",
    "id": "xtrabytes",
    "cap": "37500128.0",
    "high": "0.0960332974792",
    "low": "0.0869192034006"
  },
  {
    "date": "2018-04-27",
    "id": "all-sports",
    "cap": "37470728.4831",
    "high": "0.0529874004424",
    "low": "0.0437442995608"
  },
  {
    "date": "2018-04-27",
    "id": "bitcny",
    "cap": "37306671.292",
    "high": "0.166043996811",
    "low": "0.160803005099"
  },
  {
    "date": "2018-04-27",
    "id": "qunqun",
    "cap": "36849196.6526",
    "high": "0.0481241010129",
    "low": "0.0427655987442"
  },
  {
    "date": "2018-04-27",
    "id": "legolas-exchange",
    "cap": "36591290.3739",
    "high": "0.319510012865",
    "low": "0.300298005342"
  },
  {
    "date": "2018-04-27",
    "id": "babb",
    "cap": "36441437.5084",
    "high": "0.0033766599372",
    "low": "0.00212494004518"
  },
  {
    "date": "2018-04-27",
    "id": "kickico",
    "cap": "35717606.3939",
    "high": "0.0838704034686",
    "low": "0.0777577981353"
  },
  {
    "date": "2018-04-27",
    "id": "linkeye",
    "cap": "35658720.0",
    "high": "0.0637553036213",
    "low": "0.0594311989844"
  },
  {
    "date": "2018-04-27",
    "id": "viberate",
    "cap": "35239565.7087",
    "high": "0.229986995459",
    "low": "0.20038600266"
  },
  {
    "date": "2018-04-27",
    "id": "xel",
    "cap": "35079711.4475",
    "high": "0.453911989927",
    "low": "0.347815990448"
  },
  {
    "date": "2018-04-27",
    "id": "bankex",
    "cap": "35061690.2077",
    "high": "0.53858602047",
    "low": "0.487522006035"
  },
  {
    "date": "2018-04-27",
    "id": "banca",
    "cap": "34626706.9546",
    "high": "0.00315194996074",
    "low": "0.00242161005735"
  },
  {
    "date": "2018-04-27",
    "id": "tokenomy",
    "cap": "34431945.5391",
    "high": "0.286233991385",
    "low": "0.276324003935"
  },
  {
    "date": "2018-04-27",
    "id": "xinfin-network",
    "cap": "34009597.052",
    "high": "0.0131770996377",
    "low": "0.00964010041207"
  },
  {
    "date": "2018-04-27",
    "id": "ravencoin",
    "cap": "31420667.0886",
    "high": "0.0358809009194",
    "low": "0.0278491992503"
  },
  {
    "date": "2018-04-27",
    "id": "phore",
    "cap": "31335211.6473",
    "high": "2.61946988106",
    "low": "2.02917003632"
  },
  {
    "date": "2018-04-27",
    "id": "mercury",
    "cap": "29809700.0",
    "high": "0.31032499671",
    "low": "0.28997901082"
  },
  {
    "date": "2018-04-27",
    "id": "html-coin",
    "cap": "29805874.7918",
    "high": "0.000505906005856",
    "low": "0.000408438005252"
  },
  {
    "date": "2018-04-27",
    "id": "decision-token",
    "cap": "29690790.7153",
    "high": "1.1462199688",
    "low": "0.803188025951"
  },
  {
    "date": "2018-04-27",
    "id": "aeon",
    "cap": "29632927.1417",
    "high": "1.99556005001",
    "low": "1.84851002693"
  },
  {
    "date": "2018-04-27",
    "id": "alphacat",
    "cap": "29612859.9558",
    "high": "0.011760099791",
    "low": "0.0104906000197"
  },
  {
    "date": "2018-04-27",
    "id": "dimecoin",
    "cap": "29476893.3094",
    "high": "0.00006004090028",
    "low": "0.0000520401008544"
  },
  {
    "date": "2018-04-27",
    "id": "deeponion",
    "cap": "29255364.1507",
    "high": "2.39108991623",
    "low": "2.01213002205"
  },
  {
    "date": "2018-04-27",
    "id": "lamden",
    "cap": "28804942.4505",
    "high": "0.226835995913",
    "low": "0.197260007262"
  },
  {
    "date": "2018-04-27",
    "id": "lunyr",
    "cap": "28796924.5655",
    "high": "13.803899765",
    "low": "12.5320997238"
  },
  {
    "date": "2018-04-27",
    "id": "uptoken",
    "cap": "28615704.8087",
    "high": "0.227787002921",
    "low": "0.19787800312"
  },
  {
    "date": "2018-04-27",
    "id": "sentinel",
    "cap": "28492969.9873",
    "high": "0.0162703003734",
    "low": "0.0149382995442"
  },
  {
    "date": "2018-04-27",
    "id": "dmarket",
    "cap": "28479136.921",
    "high": "0.610743999481",
    "low": "0.566854000092"
  },
  {
    "date": "2018-04-27",
    "id": "educare",
    "cap": "28367185.0",
    "high": "0.0845173969865",
    "low": "0.0810490995646"
  },
  {
    "date": "2018-04-27",
    "id": "namecoin",
    "cap": "28123093.124",
    "high": "1.95141994953",
    "low": "1.88001000881"
  },
  {
    "date": "2018-04-27",
    "id": "potcoin",
    "cap": "27688708.0259",
    "high": "0.138114005327",
    "low": "0.125962004066"
  },
  {
    "date": "2018-04-27",
    "id": "fortuna",
    "cap": "27463657.1182",
    "high": "0.0738113969564",
    "low": "0.0666064023972"
  },
  {
    "date": "2018-04-27",
    "id": "u-network",
    "cap": "27055588.5351",
    "high": "0.00575945014134",
    "low": "0.00458073988557"
  },
  {
    "date": "2018-04-27",
    "id": "sentinel-chain",
    "cap": "26970980.3973",
    "high": "0.181296005845",
    "low": "0.158517003059"
  },
  {
    "date": "2018-04-27",
    "id": "aidoc",
    "cap": "26604813.0466",
    "high": "0.0639617964625",
    "low": "0.0600112006068"
  },
  {
    "date": "2018-04-27",
    "id": "hi-mutual-society",
    "cap": "26298302.67",
    "high": "0.0728238970041",
    "low": "0.0629191994667"
  },
  {
    "date": "2018-04-27",
    "id": "bean-cash",
    "cap": "26190100.206",
    "high": "0.0111760003492",
    "low": "0.01012550015"
  },
  {
    "date": "2018-04-27",
    "id": "restart-energy-mwat",
    "cap": "26137115.0",
    "high": "0.0658906027675",
    "low": "0.058518499136"
  },
  {
    "date": "2018-04-27",
    "id": "iocoin",
    "cap": "25859888.5298",
    "high": "1.66152000427",
    "low": "1.54386997223"
  },
  {
    "date": "2018-04-27",
    "id": "cappasity",
    "cap": "25416137.3579",
    "high": "0.0633907988667",
    "low": "0.0545763000846"
  },
  {
    "date": "2018-04-27",
    "id": "hempcoin",
    "cap": "25320627.0263",
    "high": "0.114909000695",
    "low": "0.106833003461"
  },
  {
    "date": "2018-04-27",
    "id": "zeusshield",
    "cap": "25097147.2612",
    "high": "0.0260073002428",
    "low": "0.0150186996907"
  },
  {
    "date": "2018-04-27",
    "id": "dadi",
    "cap": "24884369.196",
    "high": "0.349427014589",
    "low": "0.306672990322"
  },
  {
    "date": "2018-04-27",
    "id": "aeron",
    "cap": "24779560.0",
    "high": "1.92136001587",
    "low": "1.78190994263"
  },
  {
    "date": "2018-04-27",
    "id": "bitcoin-atom",
    "cap": "24505700.5189",
    "high": "1.42542004585",
    "low": "1.09660995007"
  },
  {
    "date": "2018-04-27",
    "id": "medical-chain",
    "cap": "24305115.0",
    "high": "0.137631997466",
    "low": "0.12535199523"
  },
  {
    "date": "2018-04-27",
    "id": "truechain",
    "cap": "24207950.0",
    "high": "1.04140996933",
    "low": "0.852033019066"
  },
  {
    "date": "2018-04-27",
    "id": "suncontract",
    "cap": "24199689.0823",
    "high": "0.218170002103",
    "low": "0.20182800293"
  },
  {
    "date": "2018-04-27",
    "id": "lympo",
    "cap": "24195017.693",
    "high": "0.043195001781",
    "low": "0.0395587012172"
  },
  {
    "date": "2018-04-27",
    "id": "ormeus-coin",
    "cap": "24080652.0648",
    "high": "1.48055994511",
    "low": "1.35046994686"
  },
  {
    "date": "2018-04-27",
    "id": "aichain",
    "cap": "23791008.2251",
    "high": "0.0505070015788",
    "low": "0.0441242009401"
  },
  {
    "date": "2018-04-27",
    "id": "alqo",
    "cap": "22653473.319",
    "high": "0.649040997028",
    "low": "0.471771985292"
  },
  {
    "date": "2018-04-27",
    "id": "agrello-delta",
    "cap": "22581921.0991",
    "high": "0.28075298667",
    "low": "0.261121988297"
  },
  {
    "date": "2018-04-27",
    "id": "carvertical",
    "cap": "22464490.3677",
    "high": "0.00452540023252",
    "low": "0.00381234008819"
  },
  {
    "date": "2018-04-27",
    "id": "datawallet",
    "cap": "22403399.3786",
    "high": "0.0628030002117",
    "low": "0.053381498903"
  },
  {
    "date": "2018-04-27",
    "id": "bloomtoken",
    "cap": "21607885.2418",
    "high": "0.475589007139",
    "low": "0.427316993475"
  },
  {
    "date": "2018-04-27",
    "id": "vericoin",
    "cap": "20707940.9977",
    "high": "0.714344978333",
    "low": "0.663739025593"
  },
  {
    "date": "2018-04-27",
    "id": "covesting",
    "cap": "20538350.0",
    "high": "1.27389001846",
    "low": "1.13066005707"
  },
  {
    "date": "2018-04-27",
    "id": "axpire",
    "cap": "20503023.5",
    "high": "0.0815088003874",
    "low": "0.0732903033495"
  },
  {
    "date": "2018-04-27",
    "id": "sibcoin",
    "cap": "20499163.4911",
    "high": "1.2926299572",
    "low": "1.03190994263"
  },
  {
    "date": "2018-04-27",
    "id": "attention-token-of-media",
    "cap": "20433953.6556",
    "high": "0.00462300982326",
    "low": "0.00329344999045"
  },
  {
    "date": "2018-04-27",
    "id": "omni",
    "cap": "20411997.3109",
    "high": "39.8582992554",
    "low": "36.3721008301"
  },
  {
    "date": "2018-04-27",
    "id": "grid",
    "cap": "20333212.839",
    "high": "0.575595021248",
    "low": "0.517112016678"
  },
  {
    "date": "2018-04-27",
    "id": "qbao",
    "cap": "20329775.8509",
    "high": "0.395098000765",
    "low": "0.309982985258"
  },
  {
    "date": "2018-04-27",
    "id": "gridcoin",
    "cap": "19994980.7497",
    "high": "0.058114901185",
    "low": "0.0505605004728"
  },
  {
    "date": "2018-04-27",
    "id": "faircoin",
    "cap": "19987316.2057",
    "high": "0.500185012817",
    "low": "0.375744998455"
  },
  {
    "date": "2018-04-27",
    "id": "flash",
    "cap": "19968120.0",
    "high": "0.0252103991807",
    "low": "0.0218032002449"
  },
  {
    "date": "2018-04-27",
    "id": "revolutionvr",
    "cap": "19912221.0",
    "high": "0.105361998081",
    "low": "0.0948200970888"
  },
  {
    "date": "2018-04-27",
    "id": "bitclave",
    "cap": "19288642.7888",
    "high": "0.0388184003532",
    "low": "0.0366295985878"
  },
  {
    "date": "2018-04-27",
    "id": "matryx",
    "cap": "19000801.0111",
    "high": "0.945008993149",
    "low": "0.818143010139"
  },
  {
    "date": "2018-04-27",
    "id": "rentberry",
    "cap": "18973882.3125",
    "high": "0.0742245018482",
    "low": "0.0551482997835"
  },
  {
    "date": "2018-04-27",
    "id": "hiveterminal-token",
    "cap": "18823012.5",
    "high": "0.0557424984872",
    "low": "0.0492562018335"
  },
  {
    "date": "2018-04-27",
    "id": "oax",
    "cap": "18591876.1378",
    "high": "0.777031004429",
    "low": "0.74221599102"
  },
  {
    "date": "2018-04-27",
    "id": "banyan-network",
    "cap": "18556384.6911",
    "high": "0.131052002311",
    "low": "0.116507001221"
  },
  {
    "date": "2018-04-27",
    "id": "whitecoin",
    "cap": "17953907.5018",
    "high": "0.0763984024525",
    "low": "0.0668317973614"
  },
  {
    "date": "2018-04-27",
    "id": "sureremit",
    "cap": "17910200.0",
    "high": "0.0397159010172",
    "low": "0.0344090014696"
  },
  {
    "date": "2018-04-27",
    "id": "pareto-rewards",
    "cap": "17772560.6681",
    "high": "0.0826136991382",
    "low": "0.0747845992446"
  },
  {
    "date": "2018-04-27",
    "id": "tokenclub",
    "cap": "17680104.7216",
    "high": "0.0457933992147",
    "low": "0.0293710008264"
  },
  {
    "date": "2018-04-27",
    "id": "incent",
    "cap": "17137410.8836",
    "high": "0.40910500288",
    "low": "0.372417986393"
  },
  {
    "date": "2018-04-27",
    "id": "te-food",
    "cap": "16986340.309",
    "high": "0.044237498194",
    "low": "0.038779001683"
  },
  {
    "date": "2018-04-27",
    "id": "blackmoon",
    "cap": "16982497.6076",
    "high": "0.834891021252",
    "low": "0.767212986946"
  },
  {
    "date": "2018-04-27",
    "id": "prizm",
    "cap": "16898589.1138",
    "high": "0.998004972935",
    "low": "0.892539978027"
  },
  {
    "date": "2018-04-27",
    "id": "hacken",
    "cap": "16648316.9839",
    "high": "4.15639019012",
    "low": "3.60606002808"
  },
  {
    "date": "2018-04-27",
    "id": "flo",
    "cap": "16531122.2252",
    "high": "0.125031992793",
    "low": "0.112942002714"
  },
  {
    "date": "2018-04-27",
    "id": "polybius",
    "cap": "16471709.9605",
    "high": "4.44407987595",
    "low": "4.09643983841"
  },
  {
    "date": "2018-04-27",
    "id": "bee-token",
    "cap": "16257311.4397",
    "high": "0.103982999921",
    "low": "0.0926373973489"
  },
  {
    "date": "2018-04-27",
    "id": "monetaryunit",
    "cap": "16176450.9976",
    "high": "0.133114993572",
    "low": "0.124499000609"
  },
  {
    "date": "2018-04-27",
    "id": "bismuth",
    "cap": "16159176.643",
    "high": "2.05538988113",
    "low": "1.73843002319"
  },
  {
    "date": "2018-04-27",
    "id": "olympus-labs",
    "cap": "15941639.0895",
    "high": "0.454340010881",
    "low": "0.397424012423"
  },
  {
    "date": "2018-04-27",
    "id": "bitdegree",
    "cap": "15667207.3387",
    "high": "0.0501715987921",
    "low": "0.0420349016786"
  },
  {
    "date": "2018-04-27",
    "id": "stox",
    "cap": "15614514.059",
    "high": "0.391544014215",
    "low": "0.364908993244"
  },
  {
    "date": "2018-04-27",
    "id": "zap",
    "cap": "15487055.3269",
    "high": "0.161711007357",
    "low": "0.134226992726"
  },
  {
    "date": "2018-04-27",
    "id": "lomocoin",
    "cap": "15058551.2251",
    "high": "0.07301209867",
    "low": "0.0651739016175"
  },
  {
    "date": "2018-04-27",
    "id": "bitgreen",
    "cap": "15047872.3037",
    "high": "5.37109994888",
    "low": "4.84609985352"
  },
  {
    "date": "2018-04-27",
    "id": "myriad",
    "cap": "15033673.111",
    "high": "0.0106979003176",
    "low": "0.00957368966192"
  },
  {
    "date": "2018-04-27",
    "id": "mediccoin",
    "cap": "14494622.205",
    "high": "0.13208399713",
    "low": "0.0681131035089"
  },
  {
    "date": "2018-04-27",
    "id": "snov",
    "cap": "14418437.9097",
    "high": "0.0408474989235",
    "low": "0.0356028005481"
  },
  {
    "date": "2018-04-27",
    "id": "bitsend",
    "cap": "14366726.176",
    "high": "0.800822973251",
    "low": "0.753185987473"
  },
  {
    "date": "2018-04-27",
    "id": "clams",
    "cap": "14097625.3258",
    "high": "4.99928998947",
    "low": "4.72077989578"
  },
  {
    "date": "2018-04-27",
    "id": "encrypgen",
    "cap": "14080114.3118",
    "high": "0.251305997372",
    "low": "0.227325007319"
  },
  {
    "date": "2018-04-27",
    "id": "bit-tube",
    "cap": "13927328.0764",
    "high": "0.363687992096",
    "low": "0.3141489923"
  },
  {
    "date": "2018-04-27",
    "id": "auctus",
    "cap": "13731931.4785",
    "high": "0.953278005123",
    "low": "0.774834990501"
  },
  {
    "date": "2018-04-27",
    "id": "etheroll",
    "cap": "13430302.5162",
    "high": "2.04717993736",
    "low": "1.89814996719"
  },
  {
    "date": "2018-04-27",
    "id": "cargox",
    "cap": "13336045.2283",
    "high": "0.114882998168",
    "low": "0.101980000734"
  },
  {
    "date": "2018-04-27",
    "id": "alis",
    "cap": "13293251.1555",
    "high": "0.3750680089",
    "low": "0.331465989351"
  },
  {
    "date": "2018-04-27",
    "id": "paragon",
    "cap": "13070283.9136",
    "high": "0.253996998072",
    "low": "0.194341003895"
  },
  {
    "date": "2018-04-27",
    "id": "patientory",
    "cap": "12974150.0",
    "high": "0.193269997835",
    "low": "0.183927997947"
  },
  {
    "date": "2018-04-27",
    "id": "decent-bet",
    "cap": "12899813.3981",
    "high": "0.118579000235",
    "low": "0.101765997708"
  },
  {
    "date": "2018-04-27",
    "id": "gobyte",
    "cap": "12638492.6704",
    "high": "9.80840015411",
    "low": "9.23945999146"
  },
  {
    "date": "2018-04-27",
    "id": "everus",
    "cap": "12481985.5686",
    "high": "0.16545599699",
    "low": "0.138310998678"
  },
  {
    "date": "2018-04-27",
    "id": "lala-world",
    "cap": "12214494.0205",
    "high": "0.0678348019719",
    "low": "0.0549506992102"
  },
  {
    "date": "2018-04-27",
    "id": "fluz-fluz",
    "cap": "12179249.544",
    "high": "0.0687758997083",
    "low": "0.0590769983828"
  },
  {
    "date": "2018-04-27",
    "id": "trueusd",
    "cap": "11980090.6976",
    "high": "1.00994002819",
    "low": "0.991057991982"
  },
  {
    "date": "2018-04-27",
    "id": "effect-ai",
    "cap": "11790733.5506",
    "high": "0.0690331012011",
    "low": "0.0608810000122"
  },
  {
    "date": "2018-04-27",
    "id": "syndicate",
    "cap": "11640589.9569",
    "high": "0.627497017384",
    "low": "0.579904019833"
  },
  {
    "date": "2018-04-27",
    "id": "leadcoin",
    "cap": "11102862.4608",
    "high": "0.0148200998083",
    "low": "0.01411630027"
  },
  {
    "date": "2018-04-27",
    "id": "worldcore",
    "cap": "10845762.1631",
    "high": "0.0642082989216",
    "low": "0.060380898416"
  },
  {
    "date": "2018-04-27",
    "id": "ip-exchange",
    "cap": "10630814.9323",
    "high": "0.0170958004892",
    "low": "0.0113901002333"
  },
  {
    "date": "2018-04-27",
    "id": "dubaicoin-dbix",
    "cap": "10625638.5877",
    "high": "4.9603099823",
    "low": "4.54936981201"
  },
  {
    "date": "2018-04-27",
    "id": "target-coin",
    "cap": "10570543.1564",
    "high": "0.012766899541",
    "low": "0.0110985003412"
  },
  {
    "date": "2018-04-27",
    "id": "solaris",
    "cap": "10536395.1424",
    "high": "9.15326023102",
    "low": "8.15406990051"
  },
  {
    "date": "2018-04-27",
    "id": "dether",
    "cap": "10375330.0",
    "high": "0.15638500452",
    "low": "0.128473997116"
  },
  {
    "date": "2018-04-27",
    "id": "coinfi",
    "cap": "10271444.9768",
    "high": "0.0643254965544",
    "low": "0.0582556016743"
  },
  {
    "date": "2018-04-27",
    "id": "atn",
    "cap": "10105308.5661",
    "high": "0.507865011692",
    "low": "0.465590000153"
  },
  {
    "date": "2018-04-27",
    "id": "auroracoin",
    "cap": "10021536.3057",
    "high": "1.27654004097",
    "low": "1.15746998787"
  },
  {
    "date": "2018-04-27",
    "id": "daneel",
    "cap": "9975074.42712",
    "high": "0.383850991726",
    "low": "0.168705999851"
  },
  {
    "date": "2018-04-27",
    "id": "dynamic",
    "cap": "9892654.55904",
    "high": "2.18892002106",
    "low": "2.02072000504"
  },
  {
    "date": "2018-04-27",
    "id": "pluton",
    "cap": "9859229.20045",
    "high": "15.8980998993",
    "low": "11.5991001129"
  },
  {
    "date": "2018-04-27",
    "id": "aventus",
    "cap": "9828120.0",
    "high": "1.72448003292",
    "low": "1.60816001892"
  },
  {
    "date": "2018-04-27",
    "id": "stealth",
    "cap": "9765591.64104",
    "high": "0.362533986568",
    "low": "0.340539008379"
  },
  {
    "date": "2018-04-27",
    "id": "payfair",
    "cap": "9684856.94384",
    "high": "0.115923002362",
    "low": "0.0980063006282"
  },
  {
    "date": "2018-04-27",
    "id": "adbank",
    "cap": "9665486.02812",
    "high": "0.0252267997712",
    "low": "0.0185077004135"
  },
  {
    "date": "2018-04-27",
    "id": "insights-network",
    "cap": "9575208.21191",
    "high": "0.0806725025177",
    "low": "0.0708606988192"
  },
  {
    "date": "2018-04-27",
    "id": "clearcoin",
    "cap": "9570480.0",
    "high": "0.0124618997797",
    "low": "0.010888800025"
  },
  {
    "date": "2018-04-27",
    "id": "espers",
    "cap": "9484575.3279",
    "high": "0.00046538899187",
    "low": "0.000372720009182"
  },
  {
    "date": "2018-04-27",
    "id": "guaranteed-ethurance-token-extra",
    "cap": "9447810.0",
    "high": "0.0344588011503",
    "low": "0.0309577994049"
  },
  {
    "date": "2018-04-27",
    "id": "bitshares-music",
    "cap": "9373272.28228",
    "high": "0.891533970833",
    "low": "0.642805993557"
  },
  {
    "date": "2018-04-27",
    "id": "atlant",
    "cap": "9199727.53897",
    "high": "0.263370990753",
    "low": "0.225082993507"
  },
  {
    "date": "2018-04-27",
    "id": "cvcoin",
    "cap": "9130497.94181",
    "high": "1.14706003666",
    "low": "0.928175985813"
  },
  {
    "date": "2018-04-27",
    "id": "mintcoin",
    "cap": "9062317.01385",
    "high": "0.000468559010187",
    "low": "0.000363258994184"
  },
  {
    "date": "2018-04-27",
    "id": "elixir",
    "cap": "8990289.70881",
    "high": "0.333730995655",
    "low": "0.280198007822"
  },
  {
    "date": "2018-04-27",
    "id": "bitqy",
    "cap": "8955003.40078",
    "high": "0.00363141996786",
    "low": "0.00287685007788"
  },
  {
    "date": "2018-04-27",
    "id": "eboostcoin",
    "cap": "8940940.0",
    "high": "0.461199998856",
    "low": "0.419324010611"
  },
  {
    "date": "2018-04-27",
    "id": "bitcrystals",
    "cap": "8692658.41946",
    "high": "0.402575999498",
    "low": "0.370862007141"
  },
  {
    "date": "2018-04-27",
    "id": "atbcoin",
    "cap": "8417688.22713",
    "high": "0.217251002789",
    "low": "0.196949005127"
  },
  {
    "date": "2018-04-27",
    "id": "curecoin",
    "cap": "8365502.85064",
    "high": "0.375366002321",
    "low": "0.348980009556"
  },
  {
    "date": "2018-04-27",
    "id": "pandacoin-pnd",
    "cap": "8255147.22134",
    "high": "0.00031152999145",
    "low": "0.000215288993786"
  },
  {
    "date": "2018-04-27",
    "id": "b2bx",
    "cap": "8185172.37916",
    "high": "0.537513971329",
    "low": "0.43431699276"
  },
  {
    "date": "2018-04-27",
    "id": "haven-protocol",
    "cap": "8037354.26638",
    "high": "5.35701990128",
    "low": "3.88300991058"
  },
  {
    "date": "2018-04-27",
    "id": "hellogold",
    "cap": "7993938.77819",
    "high": "0.0319866985083",
    "low": "0.025775000453"
  },
  {
    "date": "2018-04-27",
    "id": "ecobit",
    "cap": "7938711.11032",
    "high": "0.0223338995129",
    "low": "0.0178621001542"
  },
  {
    "date": "2018-04-27",
    "id": "geocoin",
    "cap": "7802567.80362",
    "high": "2.64077997208",
    "low": "2.40223002434"
  },
  {
    "date": "2018-04-27",
    "id": "privatix",
    "cap": "7793993.55436",
    "high": "7.63361978531",
    "low": "5.93019008636"
  },
  {
    "date": "2018-04-27",
    "id": "clearpoll",
    "cap": "7722250.07138",
    "high": "1.25648999214",
    "low": "1.09300994873"
  },
  {
    "date": "2018-04-27",
    "id": "adhive",
    "cap": "7684202.81197",
    "high": "0.0870610997081",
    "low": "0.075025498867"
  },
  {
    "date": "2018-04-27",
    "id": "artbyte",
    "cap": "7519506.2489",
    "high": "0.0102433003485",
    "low": "0.00948788970709"
  },
  {
    "date": "2018-04-27",
    "id": "hubii-network",
    "cap": "7478809.86911",
    "high": "0.558463990688",
    "low": "0.527536988258"
  },
  {
    "date": "2018-04-27",
    "id": "bitdice",
    "cap": "7453460.0",
    "high": "0.12048599869",
    "low": "0.0986199006438"
  },
  {
    "date": "2018-04-27",
    "id": "eroscoin",
    "cap": "7316517.8736",
    "high": "0.0434071011841",
    "low": "0.0391793996096"
  },
  {
    "date": "2018-04-27",
    "id": "leverj",
    "cap": "6989399.43143",
    "high": "0.0627129003406",
    "low": "0.0516091994941"
  },
  {
    "date": "2018-04-27",
    "id": "life",
    "cap": "6705308.4575",
    "high": "0.000555096019525",
    "low": "0.000276003003819"
  },
  {
    "date": "2018-04-27",
    "id": "viuly",
    "cap": "6643256.84597",
    "high": "0.0105026001111",
    "low": "0.00941749010235"
  },
  {
    "date": "2018-04-27",
    "id": "cryptoping",
    "cap": "6558645.59696",
    "high": "0.7047560215",
    "low": "0.647307991982"
  },
  {
    "date": "2018-04-27",
    "id": "exrnchain",
    "cap": "6507347.25",
    "high": "0.0000819373017293",
    "low": "0.0000618358972133"
  },
  {
    "date": "2018-04-27",
    "id": "aidcoin",
    "cap": "6483636.42321",
    "high": "0.18160200119",
    "low": "0.163176998496"
  },
  {
    "date": "2018-04-27",
    "id": "bitcoinz",
    "cap": "6421615.07645",
    "high": "0.00412190984935",
    "low": "0.00387821998447"
  },
  {
    "date": "2018-04-27",
    "id": "bitcoin-plus",
    "cap": "6401946.42251",
    "high": "60.9444999695",
    "low": "58.7561988831"
  },
  {
    "date": "2018-04-27",
    "id": "trueflip",
    "cap": "6303992.18436",
    "high": "1.13594996929",
    "low": "1.00220000744"
  },
  {
    "date": "2018-04-27",
    "id": "b3coin",
    "cap": "6184278.90664",
    "high": "0.00857650954276",
    "low": "0.00780300004408"
  },
  {
    "date": "2018-04-27",
    "id": "nework",
    "cap": "6150191.46268",
    "high": "0.0520225018263",
    "low": "0.0458413995802"
  },
  {
    "date": "2018-04-27",
    "id": "sharex",
    "cap": "6086555.19011",
    "high": "0.00993650965393",
    "low": "0.00887334998697"
  },
  {
    "date": "2018-04-27",
    "id": "stipend",
    "cap": "6067427.03582",
    "high": "2.10812997818",
    "low": "1.36694002151"
  },
  {
    "date": "2018-04-27",
    "id": "autonio",
    "cap": "5853608.91735",
    "high": "0.096039198339",
    "low": "0.0889225974679"
  },
  {
    "date": "2018-04-27",
    "id": "cryptopay",
    "cap": "5682444.63209",
    "high": "0.0846067965031",
    "low": "0.0653060004115"
  },
  {
    "date": "2018-04-27",
    "id": "qwark",
    "cap": "5591336.09508",
    "high": "0.116927996278",
    "low": "0.102407999337"
  },
  {
    "date": "2018-04-27",
    "id": "maxcoin",
    "cap": "5587475.96439",
    "high": "0.0946305021644",
    "low": "0.0859313011169"
  },
  {
    "date": "2018-04-27",
    "id": "sumokoin",
    "cap": "5440566.67807",
    "high": "2.13745999336",
    "low": "1.90576994419"
  },
  {
    "date": "2018-04-27",
    "id": "1world",
    "cap": "5383115.711",
    "high": "0.277805000544",
    "low": "0.257629007101"
  },
  {
    "date": "2018-04-27",
    "id": "hush",
    "cap": "5382637.242",
    "high": "1.55480003357",
    "low": "1.35942995548"
  },
  {
    "date": "2018-04-27",
    "id": "spreadcoin",
    "cap": "5325538.91033",
    "high": "0.574908971786",
    "low": "0.535246014595"
  },
  {
    "date": "2018-04-27",
    "id": "jet8",
    "cap": "5162313.88305",
    "high": "0.0218943990767",
    "low": "0.0180719997734"
  },
  {
    "date": "2018-04-27",
    "id": "social-send",
    "cap": "5113453.52235",
    "high": "0.196299999952",
    "low": "0.158553004265"
  },
  {
    "date": "2018-04-27",
    "id": "ethouse",
    "cap": "5030933.86272",
    "high": "0.0626923963428",
    "low": "0.04444969818"
  },
  {
    "date": "2018-04-27",
    "id": "universal-currency",
    "cap": "4945432.1622",
    "high": "0.429120004177",
    "low": "0.354813992977"
  },
  {
    "date": "2018-04-27",
    "id": "mywish",
    "cap": "4906771.12007",
    "high": "0.311648011208",
    "low": "0.254480987787"
  },
  {
    "date": "2018-04-27",
    "id": "aigang",
    "cap": "4839674.29834",
    "high": "0.273362010717",
    "low": "0.250450998545"
  },
  {
    "date": "2018-04-27",
    "id": "cannabiscoin",
    "cap": "4809038.56118",
    "high": "0.0678011029959",
    "low": "0.0618431009352"
  },
  {
    "date": "2018-04-27",
    "id": "2give",
    "cap": "4785793.19289",
    "high": "0.00983707979321",
    "low": "0.00894230045378"
  },
  {
    "date": "2018-04-27",
    "id": "goldmint",
    "cap": "4715392.47002",
    "high": "2.86565995216",
    "low": "2.10664010048"
  },
  {
    "date": "2018-04-27",
    "id": "1337coin",
    "cap": "4640530.34523",
    "high": "0.000186328004929",
    "low": "0.000114672999189"
  },
  {
    "date": "2018-04-27",
    "id": "biocoin",
    "cap": "4573710.27074",
    "high": "0.00836635008454",
    "low": "0.00735771004111"
  },
  {
    "date": "2018-04-27",
    "id": "adshares",
    "cap": "4537578.20924",
    "high": "0.260585993528",
    "low": "0.224252998829"
  },
  {
    "date": "2018-04-27",
    "id": "lampix",
    "cap": "4468454.79116",
    "high": "0.0367795005441",
    "low": "0.0320891998708"
  },
  {
    "date": "2018-04-27",
    "id": "bitcloud",
    "cap": "4453307.75386",
    "high": "0.22233299911",
    "low": "0.202659994364"
  },
  {
    "date": "2018-04-27",
    "id": "copytrack",
    "cap": "4423879.1414",
    "high": "0.225723996758",
    "low": "0.187479004264"
  },
  {
    "date": "2018-04-27",
    "id": "iungo",
    "cap": "4423480.0",
    "high": "0.126734003425",
    "low": "0.110587000847"
  },
  {
    "date": "2018-04-27",
    "id": "zeitcoin",
    "cap": "4420719.98685",
    "high": "0.000143999001011",
    "low": "0.0000898923026398"
  },
  {
    "date": "2018-04-27",
    "id": "open-trading-network",
    "cap": "4376725.95025",
    "high": "2.94464993477",
    "low": "2.14605998993"
  },
  {
    "date": "2018-04-27",
    "id": "startercoin",
    "cap": "4367886.13469",
    "high": "0.0278795994818",
    "low": "0.024624299258"
  },
  {
    "date": "2018-04-27",
    "id": "sether",
    "cap": "4327589.03831",
    "high": "0.276681005955",
    "low": "0.247783005238"
  },
  {
    "date": "2018-04-27",
    "id": "goodomy",
    "cap": "4161172.91362",
    "high": "0.0113743003458",
    "low": "0.00894130021334"
  },
  {
    "date": "2018-04-27",
    "id": "creditbit",
    "cap": "4157989.20766",
    "high": "0.267269998789",
    "low": "0.249871999025"
  },
  {
    "date": "2018-04-27",
    "id": "terracoin",
    "cap": "4054547.79074",
    "high": "0.18835799396",
    "low": "0.167290002108"
  },
  {
    "date": "2018-04-27",
    "id": "starbase",
    "cap": "4045143.75",
    "high": "0.0228278003633",
    "low": "0.021527800709"
  },
  {
    "date": "2018-04-27",
    "id": "dao-casino",
    "cap": "4003894.72648",
    "high": "0.0308353994042",
    "low": "0.0237779002637"
  },
  {
    "date": "2018-04-27",
    "id": "primalbase",
    "cap": "3713275.0",
    "high": "3142.04003906",
    "low": "2853.93994141"
  },
  {
    "date": "2018-04-27",
    "id": "evergreencoin",
    "cap": "3699045.42029",
    "high": "0.296294003725",
    "low": "0.276692986488"
  },
  {
    "date": "2018-04-27",
    "id": "audiocoin",
    "cap": "3676705.89773",
    "high": "0.0047123702243",
    "low": "0.00413622008637"
  },
  {
    "date": "2018-04-27",
    "id": "obsidian",
    "cap": "3553375.0",
    "high": "0.159325003624",
    "low": "0.136892005801"
  },
  {
    "date": "2018-04-27",
    "id": "buzzcoin",
    "cap": "3487924.88774",
    "high": "0.000278714986052",
    "low": "0.0000931468966883"
  },
  {
    "date": "2018-04-27",
    "id": "encryptotel",
    "cap": "3477401.91137",
    "high": "0.0825823023915",
    "low": "0.0469359010458"
  },
  {
    "date": "2018-04-27",
    "id": "xgox",
    "cap": "3474583.16268",
    "high": "0.00184770999476",
    "low": "0.00162233994342"
  },
  {
    "date": "2018-04-27",
    "id": "ixcoin",
    "cap": "3333605.21984",
    "high": "0.159641996026",
    "low": "0.14603599906"
  },
  {
    "date": "2018-04-27",
    "id": "piplcoin",
    "cap": "3318419.59942",
    "high": "0.0429870001972",
    "low": "0.0397680997849"
  },
  {
    "date": "2018-04-27",
    "id": "bezop",
    "cap": "3222228.85449",
    "high": "0.0856636986136",
    "low": "0.0761604979634"
  },
  {
    "date": "2018-04-27",
    "id": "rupee",
    "cap": "3146485.5535",
    "high": "0.177096992731",
    "low": "0.0904465019703"
  },
  {
    "date": "2018-04-27",
    "id": "vezt",
    "cap": "3013243.74891",
    "high": "0.0669253021479",
    "low": "0.060360699892"
  },
  {
    "date": "2018-04-27",
    "id": "sexcoin",
    "cap": "2958712.46598",
    "high": "0.0249365996569",
    "low": "0.023168200627"
  },
  {
    "date": "2018-04-27",
    "id": "eventchain",
    "cap": "2921583.96413",
    "high": "0.107837997377",
    "low": "0.091905400157"
  },
  {
    "date": "2018-04-27",
    "id": "jiyo-old",
    "cap": "2909937.92677",
    "high": "0.144507005811",
    "low": "0.105682000518"
  },
  {
    "date": "2018-04-27",
    "id": "e-gulden",
    "cap": "2885272.44362",
    "high": "0.19342200458",
    "low": "0.171621993184"
  },
  {
    "date": "2018-04-27",
    "id": "equitrader",
    "cap": "2806764.17845",
    "high": "0.280135989189",
    "low": "0.260758012533"
  },
  {
    "date": "2018-04-27",
    "id": "crave",
    "cap": "2764509.3392",
    "high": "0.217834994197",
    "low": "0.182429999113"
  },
  {
    "date": "2018-04-27",
    "id": "ace",
    "cap": "2730418.65272",
    "high": "0.330830007792",
    "low": "0.295971989632"
  },
  {
    "date": "2018-04-27",
    "id": "argentum",
    "cap": "2688987.23928",
    "high": "0.341708987951",
    "low": "0.263507008553"
  },
  {
    "date": "2018-04-27",
    "id": "imbrex",
    "cap": "2624113.79968",
    "high": "0.327836990356",
    "low": "0.296707004309"
  },
  {
    "date": "2018-04-27",
    "id": "magnet",
    "cap": "2617986.67616",
    "high": "0.121174998581",
    "low": "0.108999997377"
  },
  {
    "date": "2018-04-27",
    "id": "gcn-coin",
    "cap": "2504541.61401",
    "high": "0.0000359728983312",
    "low": "0.0000161168009072"
  },
  {
    "date": "2018-04-27",
    "id": "lethean",
    "cap": "2416145.16043",
    "high": "0.00656878016889",
    "low": "0.00551815005019"
  },
  {
    "date": "2018-04-27",
    "id": "darcrus",
    "cap": "2399666.07146",
    "high": "0.252712011337",
    "low": "0.176029995084"
  },
  {
    "date": "2018-04-27",
    "id": "crycash",
    "cap": "2375130.32327",
    "high": "0.644649982452",
    "low": "0.473630994558"
  },
  {
    "date": "2018-04-27",
    "id": "graft",
    "cap": "2327239.54727",
    "high": "0.0184486992657",
    "low": "0.0137312998995"
  },
  {
    "date": "2018-04-27",
    "id": "speed-mining-service",
    "cap": "2312739.03413",
    "high": "25.081199646",
    "low": "20.1485004425"
  },
  {
    "date": "2018-04-27",
    "id": "ergo",
    "cap": "2266048.226",
    "high": "6.40256023407",
    "low": "5.54872989655"
  },
  {
    "date": "2018-04-27",
    "id": "martexcoin",
    "cap": "2230434.14649",
    "high": "0.785969018936",
    "low": "0.705242991447"
  },
  {
    "date": "2018-04-27",
    "id": "ellaism",
    "cap": "2172821.56313",
    "high": "0.333189994097",
    "low": "0.298096001148"
  },
  {
    "date": "2018-04-27",
    "id": "wandx",
    "cap": "2160881.67105",
    "high": "0.223600000143",
    "low": "0.172448992729"
  },
  {
    "date": "2018-04-27",
    "id": "smileycoin",
    "cap": "2153781.75715",
    "high": "0.00010920099885",
    "low": "0.0000337216006301"
  },
  {
    "date": "2018-04-27",
    "id": "kz-cash",
    "cap": "2098563.90314",
    "high": "2.15930008888",
    "low": "1.69073998928"
  },
  {
    "date": "2018-04-27",
    "id": "innova",
    "cap": "2092444.47138",
    "high": "0.882712006569",
    "low": "0.737353980541"
  },
  {
    "date": "2018-04-27",
    "id": "ethersportz",
    "cap": "2065440.52178",
    "high": "0.518211007118",
    "low": "0.417970001698"
  },
  {
    "date": "2018-04-27",
    "id": "coinlancer",
    "cap": "2052700.32968",
    "high": "0.0298971999437",
    "low": "0.0266357008368"
  },
  {
    "date": "2018-04-27",
    "id": "ebtcnew",
    "cap": "2000941.08364",
    "high": "0.120141997933",
    "low": "0.10557000339"
  },
  {
    "date": "2018-04-27",
    "id": "chronologic",
    "cap": "1972077.07237",
    "high": "3.66738009453",
    "low": "2.96690988541"
  },
  {
    "date": "2018-04-27",
    "id": "kekcoin",
    "cap": "1939145.85862",
    "high": "0.204815000296",
    "low": "0.182326003909"
  },
  {
    "date": "2018-04-27",
    "id": "straks",
    "cap": "1926604.14742",
    "high": "0.578372001648",
    "low": "0.518242001534"
  },
  {
    "date": "2018-04-27",
    "id": "blocklancer",
    "cap": "1921429.19232",
    "high": "0.0198736991733",
    "low": "0.0149849001318"
  },
  {
    "date": "2018-04-27",
    "id": "biblepay",
    "cap": "1914627.78488",
    "high": "0.0037971700076",
    "low": "0.00253936997615"
  },
  {
    "date": "2018-04-27",
    "id": "bluecoin",
    "cap": "1904139.64827",
    "high": "0.00362810003571",
    "low": "0.003313370049"
  },
  {
    "date": "2018-04-27",
    "id": "anoncoin",
    "cap": "1887952.77425",
    "high": "0.937116980553",
    "low": "0.881771981716"
  },
  {
    "date": "2018-04-27",
    "id": "kobocoin",
    "cap": "1765381.04255",
    "high": "0.0993132963777",
    "low": "0.0675510019064"
  },
  {
    "date": "2018-04-27",
    "id": "ethbits",
    "cap": "1746490.36286",
    "high": "1.31461000443",
    "low": "1.25502002239"
  },
  {
    "date": "2018-04-27",
    "id": "oceanlab",
    "cap": "1657869.15",
    "high": "0.0368845015764",
    "low": "0.0312859006226"
  },
  {
    "date": "2018-04-27",
    "id": "octoin-coin",
    "cap": "1654265.36915",
    "high": "6.61691999435",
    "low": "2.65896010399"
  },
  {
    "date": "2018-04-27",
    "id": "latiumx",
    "cap": "1651926.51887",
    "high": "0.024570800364",
    "low": "0.0220132991672"
  },
  {
    "date": "2018-04-27",
    "id": "skincoin",
    "cap": "1609569.02346",
    "high": "0.0193015001714",
    "low": "0.0180478002876"
  },
  {
    "date": "2018-04-27",
    "id": "flypme",
    "cap": "1578009.3183",
    "high": "0.102268002927",
    "low": "0.0830762013793"
  },
  {
    "date": "2018-04-27",
    "id": "jesus-coin",
    "cap": "1574175.90157",
    "high": "0.0000993396970443",
    "low": "0.0000737825976103"
  },
  {
    "date": "2018-04-27",
    "id": "tidex-token",
    "cap": "1570273.91074",
    "high": "0.171939998865",
    "low": "0.146709993482"
  },
  {
    "date": "2018-04-27",
    "id": "carboncoin",
    "cap": "1439794.15048",
    "high": "0.000186119999853",
    "low": "0.0000935416028369"
  },
  {
    "date": "2018-04-27",
    "id": "arcticcoin",
    "cap": "1429863.00316",
    "high": "0.063690200448",
    "low": "0.0573485009372"
  },
  {
    "date": "2018-04-27",
    "id": "more-coin",
    "cap": "1337588.0",
    "high": "0.710296988487",
    "low": "0.654606997967"
  },
  {
    "date": "2018-04-27",
    "id": "42-coin",
    "cap": "1326216.26723",
    "high": "33830.1992188",
    "low": "31576.5996094"
  },
  {
    "date": "2018-04-27",
    "id": "galactrum",
    "cap": "1279408.63346",
    "high": "1.54334998131",
    "low": "1.23857998848"
  },
  {
    "date": "2018-04-27",
    "id": "vivo",
    "cap": "1206452.16315",
    "high": "0.775956988335",
    "low": "0.683660984039"
  },
  {
    "date": "2018-04-27",
    "id": "megacoin",
    "cap": "1196618.33847",
    "high": "0.0343939997256",
    "low": "0.0297203008085"
  },
  {
    "date": "2018-04-27",
    "id": "adzcoin",
    "cap": "1179529.25156",
    "high": "0.0332150012255",
    "low": "0.0242219995707"
  },
  {
    "date": "2018-04-27",
    "id": "dinastycoin",
    "cap": "1145324.40946",
    "high": "0.000923378975131",
    "low": "0.000627246976364"
  },
  {
    "date": "2018-04-27",
    "id": "platinumbar",
    "cap": "1097993.57288",
    "high": "1.68395996094",
    "low": "1.34363996983"
  },
  {
    "date": "2018-04-27",
    "id": "peepcoin",
    "cap": "1091626.55735",
    "high": "0.0000945619976847",
    "low": "0.0000875280020409"
  },
  {
    "date": "2018-04-27",
    "id": "draftcoin",
    "cap": "1069669.04841",
    "high": "0.157119005919",
    "low": "0.137315005064"
  },
  {
    "date": "2018-04-27",
    "id": "bata",
    "cap": "1063607.50062",
    "high": "0.213269993663",
    "low": "0.184153005481"
  },
  {
    "date": "2018-04-27",
    "id": "britcoin",
    "cap": "1040398.91236",
    "high": "0.183336004615",
    "low": "0.0258297994733"
  },
  {
    "date": "2018-04-27",
    "id": "zetacoin",
    "cap": "1037118.00299",
    "high": "0.00660631991923",
    "low": "0.00617461977527"
  },
  {
    "date": "2018-04-27",
    "id": "student-coin",
    "cap": "1021122.17595",
    "high": "0.0246865004301",
    "low": "0.0212539006025"
  },
  {
    "date": "2018-04-27",
    "id": "skeincoin",
    "cap": "1018928.36066",
    "high": "0.092871196568",
    "low": "0.068349301815"
  },
  {
    "date": "2018-04-27",
    "id": "zennies",
    "cap": "984892.905774",
    "high": "0.00112453999463",
    "low": "0.000984093057923"
  },
  {
    "date": "2018-04-27",
    "id": "ethereumcash",
    "cap": "942534.24",
    "high": "0.0813001021743",
    "low": "0.0667769983411"
  },
  {
    "date": "2018-04-27",
    "id": "procurrency",
    "cap": "937620.153531",
    "high": "0.01199979987",
    "low": "0.0091551002115"
  },
  {
    "date": "2018-04-27",
    "id": "cdx-network",
    "cap": "927512.25",
    "high": "0.0363826006651",
    "low": "0.0267558991909"
  },
  {
    "date": "2018-04-27",
    "id": "inflationcoin",
    "cap": "904451.562459",
    "high": "0.0000766267985455",
    "low": "0.0000160007002705"
  },
  {
    "date": "2018-04-27",
    "id": "qbic",
    "cap": "904231.785272",
    "high": "0.671303987503",
    "low": "0.59109300375"
  },
  {
    "date": "2018-04-27",
    "id": "authorship",
    "cap": "900229.768572",
    "high": "0.0107223000377",
    "low": "0.00940094981343"
  },
  {
    "date": "2018-04-27",
    "id": "startcoin",
    "cap": "898521.258663",
    "high": "0.0213890001178",
    "low": "0.0199318006635"
  },
  {
    "date": "2018-04-27",
    "id": "petrodollar",
    "cap": "884329.464994",
    "high": "0.0149804996327",
    "low": "0.0130206998438"
  },
  {
    "date": "2018-04-27",
    "id": "etheriya",
    "cap": "878502.513756",
    "high": "0.643545985222",
    "low": "0.555476009846"
  },
  {
    "date": "2018-04-27",
    "id": "adcoin",
    "cap": "863366.74158",
    "high": "0.14209599793",
    "low": "0.115441001952"
  },
  {
    "date": "2018-04-27",
    "id": "soma",
    "cap": "817397.548306",
    "high": "0.219070002437",
    "low": "0.168926000595"
  },
  {
    "date": "2018-04-27",
    "id": "cryptocarbon",
    "cap": "812948.534531",
    "high": "0.461786985397",
    "low": "0.191246002913"
  },
  {
    "date": "2018-04-27",
    "id": "bitradio",
    "cap": "742588.753581",
    "high": "0.123813003302",
    "low": "0.117227002978"
  },
  {
    "date": "2018-04-27",
    "id": "digitalcoin",
    "cap": "740481.115773",
    "high": "0.0288108997047",
    "low": "0.0256664007902"
  },
  {
    "date": "2018-04-27",
    "id": "happycoin",
    "cap": "736427.982981",
    "high": "0.0607035011053",
    "low": "0.0503694005311"
  },
  {
    "date": "2018-04-27",
    "id": "arbitragect",
    "cap": "727451.132804",
    "high": "0.00914711039513",
    "low": "0.00783422961831"
  },
  {
    "date": "2018-04-27",
    "id": "cream",
    "cap": "727079.734939",
    "high": "0.0183198004961",
    "low": "0.0151508999988"
  },
  {
    "date": "2018-04-27",
    "id": "suretly",
    "cap": "726191.235212",
    "high": "3.5357298851",
    "low": "3.27868008614"
  },
  {
    "date": "2018-04-27",
    "id": "insanecoin-insn",
    "cap": "719473.937761",
    "high": "0.0457703992724",
    "low": "0.0372942015529"
  },
  {
    "date": "2018-04-27",
    "id": "jetcoin",
    "cap": "714468.816103",
    "high": "0.110549002886",
    "low": "0.084021396935"
  },
  {
    "date": "2018-04-27",
    "id": "trollcoin",
    "cap": "710679.060681",
    "high": "0.00125762994867",
    "low": "0.00100368005224"
  },
  {
    "date": "2018-04-27",
    "id": "opal",
    "cap": "669438.692512",
    "high": "0.0471844002604",
    "low": "0.0363885983825"
  },
  {
    "date": "2018-04-27",
    "id": "bitbar",
    "cap": "662712.231043",
    "high": "20.8950004578",
    "low": "17.2656993866"
  },
  {
    "date": "2018-04-27",
    "id": "bitcoin-scrypt",
    "cap": "612903.85596",
    "high": "0.0424520000815",
    "low": "0.0338150002062"
  },
  {
    "date": "2018-04-27",
    "id": "hodlcoin",
    "cap": "588104.443971",
    "high": "0.00374846998602",
    "low": "0.0035785199143"
  },
  {
    "date": "2018-04-27",
    "id": "aquariuscoin",
    "cap": "545086.645925",
    "high": "0.375770002604",
    "low": "0.318955004215"
  },
  {
    "date": "2018-04-27",
    "id": "cryptonite",
    "cap": "540065.508686",
    "high": "0.00148562004324",
    "low": "0.00131018005777"
  },
  {
    "date": "2018-04-27",
    "id": "bitbtc",
    "cap": "535016.59008",
    "high": "14150.5",
    "low": "12731.7001953"
  },
  {
    "date": "2018-04-27",
    "id": "bitdeal",
    "cap": "523366.123471",
    "high": "0.00318920006976",
    "low": "0.00275053991936"
  },
  {
    "date": "2018-04-27",
    "id": "sugar-exchange",
    "cap": "518861.0",
    "high": "0.170857995749",
    "low": "0.131089001894"
  },
  {
    "date": "2018-04-27",
    "id": "motocoin",
    "cap": "517507.828945",
    "high": "0.0295548997819",
    "low": "0.0263461004943"
  },
  {
    "date": "2018-04-27",
    "id": "erc20",
    "cap": "514609.662369",
    "high": "0.00038866099203",
    "low": "0.000310433009872"
  },
  {
    "date": "2018-04-27",
    "id": "garlicoin",
    "cap": "512419.515541",
    "high": "0.060435000807",
    "low": "0.0510249994695"
  },
  {
    "date": "2018-04-27",
    "id": "mojocoin",
    "cap": "493066.062691",
    "high": "0.0485384985805",
    "low": "0.0384914986789"
  },
  {
    "date": "2018-04-27",
    "id": "ultracoin",
    "cap": "485483.123143",
    "high": "0.0120861995965",
    "low": "0.0104671996087"
  },
  {
    "date": "2018-04-27",
    "id": "mao-zedong",
    "cap": "480802.895069",
    "high": "0.0799733027816",
    "low": "0.0751077011228"
  },
  {
    "date": "2018-04-27",
    "id": "veros",
    "cap": "474994.4995",
    "high": "0.0648610964417",
    "low": "0.0519526004791"
  },
  {
    "date": "2018-04-27",
    "id": "elementrem",
    "cap": "443317.246268",
    "high": "0.0231036003679",
    "low": "0.0157734006643"
  },
  {
    "date": "2018-04-27",
    "id": "billionaire-token",
    "cap": "427264.680616",
    "high": "0.169100001454",
    "low": "0.120618000627"
  },
  {
    "date": "2018-04-27",
    "id": "supercoin",
    "cap": "408472.337328",
    "high": "0.0115283997729",
    "low": "0.00824381038547"
  },
  {
    "date": "2018-04-27",
    "id": "manna",
    "cap": "398632.523498",
    "high": "0.0119369002059",
    "low": "0.008967760019"
  },
  {
    "date": "2018-04-27",
    "id": "cryptojacks",
    "cap": "397046.744744",
    "high": "0.00102672004141",
    "low": "0.000898086000234"
  },
  {
    "date": "2018-04-27",
    "id": "goldblocks",
    "cap": "392674.780295",
    "high": "0.0279431007802",
    "low": "0.0253011994064"
  },
  {
    "date": "2018-04-27",
    "id": "blakecoin",
    "cap": "370962.78539",
    "high": "0.0278677009046",
    "low": "0.0216281991452"
  },
  {
    "date": "2018-04-27",
    "id": "pakcoin",
    "cap": "366389.822505",
    "high": "0.0078208995983",
    "low": "0.00685789994895"
  },
  {
    "date": "2018-04-27",
    "id": "speedcash",
    "cap": "361900.59151",
    "high": "1.03515994549",
    "low": "0.763854026794"
  },
  {
    "date": "2018-04-27",
    "id": "bitcoin-red",
    "cap": "357674.822388",
    "high": "0.0186666995287",
    "low": "0.016758499667"
  },
  {
    "date": "2018-04-27",
    "id": "cabbage",
    "cap": "353199.91242",
    "high": "0.0352802984416",
    "low": "0.024616099894"
  },
  {
    "date": "2018-04-27",
    "id": "bolivarcoin",
    "cap": "349615.21729",
    "high": "0.036663800478",
    "low": "0.0312936007977"
  },
  {
    "date": "2018-04-27",
    "id": "op-coin",
    "cap": "332006.507153",
    "high": "0.00260194996372",
    "low": "0.00138082995545"
  },
  {
    "date": "2018-04-27",
    "id": "securecoin",
    "cap": "322418.085341",
    "high": "0.0415535010397",
    "low": "0.0376348011196"
  },
  {
    "date": "2018-04-27",
    "id": "postcoin",
    "cap": "314954.269397",
    "high": "0.0242724008858",
    "low": "0.0190591998398"
  },
  {
    "date": "2018-04-27",
    "id": "chesscoin",
    "cap": "314205.95299",
    "high": "0.00603388017043",
    "low": "0.00554614001885"
  },
  {
    "date": "2018-04-27",
    "id": "coinonatx",
    "cap": "304460.506758",
    "high": "0.0250656995922",
    "low": "0.0163100995123"
  },
  {
    "date": "2018-04-27",
    "id": "onix",
    "cap": "299651.370603",
    "high": "0.0119826998562",
    "low": "0.0109230997041"
  },
  {
    "date": "2018-04-27",
    "id": "ethereum-gold",
    "cap": "286546.8",
    "high": "0.0279453992844",
    "low": "0.0227908995003"
  },
  {
    "date": "2018-04-27",
    "id": "bitgold",
    "cap": "277731.9542",
    "high": "1614.67004395",
    "low": "1465.25"
  },
  {
    "date": "2018-04-27",
    "id": "digital-money-bits",
    "cap": "274314.708761",
    "high": "0.00398690998554",
    "low": "0.00322995008901"
  },
  {
    "date": "2018-04-27",
    "id": "grimcoin",
    "cap": "273761.30215",
    "high": "0.00331512000412",
    "low": "0.00229830993339"
  },
  {
    "date": "2018-04-27",
    "id": "emerald",
    "cap": "266802.48096",
    "high": "0.0146190002561",
    "low": "0.0139562003314"
  },
  {
    "date": "2018-04-27",
    "id": "atomic-coin",
    "cap": "261103.808204",
    "high": "0.0180450007319",
    "low": "0.0165617000312"
  },
  {
    "date": "2018-04-27",
    "id": "bigup",
    "cap": "253785.431314",
    "high": "0.000278782012174",
    "low": "0.000104671002191"
  },
  {
    "date": "2018-04-27",
    "id": "ammo-reloaded",
    "cap": "250496.553051",
    "high": "0.00337362010032",
    "low": "0.00322066992521"
  },
  {
    "date": "2018-04-27",
    "id": "berncash",
    "cap": "235374.513772",
    "high": "0.00344096007757",
    "low": "0.0031629500445"
  },
  {
    "date": "2018-04-27",
    "id": "neuro",
    "cap": "231170.01945",
    "high": "0.00678688986227",
    "low": "0.00405044993386"
  },
  {
    "date": "2018-04-27",
    "id": "nekonium",
    "cap": "224389.106646",
    "high": "0.0259007997811",
    "low": "0.0186978001148"
  },
  {
    "date": "2018-04-27",
    "id": "quebecoin",
    "cap": "223139.298542",
    "high": "0.016068700701",
    "low": "0.0138056995347"
  },
  {
    "date": "2018-04-27",
    "id": "bitcoin-planet",
    "cap": "212556.71511",
    "high": "0.0403738990426",
    "low": "0.0168229006231"
  },
  {
    "date": "2018-04-27",
    "id": "signatum",
    "cap": "212510.917637",
    "high": "0.00241725007072",
    "low": "0.00196819007397"
  },
  {
    "date": "2018-04-27",
    "id": "globaltoken",
    "cap": "205207.072544",
    "high": "0.0074553899467",
    "low": "0.0065127001144"
  },
  {
    "date": "2018-04-27",
    "id": "rubies",
    "cap": "191418.78995",
    "high": "0.0197468008846",
    "low": "0.0183786991984"
  },
  {
    "date": "2018-04-27",
    "id": "independent-money-system",
    "cap": "189435.842367",
    "high": "0.0409336984158",
    "low": "0.0352836996317"
  },
  {
    "date": "2018-04-27",
    "id": "trident",
    "cap": "188897.1576",
    "high": "0.206165999174",
    "low": "0.137328997254"
  },
  {
    "date": "2018-04-27",
    "id": "shadow-token",
    "cap": "188860.0",
    "high": "0.043472699821",
    "low": "0.0268811993301"
  },
  {
    "date": "2018-04-27",
    "id": "briacoin",
    "cap": "185146.956498",
    "high": "0.249699994922",
    "low": "0.15000000596"
  },
  {
    "date": "2018-04-27",
    "id": "boostcoin",
    "cap": "181045.144545",
    "high": "0.0175065994263",
    "low": "0.00901676993817"
  },
  {
    "date": "2018-04-27",
    "id": "amsterdamcoin",
    "cap": "179648.453681",
    "high": "0.00384217989631",
    "low": "0.0035785199143"
  },
  {
    "date": "2018-04-27",
    "id": "parkbyte",
    "cap": "158547.749226",
    "high": "0.0393588989973",
    "low": "0.0332802012563"
  },
  {
    "date": "2018-04-27",
    "id": "bankcoin",
    "cap": "153203.455836",
    "high": "0.0220221001655",
    "low": "0.0141906999052"
  },
  {
    "date": "2018-04-27",
    "id": "secretcoin",
    "cap": "144135.969068",
    "high": "0.0356823988259",
    "low": "0.0340854004025"
  },
  {
    "date": "2018-04-27",
    "id": "bumbacoin",
    "cap": "143534.287261",
    "high": "0.00706026004627",
    "low": "0.00599020021036"
  },
  {
    "date": "2018-04-27",
    "id": "theresa-may-coin",
    "cap": "137265.555816",
    "high": "0.00431226985529",
    "low": "0.00335193006322"
  },
  {
    "date": "2018-04-27",
    "id": "hicoin",
    "cap": "134102.864561",
    "high": "0.000710779975634",
    "low": "0.00054740998894"
  },
  {
    "date": "2018-04-27",
    "id": "brat",
    "cap": "131390.56",
    "high": "0.000889856019057",
    "low": "0.00074492697604"
  },
  {
    "date": "2018-04-27",
    "id": "biteur",
    "cap": "131344.23582",
    "high": "1.3268699646",
    "low": "1.21885001659"
  },
  {
    "date": "2018-04-27",
    "id": "advanced-internet-blocks",
    "cap": "123688.88418",
    "high": "0.00497103016824",
    "low": "0.00383718009107"
  },
  {
    "date": "2018-04-27",
    "id": "guccionecoin",
    "cap": "123406.861484",
    "high": "0.00637240009382",
    "low": "0.00566858006641"
  },
  {
    "date": "2018-04-27",
    "id": "bitcoin-21",
    "cap": "120408.787706",
    "high": "0.158552005887",
    "low": "0.150033995509"
  },
  {
    "date": "2018-04-27",
    "id": "bitcoal",
    "cap": "111899.25",
    "high": "0.0279258992523",
    "low": "0.0248665008694"
  },
  {
    "date": "2018-04-27",
    "id": "dalecoin",
    "cap": "108163.997126",
    "high": "0.264494985342",
    "low": "0.232978001237"
  },
  {
    "date": "2018-04-27",
    "id": "acoin",
    "cap": "107364.181956",
    "high": "0.102591998875",
    "low": "0.0845277011395"
  },
  {
    "date": "2018-04-27",
    "id": "bolenum",
    "cap": "98714.0",
    "high": "0.0103043001145",
    "low": "0.00843282043934"
  },
  {
    "date": "2018-04-27",
    "id": "benjirolls",
    "cap": "97345.5520025",
    "high": "0.0049212500453",
    "low": "0.0039808601141"
  },
  {
    "date": "2018-04-27",
    "id": "coinonat",
    "cap": "97060.15224",
    "high": "0.0117205996066",
    "low": "0.0102201001719"
  },
  {
    "date": "2018-04-27",
    "id": "joincoin",
    "cap": "91690.4102223",
    "high": "0.0311123002321",
    "low": "0.0294336993247"
  },
  {
    "date": "2018-04-27",
    "id": "eryllium",
    "cap": "88185.6941456",
    "high": "0.0185189992189",
    "low": "0.015701700002"
  },
  {
    "date": "2018-04-27",
    "id": "allsafe",
    "cap": "88054.1106486",
    "high": "0.0107987998053",
    "low": "0.00968305021524"
  },
  {
    "date": "2018-04-27",
    "id": "cannation",
    "cap": "84340.6739825",
    "high": "0.036637801677",
    "low": "0.0296930000186"
  },
  {
    "date": "2018-04-27",
    "id": "californium",
    "cap": "77828.076529",
    "high": "0.0334550999105",
    "low": "0.0318487994373"
  },
  {
    "date": "2018-04-27",
    "id": "songcoin",
    "cap": "66376.222725",
    "high": "0.0024042900186",
    "low": "0.00197115004994"
  },
  {
    "date": "2018-04-27",
    "id": "zozocoin",
    "cap": "62891.9391338",
    "high": "0.127212002873",
    "low": "0.106461003423"
  },
  {
    "date": "2018-04-27",
    "id": "citadel",
    "cap": "56648.0431327",
    "high": "0.0109705999494",
    "low": "0.00984092988074"
  },
  {
    "date": "2018-04-27",
    "id": "dreamcoin",
    "cap": "48194.1023865",
    "high": "0.0204291995615",
    "low": "0.0186515003443"
  },
  {
    "date": "2018-04-27",
    "id": "iconic",
    "cap": "46663.8038574",
    "high": "0.080896101892",
    "low": "0.0509448982775"
  },
  {
    "date": "2018-04-27",
    "id": "veltor",
    "cap": "43136.314207",
    "high": "0.0879015997052",
    "low": "0.0777434036136"
  },
  {
    "date": "2018-04-27",
    "id": "litecoin-ultra",
    "cap": "41969.3722824",
    "high": "0.0459876991808",
    "low": "0.0390216000378"
  },
  {
    "date": "2018-04-27",
    "id": "arbit",
    "cap": "38896.3699128",
    "high": "0.00534042995423",
    "low": "0.00474154017866"
  },
  {
    "date": "2018-04-27",
    "id": "luna-coin",
    "cap": "38646.5326324",
    "high": "0.0410359986126",
    "low": "0.022647600621"
  },
  {
    "date": "2018-04-27",
    "id": "doubloon",
    "cap": "36505.6832474",
    "high": "0.00204821000807",
    "low": "0.0019199999515"
  },
  {
    "date": "2018-04-27",
    "id": "javascript-token",
    "cap": "35711.6746863",
    "high": "0.0047036302276",
    "low": "0.00433488981798"
  },
  {
    "date": "2018-04-27",
    "id": "vector",
    "cap": "33859.8668793",
    "high": "0.00204821000807",
    "low": "0.00182857003529"
  },
  {
    "date": "2018-04-27",
    "id": "wild-beast-block",
    "cap": "32924.4723832",
    "high": "0.224965006113",
    "low": "0.180984005332"
  },
  {
    "date": "2018-04-27",
    "id": "playercoin",
    "cap": "31419.405604",
    "high": "0.00102409999818",
    "low": "0.000894629978575"
  },
  {
    "date": "2018-04-27",
    "id": "plncoin",
    "cap": "22933.38872",
    "high": "0.00158051005565",
    "low": "0.00134195003193"
  },
  {
    "date": "2018-04-27",
    "id": "bitvolt",
    "cap": "22260.3412119",
    "high": "0.00140567997005",
    "low": "0.00127999996766"
  },
  {
    "date": "2018-04-27",
    "id": "save-and-gain",
    "cap": "22149.0646978",
    "high": "0.0116675999016",
    "low": "0.00683867000043"
  },
  {
    "date": "2018-04-27",
    "id": "anarchistsprime",
    "cap": "21197.5750608",
    "high": "0.00721313012764",
    "low": "0.00394788989797"
  },
  {
    "date": "2018-04-27",
    "id": "argus",
    "cap": "18515.2324527",
    "high": "0.0205553993583",
    "low": "0.016123700887"
  },
  {
    "date": "2018-04-27",
    "id": "concoin",
    "cap": "10986.4038716",
    "high": "0.0163628999144",
    "low": "0.014761400409"
  },
  {
    "date": "2018-04-27",
    "id": "magnum",
    "cap": "7785.35831965",
    "high": "0.00187422998715",
    "low": "0.00182857003529"
  },
  {
    "date": "2018-04-27",
    "id": "aditus",
    "cap": "-1",
    "high": "0.0172680001706",
    "low": "0.0139162996784"
  },
  {
    "date": "2018-04-27",
    "id": "altcommunity-coin",
    "cap": "-1",
    "high": "0.84331202507",
    "low": "0.311040014029"
  },
  {
    "date": "2018-04-27",
    "id": "amlt",
    "cap": "-1",
    "high": "0.0567945986986",
    "low": "0.0439113005996"
  },
  {
    "date": "2018-04-27",
    "id": "bastonet",
    "cap": "-1",
    "high": "0.00084340502508",
    "low": "0.000805167015642"
  },
  {
    "date": "2018-04-27",
    "id": "belacoin",
    "cap": "-1",
    "high": "0.186486005783",
    "low": "0.181942999363"
  },
  {
    "date": "2018-04-27",
    "id": "bitcoin-god",
    "cap": "-1",
    "high": "45.034198761",
    "low": "35.1152992249"
  },
  {
    "date": "2018-04-27",
    "id": "bitcoinx",
    "cap": "-1",
    "high": "0.0166443996131",
    "low": "0.012939600274"
  },
  {
    "date": "2018-04-27",
    "id": "lightning-bitcoin",
    "cap": "-1",
    "high": "64.7962036133",
    "low": "38.0969009399"
  },
  {
    "date": "2018-04-27",
    "id": "levocoin",
    "cap": "-1",
    "high": "0.00148960994557",
    "low": "0.00137143000029"
  },
  {
    "date": "2018-04-27",
    "id": "maggie",
    "cap": "-1",
    "high": "0.0228821001947",
    "low": "0.013215799816"
  },
  {
    "date": "2018-04-27",
    "id": "read",
    "cap": "-1",
    "high": "0.0236361995339",
    "low": "0.020539900288"
  },
  {
    "date": "2018-04-27",
    "id": "eosdac",
    "cap": "-1",
    "high": "0.192537993193",
    "low": "0.145717993379"
  },
  {
    "date": "2018-04-27",
    "id": "chatcoin",
    "cap": "-1",
    "high": "0.128681004047",
    "low": "0.118845000863"
  },
  {
    "date": "2018-04-27",
    "id": "aidos-kuneen",
    "cap": "-1",
    "high": "16.8859996796",
    "low": "14.337100029"
  },
  {
    "date": "2018-04-27",
    "id": "snipcoin",
    "cap": "-1",
    "high": "0.00127886002883",
    "low": "0.00113124004565"
  },
  {
    "date": "2018-04-27",
    "id": "animation-vision-cash",
    "cap": "-1",
    "high": "0.0088426200673",
    "low": "0.00767988990992"
  },
  {
    "date": "2018-04-27",
    "id": "minex",
    "cap": "-1",
    "high": "0.0123648000881",
    "low": "0.011703199707"
  },
  {
    "date": "2018-04-27",
    "id": "budbo",
    "cap": "-1",
    "high": "0.0497933998704",
    "low": "0.0407624989748"
  },
  {
    "date": "2018-04-27",
    "id": "dero",
    "cap": "-1",
    "high": "3.23430991173",
    "low": "2.56819009781"
  },
  {
    "date": "2018-04-27",
    "id": "dragon-coins",
    "cap": "-1",
    "high": "0.744552016258",
    "low": "0.647750020027"
  },
  {
    "date": "2018-04-27",
    "id": "aces",
    "cap": "-1",
    "high": "0.000867086986545",
    "low": "0.000268820003839"
  },
  {
    "date": "2018-04-27",
    "id": "super-bitcoin",
    "cap": "-1",
    "high": "32.4785995483",
    "low": "25.7185993195"
  },
  {
    "date": "2018-04-27",
    "id": "btcmoon",
    "cap": "-1",
    "high": "0.00717112980783",
    "low": "0.00537646003067"
  },
  {
    "date": "2018-04-27",
    "id": "ipchain",
    "cap": "-1",
    "high": "0.53908097744",
    "low": "0.500286996365"
  },
  {
    "date": "2018-04-27",
    "id": "ethereum-lite",
    "cap": "-1",
    "high": "0.342413008213",
    "low": "0.279092997313"
  },
  {
    "date": "2018-04-27",
    "id": "safe-trade-coin",
    "cap": "-1",
    "high": "0.00259008002467",
    "low": "0.00205764989369"
  },
  {
    "date": "2018-04-27",
    "id": "torque",
    "cap": "-1",
    "high": "0.00152306002565",
    "low": "0.00128233002033"
  },
  {
    "date": "2018-04-27",
    "id": "ofcoin",
    "cap": "-1",
    "high": "0.00165056996047",
    "low": "0.0014830599539"
  },
  {
    "date": "2018-04-27",
    "id": "jingtum-tech",
    "cap": "-1",
    "high": "0.0067774001509",
    "low": "0.00620819022879"
  },
  {
    "date": "2018-04-27",
    "id": "first-bitcoin",
    "cap": "-1",
    "high": "0.0325850993395",
    "low": "0.0240893997252"
  },
  {
    "date": "2018-04-27",
    "id": "runners",
    "cap": "-1",
    "high": "0.000374847004423",
    "low": "0.000357851997251"
  },
  {
    "date": "2018-04-27",
    "id": "dynamiccoin",
    "cap": "-1",
    "high": "0.00121456000488",
    "low": "0.000901498016901"
  },
  {
    "date": "2018-04-27",
    "id": "betacoin",
    "cap": "-1",
    "high": "0.0127138998359",
    "low": "0.00595365976915"
  },
  {
    "date": "2018-04-27",
    "id": "pundi-x",
    "cap": "-1",
    "high": "0.00477016018704",
    "low": "0.00437150988728"
  },
  {
    "date": "2018-04-27",
    "id": "blockcdn",
    "cap": "-1",
    "high": "0.0557609982789",
    "low": "0.0458057001233"
  },
  {
    "date": "2018-04-27",
    "id": "blakestar",
    "cap": "-1",
    "high": "0.0901362970471",
    "low": "0.0758707001805"
  },
  {
    "date": "2018-04-27",
    "id": "rabbitcoin",
    "cap": "-1",
    "high": "0.000082846301666",
    "low": "0.0000218012992264"
  },
  {
    "date": "2018-04-27",
    "id": "mktcoin",
    "cap": "-1",
    "high": "0.0247732996941",
    "low": "0.0203185006976"
  },
  {
    "date": "2018-04-27",
    "id": "wink",
    "cap": "-1",
    "high": "0.000744987977669",
    "low": "0.000634584983345"
  },
  {
    "date": "2018-04-27",
    "id": "clubcoin",
    "cap": "-1",
    "high": "0.553844988346",
    "low": "0.452414989471"
  },
  {
    "date": "2018-04-27",
    "id": "birds",
    "cap": "-1",
    "high": "0.000281134998659",
    "low": "0.000268389005214"
  },
  {
    "date": "2018-04-27",
    "id": "comsa-xem",
    "cap": "-1",
    "high": "0.876075029373",
    "low": "0.617276012897"
  },
  {
    "date": "2018-04-27",
    "id": "starcointv",
    "cap": "-1",
    "high": "0.0468222014606",
    "low": "0.0362741984427"
  },
  {
    "date": "2018-04-27",
    "id": "exchange-union",
    "cap": "-1",
    "high": "7.48698997498",
    "low": "6.58811998367"
  },
  {
    "date": "2018-04-27",
    "id": "molecular-future",
    "cap": "-1",
    "high": "0.367561995983",
    "low": "0.331768006086"
  },
  {
    "date": "2018-04-27",
    "id": "show",
    "cap": "-1",
    "high": "0.00447254022583",
    "low": "0.00377849000506"
  },
  {
    "date": "2018-04-27",
    "id": "syncfab",
    "cap": "-1",
    "high": "0.0401738993824",
    "low": "0.0361914001405"
  },
  {
    "date": "2018-04-27",
    "id": "win-coin",
    "cap": "-1",
    "high": "0.787279009819",
    "low": "0.735139012337"
  },
  {
    "date": "2018-04-27",
    "id": "greenmed",
    "cap": "-1",
    "high": "0.174968004227",
    "low": "0.132171005011"
  },
  {
    "date": "2018-04-27",
    "id": "valuechain",
    "cap": "-1",
    "high": "0.105718001723",
    "low": "0.0888878032565"
  },
  {
    "date": "2018-04-27",
    "id": "halalchain",
    "cap": "-1",
    "high": "0.214526996017",
    "low": "0.158277004957"
  },
  {
    "date": "2018-04-27",
    "id": "content-and-ad-network",
    "cap": "-1",
    "high": "0.0180262997746",
    "low": "0.0155669003725"
  },
  {
    "date": "2018-04-27",
    "id": "francs",
    "cap": "-1",
    "high": "0.0535548999906",
    "low": "0.0447796992958"
  },
  {
    "date": "2018-04-27",
    "id": "mark-space",
    "cap": "-1",
    "high": "0.0984890013933",
    "low": "0.0812290981412"
  },
  {
    "date": "2018-04-27",
    "id": "cfun",
    "cap": "-1",
    "high": "0.0133284004405",
    "low": "0.0100760003552"
  },
  {
    "date": "2018-04-27",
    "id": "oceanchain",
    "cap": "-1",
    "high": "0.0161373000592",
    "low": "0.0103499004617"
  },
  {
    "date": "2018-04-27",
    "id": "infinity-economics",
    "cap": "-1",
    "high": "0.0122028999031",
    "low": "0.0109743997455"
  },
  {
    "date": "2018-04-27",
    "id": "axiom",
    "cap": "-1",
    "high": "0.0133878001943",
    "low": "0.0127037996426"
  },
  {
    "date": "2018-04-27",
    "id": "sparkspay",
    "cap": "-1",
    "high": "0.256608009338",
    "low": "0.0869586989284"
  },
  {
    "date": "2018-04-27",
    "id": "fairgame",
    "cap": "-1",
    "high": "0.047321099788",
    "low": "0.036370601505"
  },
  {
    "date": "2018-04-27",
    "id": "acute-angle-cloud",
    "cap": "-1",
    "high": "0.127340003848",
    "low": "0.111553996801"
  },
  {
    "date": "2018-04-27",
    "id": "consensus",
    "cap": "-1",
    "high": "0.0291316006333",
    "low": "0.0242925006896"
  },
  {
    "date": "2018-04-27",
    "id": "avatarcoin",
    "cap": "-1",
    "high": "0.0893073007464",
    "low": "0.0734490975738"
  },
  {
    "date": "2018-04-27",
    "id": "unlimitedip",
    "cap": "-1",
    "high": "0.0489713996649",
    "low": "0.0420903004706"
  },
  {
    "date": "2018-04-27",
    "id": "quotient",
    "cap": "-1",
    "high": "0.00402959994972",
    "low": "0.00350120989606"
  },
  {
    "date": "2018-04-27",
    "id": "gold-reward-token",
    "cap": "-1",
    "high": "0.0130155002698",
    "low": "0.0112076001242"
  },
  {
    "date": "2018-04-27",
    "id": "coinmeet",
    "cap": "-1",
    "high": "0.0644102990627",
    "low": "0.0590448006988"
  },
  {
    "date": "2018-04-27",
    "id": "msd",
    "cap": "-1",
    "high": "0.0225070994347",
    "low": "0.0187784992158"
  },
  {
    "date": "2018-04-27",
    "id": "comsa-eth",
    "cap": "-1",
    "high": "0.83222001791",
    "low": "0.602364003658"
  },
  {
    "date": "2018-04-27",
    "id": "tezos",
    "cap": "-1",
    "high": "3.76618003845",
    "low": "3.40277004242"
  },
  {
    "date": "2018-04-27",
    "id": "bitstation",
    "cap": "-1",
    "high": "0.00326150003821",
    "low": "0.00283385999501"
  },
  {
    "date": "2018-04-27",
    "id": "sigmacoin",
    "cap": "-1",
    "high": "0.0265145003796",
    "low": "0.0193863008171"
  },
  {
    "date": "2018-04-27",
    "id": "filecoin",
    "cap": "-1",
    "high": "14.9718999863",
    "low": "14.1922998428"
  },
  {
    "date": "2018-04-27",
    "id": "peculium",
    "cap": "-1",
    "high": "0.00409252988175",
    "low": "0.00362201989628"
  },
  {
    "date": "2018-04-27",
    "id": "acchain",
    "cap": "-1",
    "high": "0.579581975937",
    "low": "0.0845121964812"
  },
  {
    "date": "2018-04-27",
    "id": "encryptotel-eth",
    "cap": "-1",
    "high": "0.0551395006478",
    "low": "0.0498514994979"
  }
]