[
  {
    "date": "2019-02-10",
    "id": "bitcoin",
    "cap": "64694025950.7",
    "high": "3695.03601276",
    "low": "3640.97995463"
  },
  {
    "date": "2019-02-10",
    "id": "bitcoin-cash",
    "cap": "2247451284.57",
    "high": "129.022869395",
    "low": "122.226344701"
  },
  {
    "date": "2019-02-10",
    "id": "binance-coin",
    "cap": "1300443647.11",
    "high": "9.33729187414",
    "low": "8.85615986432"
  },
  {
    "date": "2019-02-10",
    "id": "bitcoin-sv",
    "cap": "1173301756.9",
    "high": "66.6121753642",
    "low": "63.802948684"
  },
  {
    "date": "2019-02-10",
    "id": "nem",
    "cap": "360979001.667",
    "high": "0.0407901091262",
    "low": "0.0389827982194"
  },
  {
    "date": "2019-02-10",
    "id": "usd-coin",
    "cap": "262005710.303",
    "high": "1.02054996755",
    "low": "1.01024089954"
  },
  {
    "date": "2019-02-10",
    "id": "bitcoin-gold",
    "cap": "188141228.655",
    "high": "10.8097311989",
    "low": "10.350110409"
  },
  {
    "date": "2019-02-10",
    "id": "holo",
    "cap": "155469862.86",
    "high": "0.00117835264673",
    "low": "0.00108299758733"
  },
  {
    "date": "2019-02-10",
    "id": "basic-attention-token",
    "cap": "153676840.317",
    "high": "0.129991978916",
    "low": "0.118767437576"
  },
  {
    "date": "2019-02-10",
    "id": "augur",
    "cap": "150257508.996",
    "high": "13.8668349726",
    "low": "13.380792439"
  },
  {
    "date": "2019-02-10",
    "id": "0x",
    "cap": "146315717.227",
    "high": "0.252410109911",
    "low": "0.243843664553"
  },
  {
    "date": "2019-02-10",
    "id": "bytecoin-bcn",
    "cap": "116809743.895",
    "high": "0.000662688650633",
    "low": "0.000611254234949"
  },
  {
    "date": "2019-02-10",
    "id": "bitcoin-diamond",
    "cap": "112926197.641",
    "high": "0.755141526576",
    "low": "0.725261552165"
  },
  {
    "date": "2019-02-10",
    "id": "digibyte",
    "cap": "105523807.208",
    "high": "0.00966681457081",
    "low": "0.00907372409085"
  },
  {
    "date": "2019-02-10",
    "id": "aeternity",
    "cap": "91923196.8512",
    "high": "0.403417286468",
    "low": "0.384796837864"
  },
  {
    "date": "2019-02-10",
    "id": "ark",
    "cap": "59135196.8374",
    "high": "0.858090894425",
    "low": "0.400994795954"
  },
  {
    "date": "2019-02-10",
    "id": "ardor",
    "cap": "53965766.7299",
    "high": "0.0571847939349",
    "low": "0.0516319703404"
  },
  {
    "date": "2019-02-10",
    "id": "aurora",
    "cap": "46976478.0919",
    "high": "0.00913502739551",
    "low": "0.00718038940678"
  },
  {
    "date": "2019-02-10",
    "id": "quant",
    "cap": "45384282.2703",
    "high": "5.88793937564",
    "low": "4.11613494144"
  },
  {
    "date": "2019-02-10",
    "id": "loopring",
    "cap": "43620760.7071",
    "high": "0.0554786074799",
    "low": "0.0526950402315"
  },
  {
    "date": "2019-02-10",
    "id": "veritaseum",
    "cap": "39156332.6064",
    "high": "19.7676212438",
    "low": "17.06570764"
  },
  {
    "date": "2019-02-10",
    "id": "nexo",
    "cap": "34996960.7399",
    "high": "0.0632043382211",
    "low": "0.0587679683401"
  },
  {
    "date": "2019-02-10",
    "id": "aion",
    "cap": "34255886.9421",
    "high": "0.122030507519",
    "low": "0.117015527005"
  },
  {
    "date": "2019-02-10",
    "id": "crypto-com",
    "cap": "33889888.1775",
    "high": "2.16463825577",
    "low": "2.07974141045"
  },
  {
    "date": "2019-02-10",
    "id": "bancor",
    "cap": "33303061.9264",
    "high": "0.531323754293",
    "low": "0.507322898539"
  },
  {
    "date": "2019-02-10",
    "id": "aelf",
    "cap": "31150657.1216",
    "high": "0.111409487017",
    "low": "0.104098370879"
  },
  {
    "date": "2019-02-10",
    "id": "bhp-coin",
    "cap": "26012600.5368",
    "high": "0.804804909767",
    "low": "0.694533297821"
  },
  {
    "date": "2019-02-10",
    "id": "quarkchain",
    "cap": "25234332.6745",
    "high": "0.0316166643683",
    "low": "0.0301515458701"
  },
  {
    "date": "2019-02-10",
    "id": "funfair",
    "cap": "23865697.7897",
    "high": "0.00404329718928",
    "low": "0.00349144124588"
  },
  {
    "date": "2019-02-10",
    "id": "bitcoin-private",
    "cap": "23781926.7776",
    "high": "1.16758170609",
    "low": "1.09913411202"
  },
  {
    "date": "2019-02-10",
    "id": "apollo-currency",
    "cap": "23717634.8693",
    "high": "0.00163610986313",
    "low": "0.00146629326884"
  },
  {
    "date": "2019-02-10",
    "id": "eidoo",
    "cap": "21038101.5435",
    "high": "0.774242486026",
    "low": "0.7008306357"
  },
  {
    "date": "2019-02-10",
    "id": "buggyra-coin-zero",
    "cap": "20808370.7581",
    "high": "0.0131535301272",
    "low": "0.0118971577196"
  },
  {
    "date": "2019-02-10",
    "id": "storj",
    "cap": "19681805.1309",
    "high": "0.148815890057",
    "low": "0.137494399439"
  },
  {
    "date": "2019-02-10",
    "id": "nexus",
    "cap": "18342339.8061",
    "high": "0.307967070125",
    "low": "0.293437315375"
  },
  {
    "date": "2019-02-10",
    "id": "civic",
    "cap": "18123533.1907",
    "high": "0.0580713143316",
    "low": "0.0502392370431"
  },
  {
    "date": "2019-02-10",
    "id": "substratum",
    "cap": "17424754.5516",
    "high": "0.0455408689397",
    "low": "0.043114497517"
  },
  {
    "date": "2019-02-10",
    "id": "bitcoiin",
    "cap": "15060984.5535",
    "high": "0.655463799031",
    "low": "0.301694811701"
  },
  {
    "date": "2019-02-10",
    "id": "bibox-token",
    "cap": "14867526.5896",
    "high": "0.134015923394",
    "low": "0.127696564313"
  },
  {
    "date": "2019-02-10",
    "id": "bezant",
    "cap": "13710510.4818",
    "high": "0.0259839599292",
    "low": "0.0235036756651"
  },
  {
    "date": "2019-02-10",
    "id": "blockv",
    "cap": "13639745.9681",
    "high": "0.00607119472144",
    "low": "0.00552348033983"
  },
  {
    "date": "2019-02-10",
    "id": "ethos",
    "cap": "13438781.9701",
    "high": "0.144857078029",
    "low": "0.138507928866"
  },
  {
    "date": "2019-02-10",
    "id": "matrix-ai-network",
    "cap": "12666765.4393",
    "high": "0.0850042166457",
    "low": "0.0739438167773"
  },
  {
    "date": "2019-02-10",
    "id": "nectar",
    "cap": "12319957.0667",
    "high": "0.14959973024",
    "low": "0.121020566805"
  },
  {
    "date": "2019-02-10",
    "id": "emercoin",
    "cap": "12082591.5761",
    "high": "0.291100090911",
    "low": "0.272632018528"
  },
  {
    "date": "2019-02-10",
    "id": "aragon",
    "cap": "11246206.0802",
    "high": "0.398552858914",
    "low": "0.352146684471"
  },
  {
    "date": "2019-02-10",
    "id": "salus",
    "cap": "10547214.5276",
    "high": "10.5833688881",
    "low": "9.72357164319"
  },
  {
    "date": "2019-02-10",
    "id": "nucleus-vision",
    "cap": "10361038.6276",
    "high": "0.00180860415308",
    "low": "0.00172056211807"
  },
  {
    "date": "2019-02-10",
    "id": "smartcash",
    "cap": "9914025.29281",
    "high": "0.00947222156606",
    "low": "0.00888900136984"
  },
  {
    "date": "2019-02-10",
    "id": "agrello-delta",
    "cap": "9476593.30395",
    "high": "0.113581576176",
    "low": "0.108457475074"
  },
  {
    "date": "2019-02-10",
    "id": "ethlend",
    "cap": "8722218.18036",
    "high": "0.00794169217173",
    "low": "0.0075779824325"
  },
  {
    "date": "2019-02-10",
    "id": "apis",
    "cap": "8198845.84845",
    "high": "0.00197856010338",
    "low": "0.00167757629898"
  },
  {
    "date": "2019-02-10",
    "id": "amber",
    "cap": "8069324.64762",
    "high": "0.0561405935199",
    "low": "0.0538988683923"
  },
  {
    "date": "2019-02-10",
    "id": "bitcapitalvendor",
    "cap": "8046142.67151",
    "high": "0.015180995392",
    "low": "0.0135098417736"
  },
  {
    "date": "2019-02-10",
    "id": "adx-net",
    "cap": "8036755.69156",
    "high": "0.115830013105",
    "low": "0.103808184744"
  },
  {
    "date": "2019-02-10",
    "id": "burst",
    "cap": "7866458.50656",
    "high": "0.00397009867933",
    "low": "0.00355845801205"
  },
  {
    "date": "2019-02-10",
    "id": "beam",
    "cap": "7670017.21197",
    "high": "1.54649574955",
    "low": "1.36025029935"
  },
  {
    "date": "2019-02-10",
    "id": "babb",
    "cap": "7411175.06596",
    "high": "0.000352913098396",
    "low": "0.000314063016399"
  },
  {
    "date": "2019-02-10",
    "id": "cryptaur",
    "cap": "7360397.01092",
    "high": "0.00105588318223",
    "low": "0.000932688709576"
  },
  {
    "date": "2019-02-10",
    "id": "high-performance-blockchain",
    "cap": "7167589.47719",
    "high": "0.172541836997",
    "low": "0.161159644253"
  },
  {
    "date": "2019-02-10",
    "id": "iot-chain",
    "cap": "7119474.51133",
    "high": "0.100784232146",
    "low": "0.0987224002756"
  },
  {
    "date": "2019-02-10",
    "id": "red-pulse",
    "cap": "7083576.25057",
    "high": "0.00872945450853",
    "low": "0.00830468065244"
  },
  {
    "date": "2019-02-10",
    "id": "arcblock",
    "cap": "7043961.99556",
    "high": "0.0822798795809",
    "low": "0.0657706990189"
  },
  {
    "date": "2019-02-10",
    "id": "lambda",
    "cap": "6832232.51955",
    "high": "0.0137678137374",
    "low": "0.0130684816951"
  },
  {
    "date": "2019-02-10",
    "id": "iht-real-estate-protocol",
    "cap": "6830894.31096",
    "high": "0.0117267888498",
    "low": "0.00920282907618"
  },
  {
    "date": "2019-02-10",
    "id": "trade-token-x",
    "cap": "6815622.65956",
    "high": "0.0899151050707",
    "low": "0.0745337440265"
  },
  {
    "date": "2019-02-10",
    "id": "bitbay",
    "cap": "6475465.87037",
    "high": "0.00671727581349",
    "low": "0.00613879109598"
  },
  {
    "date": "2019-02-10",
    "id": "bitcny",
    "cap": "6437950.83921",
    "high": "0.156294570951",
    "low": "0.153836833205"
  },
  {
    "date": "2019-02-10",
    "id": "dew",
    "cap": "6298679.07214",
    "high": "0.0616414494649",
    "low": "0.0607686193037"
  },
  {
    "date": "2019-02-10",
    "id": "bittwatt",
    "cap": "6296701.60569",
    "high": "0.0226247133193",
    "low": "0.0182636945771"
  },
  {
    "date": "2019-02-10",
    "id": "amo-coin",
    "cap": "6240909.05076",
    "high": "0.000740742733038",
    "low": "0.000547730695083"
  },
  {
    "date": "2019-02-10",
    "id": "zip",
    "cap": "6237410.61908",
    "high": "0.00040820116838",
    "low": "0.000374125161713"
  },
  {
    "date": "2019-02-10",
    "id": "bitnewchain",
    "cap": "5989047.32626",
    "high": "0.0334817837101",
    "low": "0.0332112592112"
  },
  {
    "date": "2019-02-10",
    "id": "bottos",
    "cap": "5738013.36922",
    "high": "0.0112445930429",
    "low": "0.00996877902365"
  },
  {
    "date": "2019-02-10",
    "id": "achain",
    "cap": "5693694.22352",
    "high": "0.00684610721425",
    "low": "0.00643579326604"
  },
  {
    "date": "2019-02-10",
    "id": "asch",
    "cap": "5678532.9315",
    "high": "0.0611220293914",
    "low": "0.0569545158822"
  },
  {
    "date": "2019-02-10",
    "id": "all-sports",
    "cap": "5597337.93447",
    "high": "0.00374566341671",
    "low": "0.00360622166313"
  },
  {
    "date": "2019-02-10",
    "id": "atc-coin",
    "cap": "5524601.38415",
    "high": "0.0465259948384",
    "low": "0.0151489053704"
  },
  {
    "date": "2019-02-10",
    "id": "cashbery-coin",
    "cap": "5493975.7455",
    "high": "0.0832787252007",
    "low": "0.082078566282"
  },
  {
    "date": "2019-02-10",
    "id": "aeron",
    "cap": "5267891.88922",
    "high": "0.292660660512",
    "low": "0.272212691189"
  },
  {
    "date": "2019-02-10",
    "id": "decent-bet",
    "cap": "4967723.99528",
    "high": "0.0366552216018",
    "low": "0.0283451416318"
  },
  {
    "date": "2019-02-10",
    "id": "rublix",
    "cap": "4963222.69797",
    "high": "0.243464320114",
    "low": "0.233508554522"
  },
  {
    "date": "2019-02-10",
    "id": "loki",
    "cap": "4833841.47034",
    "high": "0.152593311414",
    "low": "0.147875741751"
  },
  {
    "date": "2019-02-10",
    "id": "smartshare",
    "cap": "4817959.84199",
    "high": "0.00106074483174",
    "low": "0.00100314281314"
  },
  {
    "date": "2019-02-10",
    "id": "loyalcoin",
    "cap": "4681500.44789",
    "high": "0.000881806210295",
    "low": "0.000760643018808"
  },
  {
    "date": "2019-02-10",
    "id": "playcoin-erc20",
    "cap": "4678901.27423",
    "high": "0.0374693406749",
    "low": "0.0270763848705"
  },
  {
    "date": "2019-02-10",
    "id": "appcoins",
    "cap": "4629033.184",
    "high": "0.0467797929726",
    "low": "0.0437703664557"
  },
  {
    "date": "2019-02-10",
    "id": "bitkan",
    "cap": "4441585.491",
    "high": "0.00134440701468",
    "low": "0.0013070871744"
  },
  {
    "date": "2019-02-10",
    "id": "aston",
    "cap": "4419820.33697",
    "high": "0.00557741306157",
    "low": "0.00417607202897"
  },
  {
    "date": "2019-02-10",
    "id": "aeon",
    "cap": "4398808.40421",
    "high": "0.287876521362",
    "low": "0.274024492359"
  },
  {
    "date": "2019-02-10",
    "id": "eosdac",
    "cap": "4358527.92484",
    "high": "0.00772144000722",
    "low": "0.00588212918676"
  },
  {
    "date": "2019-02-10",
    "id": "penta",
    "cap": "4303737.54571",
    "high": "0.000207099379039",
    "low": "0.000177678344292"
  },
  {
    "date": "2019-02-10",
    "id": "box-token",
    "cap": "4246917.12515",
    "high": "0.0555747411538",
    "low": "0.0488079991076"
  },
  {
    "date": "2019-02-10",
    "id": "airswap",
    "cap": "4085178.51254",
    "high": "0.0274283899676",
    "low": "0.0259948888186"
  },
  {
    "date": "2019-02-10",
    "id": "b2bcoin",
    "cap": "3939490.2007",
    "high": "0.00885283659917",
    "low": "0.00655145695086"
  },
  {
    "date": "2019-02-10",
    "id": "bitcoin-interest",
    "cap": "3795063.77244",
    "high": "0.210690463271",
    "low": "0.196000513139"
  },
  {
    "date": "2019-02-10",
    "id": "adtoken",
    "cap": "3712358.2711",
    "high": "0.00770878551714",
    "low": "0.00573835293041"
  },
  {
    "date": "2019-02-10",
    "id": "b2bx",
    "cap": "3610207.29813",
    "high": "0.229458132181",
    "low": "0.211187690873"
  },
  {
    "date": "2019-02-10",
    "id": "baasid",
    "cap": "3586201.42403",
    "high": "0.0013614093136",
    "low": "0.00102296934279"
  },
  {
    "date": "2019-02-10",
    "id": "bitcore",
    "cap": "3538892.31528",
    "high": "0.212175487657",
    "low": "0.19908605159"
  },
  {
    "date": "2019-02-10",
    "id": "callisto-network",
    "cap": "3407343.18906",
    "high": "0.00296751473476",
    "low": "0.00266591826838"
  },
  {
    "date": "2019-02-10",
    "id": "0chain",
    "cap": "3387090.86721",
    "high": "0.0910040964575",
    "low": "0.0722861589839"
  },
  {
    "date": "2019-02-10",
    "id": "moneytoken",
    "cap": "3381091.62147",
    "high": "0.000361576918713",
    "low": "0.000335831839753"
  },
  {
    "date": "2019-02-10",
    "id": "apex",
    "cap": "3300996.36735",
    "high": "0.00736467248961",
    "low": "0.00673512128649"
  },
  {
    "date": "2019-02-10",
    "id": "ivy",
    "cap": "3270105.00637",
    "high": "0.0107071279689",
    "low": "0.00914835830764"
  },
  {
    "date": "2019-02-10",
    "id": "bit-z-token",
    "cap": "3204672.76127",
    "high": "0.0720151252691",
    "low": "0.0647996716012"
  },
  {
    "date": "2019-02-10",
    "id": "lamden",
    "cap": "3025735.57597",
    "high": "0.0288350820658",
    "low": "0.0184349466651"
  },
  {
    "date": "2019-02-10",
    "id": "lendingblock",
    "cap": "2988053.43542",
    "high": "0.00444303887051",
    "low": "0.00230444459672"
  },
  {
    "date": "2019-02-10",
    "id": "bit-tube",
    "cap": "2966301.61168",
    "high": "0.0248859093496",
    "low": "0.0229023033886"
  },
  {
    "date": "2019-02-10",
    "id": "avinoc",
    "cap": "2963255.60909",
    "high": "0.00765335438494",
    "low": "0.00540094327056"
  },
  {
    "date": "2019-02-10",
    "id": "atn",
    "cap": "2898081.54406",
    "high": "0.0348387362263",
    "low": "0.0333576535112"
  },
  {
    "date": "2019-02-10",
    "id": "global-cryptocurrency",
    "cap": "2777982.5436",
    "high": "0.00228298790624",
    "low": "0.00156499493566"
  },
  {
    "date": "2019-02-10",
    "id": "encrypgen",
    "cap": "2562044.06379",
    "high": "0.0398602178466",
    "low": "0.0373196783782"
  },
  {
    "date": "2019-02-10",
    "id": "covesting",
    "cap": "2551778.26335",
    "high": "0.148139635548",
    "low": "0.13364013454"
  },
  {
    "date": "2019-02-10",
    "id": "tv-two",
    "cap": "2537778.48002",
    "high": "0.00624572287553",
    "low": "0.00303096859001"
  },
  {
    "date": "2019-02-10",
    "id": "pandacoin-pnd",
    "cap": "2443013.92647",
    "high": "0.0000751351736236",
    "low": "0.0000701471801517"
  },
  {
    "date": "2019-02-10",
    "id": "unibright",
    "cap": "2343470.02814",
    "high": "0.0166222151721",
    "low": "0.0120379217582"
  },
  {
    "date": "2019-02-10",
    "id": "pal-network",
    "cap": "2297776.68397",
    "high": "0.00416846082244",
    "low": "0.00392363659529"
  },
  {
    "date": "2019-02-10",
    "id": "bitcoin-atom",
    "cap": "2284637.25261",
    "high": "0.159387583048",
    "low": "0.122217262761"
  },
  {
    "date": "2019-02-10",
    "id": "bitshares-music",
    "cap": "2216039.06837",
    "high": "0.168408657379",
    "low": "0.0190744921829"
  },
  {
    "date": "2019-02-10",
    "id": "bean-cash",
    "cap": "2122037.37664",
    "high": "0.000842990849256",
    "low": "0.000764848221455"
  },
  {
    "date": "2019-02-10",
    "id": "etheroll",
    "cap": "2117397.18435",
    "high": "0.302641991912",
    "low": "0.280766577559"
  },
  {
    "date": "2019-02-10",
    "id": "ebcoin",
    "cap": "2083814.47917",
    "high": "0.000585436940495",
    "low": "0.000513701145345"
  },
  {
    "date": "2019-02-10",
    "id": "hubii-network",
    "cap": "2076386.25842",
    "high": "0.137404654092",
    "low": "0.102395718866"
  },
  {
    "date": "2019-02-10",
    "id": "bitdice",
    "cap": "2071559.58211",
    "high": "0.0295937083158",
    "low": "0.025498327282"
  },
  {
    "date": "2019-02-10",
    "id": "alqo",
    "cap": "2047359.43691",
    "high": "0.0394216667577",
    "low": "0.0328233874724"
  },
  {
    "date": "2019-02-10",
    "id": "adamant-messenger",
    "cap": "2011840.02996",
    "high": "0.0340293541583",
    "low": "0.022826669915"
  },
  {
    "date": "2019-02-10",
    "id": "gene-source-code-chain",
    "cap": "1910727.83409",
    "high": "0.00524832791797",
    "low": "0.00484523797623"
  },
  {
    "date": "2019-02-10",
    "id": "suncontract",
    "cap": "1856794.83779",
    "high": "0.0151741870257",
    "low": "0.0143959224778"
  },
  {
    "date": "2019-02-10",
    "id": "mysterium",
    "cap": "1841732.19139",
    "high": "0.085564069683",
    "low": "0.0674303183377"
  },
  {
    "date": "2019-02-10",
    "id": "mintcoin",
    "cap": "1829356.51111",
    "high": "0.0000733289528333",
    "low": "0.0000733289528333"
  },
  {
    "date": "2019-02-10",
    "id": "chatcoin",
    "cap": "1802550.34941",
    "high": "0.00261238938765",
    "low": "0.00251912443207"
  },
  {
    "date": "2019-02-10",
    "id": "aergo",
    "cap": "1747424.11134",
    "high": "0.066517329109",
    "low": "0.0602701954217"
  },
  {
    "date": "2019-02-10",
    "id": "haven-protocol",
    "cap": "1745763.90402",
    "high": "0.246553042106",
    "low": "0.228827258064"
  },
  {
    "date": "2019-02-10",
    "id": "aidcoin",
    "cap": "1689923.04783",
    "high": "0.0373531163019",
    "low": "0.0364701817823"
  },
  {
    "date": "2019-02-10",
    "id": "auroracoin",
    "cap": "1676955.15697",
    "high": "0.135395865425",
    "low": "0.0923019245467"
  },
  {
    "date": "2019-02-10",
    "id": "axpire",
    "cap": "1666102.88518",
    "high": "0.00607700296029",
    "low": "0.00357052656332"
  },
  {
    "date": "2019-02-10",
    "id": "vipstar-coin",
    "cap": "1663539.95949",
    "high": "0.0000600191798568",
    "low": "0.0000465674921"
  },
  {
    "date": "2019-02-10",
    "id": "bitmart-token",
    "cap": "1662913.76974",
    "high": "0.0138074806795",
    "low": "0.0128249097579"
  },
  {
    "date": "2019-02-10",
    "id": "business-credit-alliance-chain",
    "cap": "1646834.0014",
    "high": "0.00258988203585",
    "low": "0.00241488110943"
  },
  {
    "date": "2019-02-10",
    "id": "birake",
    "cap": "1582288.02044",
    "high": "0.0370020729002",
    "low": "0.0335871987861"
  },
  {
    "date": "2019-02-10",
    "id": "mktcoin",
    "cap": "1568176.19153",
    "high": "0.00139719945766",
    "low": "0.00128045831863"
  },
  {
    "date": "2019-02-10",
    "id": "aidoc",
    "cap": "1525578.79476",
    "high": "0.00363498800693",
    "low": "0.00320064515063"
  },
  {
    "date": "2019-02-10",
    "id": "amlt",
    "cap": "1524794.52726",
    "high": "0.0180130805553",
    "low": "0.0165744678425"
  },
  {
    "date": "2019-02-10",
    "id": "banca",
    "cap": "1507377.89571",
    "high": "0.0000842192316005",
    "low": "0.0000788020591005"
  },
  {
    "date": "2019-02-10",
    "id": "bitgreen",
    "cap": "1444152.86236",
    "high": "0.223638006151",
    "low": "0.185921417571"
  },
  {
    "date": "2019-02-10",
    "id": "airbloc",
    "cap": "1214504.57321",
    "high": "0.00538463697114",
    "low": "0.00497620170915"
  },
  {
    "date": "2019-02-10",
    "id": "abyss-token",
    "cap": "1205551.82355",
    "high": "0.00567017456195",
    "low": "0.00511964859047"
  },
  {
    "date": "2019-02-10",
    "id": "effect-ai",
    "cap": "1187803.18086",
    "high": "0.00659583776298",
    "low": "0.00513700464666"
  },
  {
    "date": "2019-02-10",
    "id": "bankex",
    "cap": "1162102.34149",
    "high": "0.0124771915962",
    "low": "0.0122194966231"
  },
  {
    "date": "2019-02-10",
    "id": "on-live",
    "cap": "1141210.38061",
    "high": "0.0527795307049",
    "low": "0.0495495278282"
  },
  {
    "date": "2019-02-10",
    "id": "bezop",
    "cap": "1136486.17826",
    "high": "0.0216587445853",
    "low": "0.0201860568801"
  },
  {
    "date": "2019-02-10",
    "id": "global-awards-token",
    "cap": "1114399.96958",
    "high": "0.00210382158701",
    "low": "0.00188939147024"
  },
  {
    "date": "2019-02-10",
    "id": "aventus",
    "cap": "1108036.02861",
    "high": "0.191632471936",
    "low": "0.139913483209"
  },
  {
    "date": "2019-02-10",
    "id": "blockparty-boxx-token",
    "cap": "1098573.59401",
    "high": "0.0472672690777",
    "low": "0.0456402790704"
  },
  {
    "date": "2019-02-10",
    "id": "energycoin",
    "cap": "1053056.2192",
    "high": "0.00921171107736",
    "low": "0.00786736161849"
  },
  {
    "date": "2019-02-10",
    "id": "bitcoen",
    "cap": "1035677.96258",
    "high": "0.148532575646",
    "low": "0.128868607921"
  },
  {
    "date": "2019-02-10",
    "id": "alax",
    "cap": "1032513.13261",
    "high": "0.00210143185822",
    "low": "0.00187825358398"
  },
  {
    "date": "2019-02-10",
    "id": "anoncoin",
    "cap": "1014924.71723",
    "high": "0.480934752268",
    "low": "0.468549905007"
  },
  {
    "date": "2019-02-10",
    "id": "latiumx",
    "cap": "999031.44133",
    "high": "0.00955730717688",
    "low": "0.00919996814269"
  },
  {
    "date": "2019-02-10",
    "id": "bitdegree",
    "cap": "994997.646089",
    "high": "0.00279808384824",
    "low": "0.002628510798"
  },
  {
    "date": "2019-02-10",
    "id": "0xcert",
    "cap": "954980.045578",
    "high": "0.00335493198618",
    "low": "0.00279489196655"
  },
  {
    "date": "2019-02-10",
    "id": "beetle-coin",
    "cap": "911039.74228",
    "high": "0.00556670218301",
    "low": "0.00385939382208"
  },
  {
    "date": "2019-02-10",
    "id": "bitcrystals",
    "cap": "886591.978964",
    "high": "0.0387420406863",
    "low": "0.0386877416156"
  },
  {
    "date": "2019-02-10",
    "id": "trittium",
    "cap": "875457.702813",
    "high": "0.00918445442044",
    "low": "0.00784041376027"
  },
  {
    "date": "2019-02-10",
    "id": "artbyte",
    "cap": "850520.859595",
    "high": "0.00113240606258",
    "low": "0.00105991319772"
  },
  {
    "date": "2019-02-10",
    "id": "red",
    "cap": "801430.08869",
    "high": "0.00660621354107",
    "low": "0.00599991805558"
  },
  {
    "date": "2019-02-10",
    "id": "adshares",
    "cap": "789995.591011",
    "high": "0.0439880787768",
    "low": "0.0383741195722"
  },
  {
    "date": "2019-02-10",
    "id": "0xbtc",
    "cap": "787356.109838",
    "high": "0.213346016732",
    "low": "0.169057602865"
  },
  {
    "date": "2019-02-10",
    "id": "42-coin",
    "cap": "777915.004572",
    "high": "18521.8049932",
    "low": "15973.9736885"
  },
  {
    "date": "2019-02-10",
    "id": "alphacat",
    "cap": "777018.515007",
    "high": "0.000286057023683",
    "low": "0.000257109114225"
  },
  {
    "date": "2019-02-10",
    "id": "bee-token",
    "cap": "763373.246725",
    "high": "0.00363074169555",
    "low": "0.00346969960104"
  },
  {
    "date": "2019-02-10",
    "id": "2give",
    "cap": "750908.089732",
    "high": "0.00157141763437",
    "low": "0.00139035490372"
  },
  {
    "date": "2019-02-10",
    "id": "lethean",
    "cap": "739096.250349",
    "high": "0.00125585569323",
    "low": "0.0012110513775"
  },
  {
    "date": "2019-02-10",
    "id": "vetri",
    "cap": "728395.700682",
    "high": "0.00309214159564",
    "low": "0.00306994866442"
  },
  {
    "date": "2019-02-10",
    "id": "arbidex",
    "cap": "727725.498449",
    "high": "0.0356943857235",
    "low": "0.0337929020717"
  },
  {
    "date": "2019-02-10",
    "id": "ailink-token",
    "cap": "717630.162269",
    "high": "0.000322824520138",
    "low": "0.000297123505507"
  },
  {
    "date": "2019-02-10",
    "id": "airwire",
    "cap": "716854.892644",
    "high": "0.00674813856758",
    "low": "0.00588589651327"
  },
  {
    "date": "2019-02-10",
    "id": "sentinel-chain",
    "cap": "712578.59032",
    "high": "0.00381616189839",
    "low": "0.00347156469682"
  },
  {
    "date": "2019-02-10",
    "id": "bitcoinz",
    "cap": "707766.098473",
    "high": "0.000190789316579",
    "low": "0.000179869068332"
  },
  {
    "date": "2019-02-10",
    "id": "autonio",
    "cap": "690123.354073",
    "high": "0.00841287444151",
    "low": "0.00731252681147"
  },
  {
    "date": "2019-02-10",
    "id": "coinsuper-ecosystem-network",
    "cap": "688820.35912",
    "high": "0.00493854072453",
    "low": "0.00452158591253"
  },
  {
    "date": "2019-02-10",
    "id": "atlant",
    "cap": "685617.114947",
    "high": "0.018257853771",
    "low": "0.0179909665736"
  },
  {
    "date": "2019-02-10",
    "id": "snowgem",
    "cap": "622096.084582",
    "high": "0.0548672258103",
    "low": "0.0502058340128"
  },
  {
    "date": "2019-02-10",
    "id": "bitscreener-token",
    "cap": "615688.396399",
    "high": "0.00408554732219",
    "low": "0.00363195475957"
  },
  {
    "date": "2019-02-10",
    "id": "alis",
    "cap": "609064.229368",
    "high": "0.017994691119",
    "low": "0.0154097615575"
  },
  {
    "date": "2019-02-10",
    "id": "1world",
    "cap": "591511.650823",
    "high": "0.0305425835933",
    "low": "0.0243795855995"
  },
  {
    "date": "2019-02-10",
    "id": "bitcoin-incognito",
    "cap": "587550.952161",
    "high": "0.0798513159895",
    "low": "0.0690895667377"
  },
  {
    "date": "2019-02-10",
    "id": "b3coin",
    "cap": "572861.60219",
    "high": "0.00090548301468",
    "low": "0.000683844515279"
  },
  {
    "date": "2019-02-10",
    "id": "betterbetting",
    "cap": "570100.722178",
    "high": "0.00327185606278",
    "low": "0.00312611129478"
  },
  {
    "date": "2019-02-10",
    "id": "acute-angle-cloud",
    "cap": "569380.488368",
    "high": "0.00247230664596",
    "low": "0.00227752195347"
  },
  {
    "date": "2019-02-10",
    "id": "bitcoin-plus",
    "cap": "567703.997917",
    "high": "5.05903696649",
    "low": "4.2431631888"
  },
  {
    "date": "2019-02-10",
    "id": "kryll",
    "cap": "556858.157016",
    "high": "0.0435957505954",
    "low": "0.0410450020943"
  },
  {
    "date": "2019-02-10",
    "id": "apollon",
    "cap": "556352.005213",
    "high": "0.0101176579733",
    "low": "0.00254584489001"
  },
  {
    "date": "2019-02-10",
    "id": "fedoracoin",
    "cap": "555997.48101",
    "high": "0.00000272254567553",
    "low": "0.00000245830388117"
  },
  {
    "date": "2019-02-10",
    "id": "banyan-network",
    "cap": "537769.490711",
    "high": "0.00117207314701",
    "low": "0.000854825665915"
  },
  {
    "date": "2019-02-10",
    "id": "adbank",
    "cap": "521095.936584",
    "high": "0.000865220874622",
    "low": "0.000817319068832"
  },
  {
    "date": "2019-02-10",
    "id": "arionum",
    "cap": "503918.153169",
    "high": "0.00726453023071",
    "low": "0.00634984822625"
  },
  {
    "date": "2019-02-10",
    "id": "aphelion",
    "cap": "492945.017862",
    "high": "0.0102431490903",
    "low": "0.0096809519825"
  },
  {
    "date": "2019-02-10",
    "id": "bitrent",
    "cap": "443143.821404",
    "high": "0.000540650018755",
    "low": "0.000397761860423"
  },
  {
    "date": "2019-02-10",
    "id": "payfair",
    "cap": "438583.058858",
    "high": "0.00606817720206",
    "low": "0.00337104071469"
  },
  {
    "date": "2019-02-10",
    "id": "buzzcoin",
    "cap": "424499.268553",
    "high": "0.0000242388042603",
    "low": "0.000020453778474"
  },
  {
    "date": "2019-02-10",
    "id": "aichain",
    "cap": "415666.509342",
    "high": "0.000832391227097",
    "low": "0.000771532591154"
  },
  {
    "date": "2019-02-10",
    "id": "1337coin",
    "cap": "411997.977152",
    "high": "0.0000169410242941",
    "low": "0.000015479740764"
  },
  {
    "date": "2019-02-10",
    "id": "starbase",
    "cap": "402014.731798",
    "high": "0.00220134154658",
    "low": "0.00184959284738"
  },
  {
    "date": "2019-02-10",
    "id": "erc20",
    "cap": "400228.929988",
    "high": "0.145346780636",
    "low": "0.0476373410787"
  },
  {
    "date": "2019-02-10",
    "id": "atbcoin",
    "cap": "397044.858866",
    "high": "0.00946351048598",
    "low": "0.00845566230057"
  },
  {
    "date": "2019-02-10",
    "id": "coin-lion",
    "cap": "395578.834609",
    "high": "0.0131651257143",
    "low": "0.0106252151828"
  },
  {
    "date": "2019-02-10",
    "id": "atonomi",
    "cap": "390486.930628",
    "high": "0.00104732380997",
    "low": "0.000686107188632"
  },
  {
    "date": "2019-02-10",
    "id": "bethereum",
    "cap": "384885.869139",
    "high": "0.00124130962119",
    "low": "0.00117808546273"
  },
  {
    "date": "2019-02-10",
    "id": "bettex-coin",
    "cap": "376650.708347",
    "high": "0.0838960212607",
    "low": "0.0747387237328"
  },
  {
    "date": "2019-02-10",
    "id": "ultranote-coin",
    "cap": "364320.927604",
    "high": "0.00010960977578",
    "low": "0.0000368691288694"
  },
  {
    "date": "2019-02-10",
    "id": "auctus",
    "cap": "356519.563743",
    "high": "0.0143153180996",
    "low": "0.0130382921473"
  },
  {
    "date": "2019-02-10",
    "id": "adelphoi",
    "cap": "355813.608216",
    "high": "0.017170628414",
    "low": "0.017170628414"
  },
  {
    "date": "2019-02-10",
    "id": "attention-token-of-media",
    "cap": "350298.637017",
    "high": "0.000100149325709",
    "low": "0.0000472210299304"
  },
  {
    "date": "2019-02-10",
    "id": "rupee",
    "cap": "343376.141855",
    "high": "0.0103839127348",
    "low": "0.0102634551594"
  },
  {
    "date": "2019-02-10",
    "id": "auxilium",
    "cap": "333831.297736",
    "high": "0.00378859420453",
    "low": "0.00293377878042"
  },
  {
    "date": "2019-02-10",
    "id": "pesetacoin",
    "cap": "333789.665206",
    "high": "0.00359888055927",
    "low": "0.00240857038971"
  },
  {
    "date": "2019-02-10",
    "id": "beacon",
    "cap": "323952.83448",
    "high": "0.0635554935244",
    "low": "0.0477778830574"
  },
  {
    "date": "2019-02-10",
    "id": "quadrantprotocol",
    "cap": "319408.395103",
    "high": "0.00101290659257",
    "low": "0.000959899945892"
  },
  {
    "date": "2019-02-10",
    "id": "alt-estate-token",
    "cap": "317181.672103",
    "high": "0.000437986883074",
    "low": "0.000430983276481"
  },
  {
    "date": "2019-02-10",
    "id": "biocoin",
    "cap": "312874.229419",
    "high": "0.000369921353948",
    "low": "0.000327835636483"
  },
  {
    "date": "2019-02-10",
    "id": "beat",
    "cap": "292465.531431",
    "high": "0.00247547426337",
    "low": "0.00229828888272"
  },
  {
    "date": "2019-02-10",
    "id": "fantasygold",
    "cap": "282471.601295",
    "high": "0.0240276664387",
    "low": "0.0204394981393"
  },
  {
    "date": "2019-02-10",
    "id": "biblepay",
    "cap": "282450.212163",
    "high": "0.000218663115958",
    "low": "0.000180754214422"
  },
  {
    "date": "2019-02-10",
    "id": "biotron",
    "cap": "282366.761186",
    "high": "0.00536385963224",
    "low": "0.00528179636555"
  },
  {
    "date": "2019-02-10",
    "id": "xovbank",
    "cap": "281520.41247",
    "high": "0.00282011576464",
    "low": "0.00231082618487"
  },
  {
    "date": "2019-02-10",
    "id": "cdx-network",
    "cap": "276941.621633",
    "high": "0.00979475456547",
    "low": "0.00776731736727"
  },
  {
    "date": "2019-02-10",
    "id": "wandx",
    "cap": "276346.659424",
    "high": "0.0226843330697",
    "low": "0.0217040768244"
  },
  {
    "date": "2019-02-10",
    "id": "bitibu-coin",
    "cap": "263224.619046",
    "high": "0.0620761723521",
    "low": "0.0592979894178"
  },
  {
    "date": "2019-02-10",
    "id": "cryptonite",
    "cap": "262005.525878",
    "high": "0.000405046241429",
    "low": "0.000363665044213"
  },
  {
    "date": "2019-02-10",
    "id": "mithril-ore",
    "cap": "260383.16285",
    "high": "22.0926937393",
    "low": "22.0926937393"
  },
  {
    "date": "2019-02-10",
    "id": "clearcoin",
    "cap": "259798.537494",
    "high": "0.000492160380888",
    "low": "0.000492160380888"
  },
  {
    "date": "2019-02-10",
    "id": "argentum",
    "cap": "250345.18495",
    "high": "0.0262120319875",
    "low": "0.0223692065179"
  },
  {
    "date": "2019-02-10",
    "id": "bitclave",
    "cap": "248586.332422",
    "high": "0.000514902735516",
    "low": "0.00049579"
  },
  {
    "date": "2019-02-10",
    "id": "mediccoin",
    "cap": "247443.200025",
    "high": "0.00102326292757",
    "low": "0.000982250944459"
  },
  {
    "date": "2019-02-10",
    "id": "audiocoin",
    "cap": "245906.220582",
    "high": "0.000258944947763",
    "low": "0.000254766617433"
  },
  {
    "date": "2019-02-10",
    "id": "adhive",
    "cap": "245733.283188",
    "high": "0.00209333012341",
    "low": "0.00194215865985"
  },
  {
    "date": "2019-02-10",
    "id": "ixcoin",
    "cap": "245323.297669",
    "high": "0.0132346865575",
    "low": "0.0115073826843"
  },
  {
    "date": "2019-02-10",
    "id": "syncfab",
    "cap": "244864.811852",
    "high": "0.00154970930395",
    "low": "0.0013769047787"
  },
  {
    "date": "2019-02-10",
    "id": "relex",
    "cap": "243894.878497",
    "high": "0.0001852122403",
    "low": "0.000145179905637"
  },
  {
    "date": "2019-02-10",
    "id": "advanced-internet-blocks",
    "cap": "236129.132854",
    "high": "0.0106968929234",
    "low": "0.00567773938416"
  },
  {
    "date": "2019-02-10",
    "id": "bigbom",
    "cap": "232592.140531",
    "high": "0.000722066244035",
    "low": "0.000562167915063"
  },
  {
    "date": "2019-02-10",
    "id": "actinium",
    "cap": "231180.485746",
    "high": "0.0294942904733",
    "low": "0.0254033052471"
  },
  {
    "date": "2019-02-10",
    "id": "posw-coin",
    "cap": "209400.601318",
    "high": "0.00474831295506",
    "low": "0.00474831295506"
  },
  {
    "date": "2019-02-10",
    "id": "dinastycoin",
    "cap": "202064.216671",
    "high": "0.000110976406184",
    "low": "0.0000727866294261"
  },
  {
    "date": "2019-02-10",
    "id": "bitrewards",
    "cap": "200229.222633",
    "high": "0.000593343673175",
    "low": "0.000546848144462"
  },
  {
    "date": "2019-02-10",
    "id": "bitdeal",
    "cap": "199300.683863",
    "high": "0.0011414897792",
    "low": "0.0011333145152"
  },
  {
    "date": "2019-02-10",
    "id": "bbscoin",
    "cap": "197253.275727",
    "high": "0.0000026777069466",
    "low": "0.00000200679990471"
  },
  {
    "date": "2019-02-10",
    "id": "amon",
    "cap": "196032.494572",
    "high": "0.000468010152835",
    "low": "0.000328941758135"
  },
  {
    "date": "2019-02-10",
    "id": "aditus",
    "cap": "195070.05831",
    "high": "0.000833237872773",
    "low": "0.000778613107837"
  },
  {
    "date": "2019-02-10",
    "id": "cfun",
    "cap": "192214.827914",
    "high": "0.000447604838277",
    "low": "0.000394587220126"
  },
  {
    "date": "2019-02-10",
    "id": "peepcoin",
    "cap": "188767.853274",
    "high": "0.00000487867067194",
    "low": "0.00000452356671936"
  },
  {
    "date": "2019-02-10",
    "id": "bitbar",
    "cap": "188457.206549",
    "high": "8.97628242988",
    "low": "4.43029172404"
  },
  {
    "date": "2019-02-10",
    "id": "bitnautic-token",
    "cap": "186921.029669",
    "high": "0.0164804404533",
    "low": "0.00862189136045"
  },
  {
    "date": "2019-02-10",
    "id": "bitcoin-zero",
    "cap": "186678.719724",
    "high": "0.020488591434",
    "low": "0.0129495660831"
  },
  {
    "date": "2019-02-10",
    "id": "belacoin",
    "cap": "186363.083697",
    "high": "0.00699795717841",
    "low": "0.0046416206441"
  },
  {
    "date": "2019-02-10",
    "id": "allsafe",
    "cap": "186267.725537",
    "high": "0.0280776432623",
    "low": "0.0257147001912"
  },
  {
    "date": "2019-02-10",
    "id": "ace",
    "cap": "172640.898841",
    "high": "0.0147688323692",
    "low": "0.0136597086024"
  },
  {
    "date": "2019-02-10",
    "id": "dietbitcoin",
    "cap": "172449.481105",
    "high": "0.0632019736911",
    "low": "0.00437905591552"
  },
  {
    "date": "2019-02-10",
    "id": "bitcoin-scrypt",
    "cap": "165511.510561",
    "high": "0.027895315024",
    "low": "0.00799701945129"
  },
  {
    "date": "2019-02-10",
    "id": "bitqy",
    "cap": "163768.917314",
    "high": "0.000100445655508",
    "low": "0.0000313112440103"
  },
  {
    "date": "2019-02-10",
    "id": "startercoin",
    "cap": "161766.634889",
    "high": "0.000572813445372",
    "low": "0.000572813445372"
  },
  {
    "date": "2019-02-10",
    "id": "bitgold",
    "cap": "158519.560638",
    "high": "894.782635501",
    "low": "824.771910494"
  },
  {
    "date": "2019-02-10",
    "id": "bata",
    "cap": "157075.857369",
    "high": "0.0319380263175",
    "low": "0.0161236197904"
  },
  {
    "date": "2019-02-10",
    "id": "xmct",
    "cap": "153998.355018",
    "high": "0.0015977338088",
    "low": "0.00137425609801"
  },
  {
    "date": "2019-02-10",
    "id": "op-coin",
    "cap": "153969.154322",
    "high": "0.0000828243219835",
    "low": "0.000050472168877"
  },
  {
    "date": "2019-02-10",
    "id": "ethersportz",
    "cap": "151828.868968",
    "high": "0.0250510193483",
    "low": "0.0209328051162"
  },
  {
    "date": "2019-02-10",
    "id": "open-trading-network",
    "cap": "149783.350467",
    "high": "0.0739842707896",
    "low": "0.0363941430951"
  },
  {
    "date": "2019-02-10",
    "id": "absolute",
    "cap": "148885.261744",
    "high": "0.0165794750867",
    "low": "0.0151520502466"
  },
  {
    "date": "2019-02-10",
    "id": "zennies",
    "cap": "148088.81567",
    "high": "0.000147968541579",
    "low": "0.000145580924247"
  },
  {
    "date": "2019-02-10",
    "id": "blockchain-certified-data-token",
    "cap": "147992.671493",
    "high": "0.00478033525543",
    "low": "0.00467689826335"
  },
  {
    "date": "2019-02-10",
    "id": "iconiq-lab-token",
    "cap": "140590.970512",
    "high": "0.0427971496352",
    "low": "0.0352794199961"
  },
  {
    "date": "2019-02-10",
    "id": "more-coin",
    "cap": "140552.265597",
    "high": "0.0794055924647",
    "low": "0.0680418039518"
  },
  {
    "date": "2019-02-10",
    "id": "bitradio",
    "cap": "135737.105915",
    "high": "0.0377428789042",
    "low": "0.018673778311"
  },
  {
    "date": "2019-02-10",
    "id": "bitcoin-turbo-koin",
    "cap": "135010.800846",
    "high": "0.0000146548981548",
    "low": "0.0000132130336208"
  },
  {
    "date": "2019-02-10",
    "id": "block-logic",
    "cap": "132971.931332",
    "high": "0.0136767354049",
    "low": "0.0129817737569"
  },
  {
    "date": "2019-02-10",
    "id": "bitcloud",
    "cap": "132418.676515",
    "high": "0.00981339565074",
    "low": "0.00456759448668"
  },
  {
    "date": "2019-02-10",
    "id": "bitbtc",
    "cap": "131132.147696",
    "high": "3434.55823919",
    "low": "3062.96311442"
  },
  {
    "date": "2019-02-10",
    "id": "ellaism",
    "cap": "130981.237139",
    "high": "0.00799045767183",
    "low": "0.00767202197328"
  },
  {
    "date": "2019-02-10",
    "id": "biteur",
    "cap": "128855.046465",
    "high": "1.21811835358",
    "low": "1.1881798398"
  },
  {
    "date": "2019-02-10",
    "id": "apr-coin",
    "cap": "124235.583832",
    "high": "0.0225634093406",
    "low": "0.0178910168993"
  },
  {
    "date": "2019-02-10",
    "id": "procurrency",
    "cap": "123389.370213",
    "high": "0.00122074046803",
    "low": "0.000604160835626"
  },
  {
    "date": "2019-02-10",
    "id": "aigang",
    "cap": "117971.586875",
    "high": "0.0040765105602",
    "low": "0.00385074176796"
  },
  {
    "date": "2019-02-10",
    "id": "akroma",
    "cap": "117218.815825",
    "high": "0.00983316657232",
    "low": "0.00551774478255"
  },
  {
    "date": "2019-02-10",
    "id": "chronologic",
    "cap": "116795.779035",
    "high": "0.143409001313",
    "low": "0.134713129761"
  },
  {
    "date": "2019-02-10",
    "id": "unify",
    "cap": "107464.710156",
    "high": "0.00703307564663",
    "low": "0.00561514462731"
  },
  {
    "date": "2019-02-10",
    "id": "cazcoin",
    "cap": "107144.373165",
    "high": "0.00285719428235",
    "low": "0.0025117213459"
  },
  {
    "date": "2019-02-10",
    "id": "ac3",
    "cap": "106409.8425",
    "high": "0.0015",
    "low": "0.0015"
  },
  {
    "date": "2019-02-10",
    "id": "chesscoin",
    "cap": "105935.737168",
    "high": "0.00196058317592",
    "low": "0.00181035411299"
  },
  {
    "date": "2019-02-10",
    "id": "arion",
    "cap": "99367.7069766",
    "high": "0.0112124720543",
    "low": "0.00982158647133"
  },
  {
    "date": "2019-02-10",
    "id": "megacoin",
    "cap": "96494.4054828",
    "high": "0.00255245734224",
    "low": "0.00236579118837"
  },
  {
    "date": "2019-02-10",
    "id": "oceanlab",
    "cap": "95918.0074348",
    "high": "0.0020859033502",
    "low": "0.00194208317323"
  },
  {
    "date": "2019-02-10",
    "id": "crave",
    "cap": "90195.6252125",
    "high": "0.00586957047483",
    "low": "0.00263416538624"
  },
  {
    "date": "2019-02-10",
    "id": "aegeus",
    "cap": "89361.8719049",
    "high": "0.00506744609616",
    "low": "0.00259247957377"
  },
  {
    "date": "2019-02-10",
    "id": "briacoin",
    "cap": "89211.6924036",
    "high": "0.12",
    "low": "0.11"
  },
  {
    "date": "2019-02-10",
    "id": "aquariuscoin",
    "cap": "87986.4379695",
    "high": "0.102704120759",
    "low": "0.0405054147387"
  },
  {
    "date": "2019-02-10",
    "id": "billionaire-token",
    "cap": "87348.1322832",
    "high": "0.02634722609",
    "low": "0.02634722609"
  },
  {
    "date": "2019-02-10",
    "id": "kz-cash",
    "cap": "85284.2752984",
    "high": "0.040900202382",
    "low": "0.0370559295233"
  },
  {
    "date": "2019-02-10",
    "id": "paycoin2",
    "cap": "83620.4032606",
    "high": "0.00697107259848",
    "low": "0.00697107259848"
  },
  {
    "date": "2019-02-10",
    "id": "platinumbar",
    "cap": "83118.0392509",
    "high": "0.0384783361407",
    "low": "0.0384783361407"
  },
  {
    "date": "2019-02-10",
    "id": "adzcoin",
    "cap": "82726.7171879",
    "high": "0.00224188103331",
    "low": "0.00147578849465"
  },
  {
    "date": "2019-02-10",
    "id": "bitblocks",
    "cap": "81831.2260239",
    "high": "0.000943257678677",
    "low": "0.00066177239949"
  },
  {
    "date": "2019-02-10",
    "id": "xdna",
    "cap": "81617.3368827",
    "high": "0.0291393827038",
    "low": "0.0236697905606"
  },
  {
    "date": "2019-02-10",
    "id": "bitnation",
    "cap": "81246.6876653",
    "high": "0.00000426152026558",
    "low": "0.00000343482357899"
  },
  {
    "date": "2019-02-10",
    "id": "azart",
    "cap": "80147.9766851",
    "high": "0.0199277489818",
    "low": "0.0148671261471"
  },
  {
    "date": "2019-02-10",
    "id": "bitcoinus",
    "cap": "77258.1973384",
    "high": "0.00147679478461",
    "low": "0.00136151463737"
  },
  {
    "date": "2019-02-10",
    "id": "bitstar",
    "cap": "77234.6617687",
    "high": "0.00384707898751",
    "low": "0.00384707898751"
  },
  {
    "date": "2019-02-10",
    "id": "bolivarcoin",
    "cap": "73836.3697159",
    "high": "0.00619874992434",
    "low": "0.00515483374261"
  },
  {
    "date": "2019-02-10",
    "id": "bitcoin-red",
    "cap": "71006.304649",
    "high": "0.0034735088186",
    "low": "0.00343687978043"
  },
  {
    "date": "2019-02-10",
    "id": "adcoin",
    "cap": "70768.7404977",
    "high": "0.0139760343654",
    "low": "0.0107010464486"
  },
  {
    "date": "2019-02-10",
    "id": "arcticcoin",
    "cap": "70543.8841812",
    "high": "0.00281753588762",
    "low": "0.00252051197678"
  },
  {
    "date": "2019-02-10",
    "id": "zozocoin",
    "cap": "69544.0250753",
    "high": "0.0461334651983",
    "low": "0.0352141668674"
  },
  {
    "date": "2019-02-10",
    "id": "arbitragect",
    "cap": "63194.8303506",
    "high": "0.000729496326586",
    "low": "0.000692777583889"
  },
  {
    "date": "2019-02-10",
    "id": "bitether",
    "cap": "63155.3661065",
    "high": "0.00122074046803",
    "low": "0.0011689033054"
  },
  {
    "date": "2019-02-10",
    "id": "bitcoin2network",
    "cap": "61763.4656777",
    "high": "0.0000653525558365",
    "low": "0.0000468095621122"
  },
  {
    "date": "2019-02-10",
    "id": "authorship",
    "cap": "61293.9316829",
    "high": "0.000613114494944",
    "low": "0.000613114494944"
  },
  {
    "date": "2019-02-10",
    "id": "kobocoin",
    "cap": "60465.0482303",
    "high": "0.00244795311378",
    "low": "0.00244795311378"
  },
  {
    "date": "2019-02-10",
    "id": "witchain",
    "cap": "52746.2539022",
    "high": "0.0000359263705767",
    "low": "0.0000297040700404"
  },
  {
    "date": "2019-02-10",
    "id": "arepacoin",
    "cap": "52252.7551113",
    "high": "0.00342458829326",
    "low": "0.00295392785486"
  },
  {
    "date": "2019-02-10",
    "id": "bitcoin-21",
    "cap": "52164.279831",
    "high": "0.0657720167319",
    "low": "0.0647073135598"
  },
  {
    "date": "2019-02-10",
    "id": "viuly",
    "cap": "52102.3513316",
    "high": "0.000152299984897",
    "low": "0.000109179944139"
  },
  {
    "date": "2019-02-10",
    "id": "block-chain-com",
    "cap": "51335.5873271",
    "high": "0.00511691884189",
    "low": "0.00466713864466"
  },
  {
    "date": "2019-02-10",
    "id": "4new",
    "cap": "51125.256267",
    "high": "0.00109023193081",
    "low": "0.000707107790788"
  },
  {
    "date": "2019-02-10",
    "id": "insanecoin-insn",
    "cap": "50724.7364683",
    "high": "0.00218253598829",
    "low": "0.00201672480906"
  },
  {
    "date": "2019-02-10",
    "id": "altcommunity-coin",
    "cap": "49327.58397",
    "high": "0.0382251357017",
    "low": "0.0364488634697"
  },
  {
    "date": "2019-02-10",
    "id": "bitcoin-w-spectrum",
    "cap": "48910.540121",
    "high": "0.000993474152662",
    "low": "0.000837802182122"
  },
  {
    "date": "2019-02-10",
    "id": "adultchain",
    "cap": "48010.1690539",
    "high": "0.000961795520264",
    "low": "0.000727866294261"
  },
  {
    "date": "2019-02-10",
    "id": "bitcoinote",
    "cap": "43439.1068662",
    "high": "0.00449505967042",
    "low": "0.00342546730551"
  },
  {
    "date": "2019-02-10",
    "id": "berncash",
    "cap": "34256.415705",
    "high": "0.000480897760132",
    "low": "0.000436719776557"
  },
  {
    "date": "2019-02-10",
    "id": "bitmoney",
    "cap": "29298.7598041",
    "high": "0.000360954266832",
    "low": "0.000346698565288"
  },
  {
    "date": "2019-02-10",
    "id": "aced",
    "cap": "29234.5677203",
    "high": "0.0137403811128",
    "low": "0.00999496277817"
  },
  {
    "date": "2019-02-10",
    "id": "atheios",
    "cap": "27768.1715425",
    "high": "0.00234969464311",
    "low": "0.00218948187777"
  },
  {
    "date": "2019-02-10",
    "id": "atomic-coin",
    "cap": "27455.3369429",
    "high": "0.00219747600693",
    "low": "0.00146321459397"
  },
  {
    "date": "2019-02-10",
    "id": "joincoin",
    "cap": "24368.5413807",
    "high": "0.00917876607265",
    "low": "0.00492447918961"
  },
  {
    "date": "2019-02-10",
    "id": "bionic",
    "cap": "23008.3602415",
    "high": "0.0000432016454464",
    "low": "0.0000306054842114"
  },
  {
    "date": "2019-02-10",
    "id": "amsterdamcoin",
    "cap": "22284.8996412",
    "high": "0.000443905624737",
    "low": "0.000436742772742"
  },
  {
    "date": "2019-02-10",
    "id": "bitcoin-adult",
    "cap": "21071.8526694",
    "high": "0.00105959333189",
    "low": "0.000655187608551"
  },
  {
    "date": "2019-02-10",
    "id": "thunderstake",
    "cap": "19649.4623474",
    "high": "0.0000736445018837",
    "low": "0.0000363933147131"
  },
  {
    "date": "2019-02-10",
    "id": "boostcoin",
    "cap": "19493.6769576",
    "high": "0.0016570073513",
    "low": "0.00163778539778"
  },
  {
    "date": "2019-02-10",
    "id": "tajcoin",
    "cap": "16187.4313684",
    "high": "0.00143607303779",
    "low": "0.00141941401141"
  },
  {
    "date": "2019-02-10",
    "id": "bigup",
    "cap": "16155.8488865",
    "high": "0.00000756009682955",
    "low": "0.00000403456987288"
  },
  {
    "date": "2019-02-10",
    "id": "bitball",
    "cap": "16111.8224619",
    "high": "0.000110296253266",
    "low": "0.0000364225964904"
  },
  {
    "date": "2019-02-10",
    "id": "bitcoin-planet",
    "cap": "11674.4493605",
    "high": "0.00224616552065",
    "low": "0.00152989963692"
  },
  {
    "date": "2019-02-10",
    "id": "ammo-reloaded",
    "cap": "10728.6920797",
    "high": "0.000137940328119",
    "low": "0.000137940328119"
  },
  {
    "date": "2019-02-10",
    "id": "bankcoin",
    "cap": "10614.7005528",
    "high": "0.0010429516751",
    "low": "0.000528957535752"
  },
  {
    "date": "2019-02-10",
    "id": "acoin",
    "cap": "6997.59462458",
    "high": "0.00573533390966",
    "low": "0.00573533390966"
  },
  {
    "date": "2019-02-10",
    "id": "playercoin",
    "cap": "6884.96369347",
    "high": "0.00019604110742",
    "low": "0.00019604110742"
  },
  {
    "date": "2019-02-10",
    "id": "bitcoal",
    "cap": "6658.58437105",
    "high": "0.00147968541579",
    "low": "0.00116577154315"
  },
  {
    "date": "2019-02-10",
    "id": "bumbacoin",
    "cap": "6430.08231271",
    "high": "0.000275547389727",
    "low": "0.00026392770642"
  },
  {
    "date": "2019-02-10",
    "id": "iconic",
    "cap": "5460.72764723",
    "high": "0.00921030062047",
    "low": "0.00921030062047"
  },
  {
    "date": "2019-02-10",
    "id": "bitcoin-x",
    "cap": "3969.15419023",
    "high": "0.00164249866484",
    "low": "0.00136429235612"
  },
  {
    "date": "2019-02-10",
    "id": "bitcoin-one",
    "cap": "3699.21353948",
    "high": "0.000475291068174",
    "low": "0.000365282282939"
  },
  {
    "date": "2019-02-10",
    "id": "arbit",
    "cap": "3187.23498718",
    "high": "0.000438255302538",
    "low": "0.000291161848495"
  },
  {
    "date": "2019-02-10",
    "id": "abulaba",
    "cap": "2783.48149977",
    "high": "0.000218735050745",
    "low": "0.0000853607800922"
  },
  {
    "date": "2019-02-10",
    "id": "anarchistsprime",
    "cap": "2763.78803373",
    "high": "0.000682498705001",
    "low": "0.000618686350122"
  },
  {
    "date": "2019-02-10",
    "id": "acre",
    "cap": "2430.31885966",
    "high": "0.000554882030922",
    "low": "0.000545899720696"
  },
  {
    "date": "2019-02-10",
    "id": "alpha-coin",
    "cap": "2285.30568949",
    "high": "0.000258944947763",
    "low": "0.000182466903053"
  },
  {
    "date": "2019-02-10",
    "id": "benjirolls",
    "cap": "2250.16861471",
    "high": "0.000110976406184",
    "low": "0.000109179944139"
  },
  {
    "date": "2019-02-10",
    "id": "benz",
    "cap": "1002.80642372",
    "high": "0.0001991302296",
    "low": "0.000159539692476"
  },
  {
    "date": "2019-02-10",
    "id": "argus",
    "cap": "462.374722314",
    "high": "0.000405046241429",
    "low": "0.00040034754168"
  },
  {
    "date": "2019-02-10",
    "id": "bolenum",
    "cap": "112.407343054",
    "high": "0.0000112565546826",
    "low": "0.00000846353339255"
  },
  {
    "date": "2019-02-10",
    "id": "cjs",
    "cap": "96.3157971943",
    "high": "0.0570168669966",
    "low": "0.0544514731875"
  },
  {
    "date": "2019-02-10",
    "id": "abcc-token",
    "cap": "-1",
    "high": "0.077670173552",
    "low": "0.0753438842567"
  },
  {
    "date": "2019-02-10",
    "id": "acchain",
    "cap": "-1",
    "high": "0.0205676272795",
    "low": "0.0202165309164"
  },
  {
    "date": "2019-02-10",
    "id": "aces",
    "cap": "-1",
    "high": "0.0000368223855845",
    "low": "0.000036596883934"
  },
  {
    "date": "2019-02-10",
    "id": "aencoin",
    "cap": "-1",
    "high": "0.0152954375307",
    "low": "0.0114346978793"
  },
  {
    "date": "2019-02-10",
    "id": "albos",
    "cap": "-1",
    "high": "0.00033810832901",
    "low": "0.00030798320109"
  },
  {
    "date": "2019-02-10",
    "id": "alchemint-standards",
    "cap": "-1",
    "high": "0.00342675910772",
    "low": "0.00266790164047"
  },
  {
    "date": "2019-02-10",
    "id": "allcoin",
    "cap": "-1",
    "high": "0.010428239706",
    "low": "0.00916649838475"
  },
  {
    "date": "2019-02-10",
    "id": "almeela",
    "cap": "-1",
    "high": "0.238403960656",
    "low": "0.185244139218"
  },
  {
    "date": "2019-02-10",
    "id": "alttex",
    "cap": "-1",
    "high": "0.000516206257989",
    "low": "0.000263466049488"
  },
  {
    "date": "2019-02-10",
    "id": "amoveo",
    "cap": "-1",
    "high": "81.2630008036",
    "low": "73.1934889395"
  },
  {
    "date": "2019-02-10",
    "id": "anon",
    "cap": "-1",
    "high": "0.184997669109",
    "low": "0.18200296688"
  },
  {
    "date": "2019-02-10",
    "id": "apot",
    "cap": "-1",
    "high": "0.0121715279263",
    "low": "0.0104189473551"
  },
  {
    "date": "2019-02-10",
    "id": "asura-coin",
    "cap": "-1",
    "high": "0.000641039322387",
    "low": "0.00048437995762"
  },
  {
    "date": "2019-02-10",
    "id": "atlantis-blue-digital-token",
    "cap": "-1",
    "high": "0.00429301778263",
    "low": "0.00322664878973"
  },
  {
    "date": "2019-02-10",
    "id": "atlas-protocol",
    "cap": "-1",
    "high": "0.0186077595214",
    "low": "0.0179845503433"
  },
  {
    "date": "2019-02-10",
    "id": "atomic-wallet-coin",
    "cap": "-1",
    "high": "0.0287303252274",
    "low": "0.0245907188833"
  },
  {
    "date": "2019-02-10",
    "id": "avatarcoin",
    "cap": "-1",
    "high": "0.0292977712327",
    "low": "0.0269642243491"
  },
  {
    "date": "2019-02-10",
    "id": "axiom",
    "cap": "-1",
    "high": "0.00390317287195",
    "low": "0.00385789449255"
  },
  {
    "date": "2019-02-10",
    "id": "baer-chain",
    "cap": "-1",
    "high": "0.51726591197",
    "low": "0.50427202661"
  },
  {
    "date": "2019-02-10",
    "id": "bankera",
    "cap": "-1",
    "high": "0.00220827467323",
    "low": "0.00213358297735"
  },
  {
    "date": "2019-02-10",
    "id": "bastonet",
    "cap": "-1",
    "high": "0.00000197612534557",
    "low": "0.00000196896924852"
  },
  {
    "date": "2019-02-10",
    "id": "beekan",
    "cap": "-1",
    "high": "0.000597244274622",
    "low": "0.000468176615197"
  },
  {
    "date": "2019-02-10",
    "id": "betacoin",
    "cap": "-1",
    "high": "0.0013231573776",
    "low": "0.0013231573776"
  },
  {
    "date": "2019-02-10",
    "id": "bgogo-token",
    "cap": "-1",
    "high": "0.000929781403834",
    "low": "0.000840272239761"
  },
  {
    "date": "2019-02-10",
    "id": "bidooh-dooh-token",
    "cap": "-1",
    "high": "0.0000842778899435",
    "low": "0.0000700301451353"
  },
  {
    "date": "2019-02-10",
    "id": "bingocoin",
    "cap": "-1",
    "high": "0.0118293991263",
    "low": "0.0101839240001"
  },
  {
    "date": "2019-02-10",
    "id": "birds",
    "cap": "-1",
    "high": "0.000147289003767",
    "low": "0.000146391849306"
  },
  {
    "date": "2019-02-10",
    "id": "bitcoin-file",
    "cap": "-1",
    "high": "0.00136827371151",
    "low": "0.00103444710372"
  },
  {
    "date": "2019-02-10",
    "id": "bitcoin-god",
    "cap": "-1",
    "high": "6.5489794011",
    "low": "5.86912733386"
  },
  {
    "date": "2019-02-10",
    "id": "bitcoinx",
    "cap": "-1",
    "high": "0.00219954300985",
    "low": "0.0014674356845"
  },
  {
    "date": "2019-02-10",
    "id": "bitmax-token",
    "cap": "-1",
    "high": "0.0186381871133",
    "low": "0.0180241078093"
  },
  {
    "date": "2019-02-10",
    "id": "coni",
    "cap": "-1",
    "high": "0.00848779799004",
    "low": "0.00764821613621"
  },
  {
    "date": "2019-02-10",
    "id": "lightning-bitcoin",
    "cap": "-1",
    "high": "1.65888850534",
    "low": "1.38179863565"
  },
  {
    "date": "2019-02-10",
    "id": "sexcoin",
    "cap": "-1",
    "high": "0.00761701228781",
    "low": "0.00666349044367"
  },
  {
    "date": "2019-02-10",
    "id": "nos",
    "cap": "-1",
    "high": "0.0430547499819",
    "low": "0.0356750390524"
  },
  {
    "date": "2019-02-10",
    "id": "superedge",
    "cap": "-1",
    "high": "0.0000307579765784",
    "low": "0.0000299960493528"
  },
  {
    "date": "2019-02-10",
    "id": "maggie",
    "cap": "-1",
    "high": "0.00105190837564",
    "low": "0.000226518357248"
  },
  {
    "date": "2019-02-10",
    "id": "livepeer",
    "cap": "-1",
    "high": "4.77848817474",
    "low": "4.17864225578"
  },
  {
    "date": "2019-02-10",
    "id": "abbc-coin",
    "cap": "-1",
    "high": "0.0632182761021",
    "low": "0.053576882094"
  },
  {
    "date": "2019-02-10",
    "id": "content-and-ad-network",
    "cap": "-1",
    "high": "0.00179985436399",
    "low": "0.00117514037342"
  },
  {
    "date": "2019-02-10",
    "id": "emaratcoin",
    "cap": "-1",
    "high": "0.0307913984475",
    "low": "0.0307913984475"
  },
  {
    "date": "2019-02-10",
    "id": "molecular-future",
    "cap": "-1",
    "high": "0.0314050297869",
    "low": "0.0302580277194"
  },
  {
    "date": "2019-02-10",
    "id": "karatgold-coin",
    "cap": "-1",
    "high": "0.0293110260903",
    "low": "0.028360677709"
  },
  {
    "date": "2019-02-10",
    "id": "ipchain",
    "cap": "-1",
    "high": "0.0871292724457",
    "low": "0.0805784846631"
  },
  {
    "date": "2019-02-10",
    "id": "stronghands-masternode",
    "cap": "-1",
    "high": "0.312213622732",
    "low": "0.290316669196"
  },
  {
    "date": "2019-02-10",
    "id": "futurocoin",
    "cap": "-1",
    "high": "4.39670219739",
    "low": "4.21862830868"
  },
  {
    "date": "2019-02-10",
    "id": "contractnet",
    "cap": "-1",
    "high": "0.000982606250413",
    "low": "0.000782456266331"
  },
  {
    "date": "2019-02-10",
    "id": "oceanchain",
    "cap": "-1",
    "high": "0.000328612045353",
    "low": "0.000322440858653"
  },
  {
    "date": "2019-02-10",
    "id": "read",
    "cap": "-1",
    "high": "0.00322279091191",
    "low": "0.00242404622621"
  },
  {
    "date": "2019-02-10",
    "id": "fundtoken",
    "cap": "-1",
    "high": "0.00540411581218",
    "low": "0.00441974828444"
  },
  {
    "date": "2019-02-10",
    "id": "davinci-coin",
    "cap": "-1",
    "high": "0.00778507805836",
    "low": "0.00737830309941"
  },
  {
    "date": "2019-02-10",
    "id": "agrolot",
    "cap": "-1",
    "high": "0.019000281486",
    "low": "0.0185928682016"
  },
  {
    "date": "2019-02-10",
    "id": "darkpaycoin",
    "cap": "-1",
    "high": "0.019876089137",
    "low": "0.0178804554456"
  },
  {
    "date": "2019-02-10",
    "id": "encryptotel-eth",
    "cap": "-1",
    "high": "0.0134601396398",
    "low": "0.00768167645922"
  },
  {
    "date": "2019-02-10",
    "id": "clubcoin",
    "cap": "-1",
    "high": "0.349995773935",
    "low": "0.325359693343"
  },
  {
    "date": "2019-02-10",
    "id": "hitchain",
    "cap": "-1",
    "high": "0.0000903921421172",
    "low": "0.0000846611301923"
  },
  {
    "date": "2019-02-10",
    "id": "filecoin",
    "cap": "-1",
    "high": "3.06599340644",
    "low": "2.74335697221"
  },
  {
    "date": "2019-02-10",
    "id": "ors-group",
    "cap": "-1",
    "high": "0.0457526334963",
    "low": "0.0440894960716"
  },
  {
    "date": "2019-02-10",
    "id": "esports-token",
    "cap": "-1",
    "high": "0.00176387859068",
    "low": "0.00164545519166"
  },
  {
    "date": "2019-02-10",
    "id": "aidos-kuneen",
    "cap": "-1",
    "high": "5.94772465507",
    "low": "2.36967030182"
  },
  {
    "date": "2019-02-10",
    "id": "snapcoin",
    "cap": "-1",
    "high": "0.0176795832868",
    "low": "0.0135103024384"
  },
  {
    "date": "2019-02-10",
    "id": "snipcoin",
    "cap": "-1",
    "high": "0.000652053468205",
    "low": "0.00036113617586"
  },
  {
    "date": "2019-02-10",
    "id": "palletone",
    "cap": "-1",
    "high": "0.00624102651209",
    "low": "0.00573850319372"
  },
  {
    "date": "2019-02-10",
    "id": "animation-vision-cash",
    "cap": "-1",
    "high": "0.000443905624737",
    "low": "0.000401895432876"
  }
]